Workbook

Sheet China BEVs penetration rate
B1: BEV Sales | C1: BEV Cumulative | D1: PHEV Sales | E1: PHEV (Cumulative) | F1: NEV Sale | G1: NEV Cumulative | H1: PVS | I1: PVS Cumulative | J1: NEV/Total | K1: BEV/Total | L1: BEV (Cum)/PVS(Cum) | M1: NEV(Cum)/PVS(Cum)
A3: 41275 | H3: 1725500 | I3: =SUM($H$3:H3) -> 1725500
A4: 41306 | H4: 1111900 | I4: =SUM($H$3:H4) -> 2837400
A5: 41334 | H5: 1585500 | I5: =SUM($H$3:H5) -> 4422900
A6: 41365 | H6: 1441400 | I6: =SUM($H$3:H6) -> 5864300
A7: 41395 | H7: 1396900 | I7: =SUM($H$3:H7) -> 7261200
A8: 41426 | H8: 1403500 | I8: =SUM($H$3:H8) -> 8664700
A9: 41456 | H9: 1237600 | I9: =SUM($H$3:H9) -> 9902300
A10: 41487 | H10: 1353200 | I10: =SUM($H$3:H10) -> 11255500
A11: 41518 | H11: 1593500 | I11: =SUM($H$3:H11) -> 12849000
A12: 41548 | H12: 1605700 | I12: =SUM($H$3:H12) -> 14454700
A13: 41579 | H13: 1696300 | I13: =SUM($H$3:H13) -> 16151000
A14: 41609 | H14: 1462900 | I14: =SUM($H$3:H14) -> 17613900
A15: 2013 | C15: 14604 | E15: 3290 | F15: =SUM(C15+E15) -> 17894 | G15: =SUM($F15:F$17) -> 17894 | H15: =C15/G15 -> 0.81613949 | I15: 17613900 | L15: =C15/I15 -> 0.00082911791 | M15: =G15/I15 -> 0.0010159022
H16: =C16/G16 -> #DIV/0!
A17: 41640 | H17: =C17/G17 -> #DIV/0! | I17: =SUM($H$17:H17) -> #DIV/0!
A18: 41671 | H18: =C18/G18 -> #DIV/0! | I18: =SUM($H$17:H18) -> #DIV/0!
A19: 41699 | H19: =C19/G19 -> #DIV/0! | I19: =SUM($H$17:H19) -> #DIV/0!
A20: 41730 | H20: =C20/G20 -> #DIV/0! | I20: =SUM($H$17:H20) -> #DIV/0!
A21: 41760 | H21: =C21/G21 -> #DIV/0! | I21: =SUM($H$17:H21) -> #DIV/0!
A22: 41791 | H22: =C22/G22 -> #DIV/0! | I22: =SUM($H$17:H22) -> #DIV/0!
A23: 41821 | H23: =C23/G23 -> #DIV/0! | I23: =SUM($H$17:H23) -> #DIV/0!
A24: 41852 | H24: =C24/G24 -> #DIV/0! | I24: =SUM($H$17:H24) -> #DIV/0!
A25: 41883 | H25: =C25/G25 -> #DIV/0! | I25: =SUM($H$17:H25) -> #DIV/0!
A26: 41913 | H26: =C26/G26 -> #DIV/0! | I26: =SUM($H$17:H26) -> #DIV/0!
A27: 41944 | H27: =C27/G27 -> #DIV/0! | I27: =SUM($H$17:H27) -> #DIV/0!
A28: 41974 | H28: =C28/G28 -> #DIV/0! | I28: =SUM($H$17:H28) -> #DIV/0! | L28: =C31/I28 -> #DIV/0! | M28: =G31/I28 -> #DIV/0!
H29: =C29/G29 -> #DIV/0!
H30: =C30/G30 -> #DIV/0!
A31: 2014 | C31: 21732 | E31: 16129 | F31: =SUM(C31+E31) -> 37861 | G31: =SUM($F$17:F31) -> 37861 | H31: =C31/G31 -> 0.57399435 | I31: 19604338 | L31: =C31/I31 -> 0.0011085302 | M31: =G31/I31 -> 0.0019312562
H32: =C32/G32 -> #DIV/0!
A33: 42005 | H33: =C33/G33 -> #DIV/0! | I33: =SUM($H$33:H33) -> #DIV/0!
A34: 42036 | H34: =C34/G34 -> #DIV/0! | I34: =SUM($H$33:H34) -> #DIV/0!
A35: 42064 | H35: =C35/G35 -> #DIV/0! | I35: =SUM($H$33:H35) -> #DIV/0!
A36: 42095 | H36: =C36/G36 -> #DIV/0! | I36: =SUM($H$33:H36) -> #DIV/0!
A37: 42125 | H37: =C37/G37 -> #DIV/0! | I37: =SUM($H$33:H37) -> #DIV/0!
A38: 42156 | H38: =C38/G38 -> #DIV/0! | I38: =SUM($H$33:H38) -> #DIV/0!
A39: 42186 | H39: =C39/G39 -> #DIV/0! | I39: =SUM($H$33:H39) -> #DIV/0!
A40: 42217 | H40: =C40/G40 -> #DIV/0! | I40: =SUM($H$33:H40) -> #DIV/0!
A41: 42248 | H41: =C41/G41 -> #DIV/0! | I41: =SUM($H$33:H41) -> #DIV/0!
A42: 42278 | H42: =C42/G42 -> #DIV/0! | I42: =SUM($H$33:H42) -> #DIV/0!
A43: 42309 | H43: =C43/G43 -> #DIV/0! | I43: =SUM($H$33:H43) -> #DIV/0!
A44: 42339 | H44: =C44/G44 -> #DIV/0! | I44: =SUM($H$33:H44) -> #DIV/0! | L44: =C46/I44 -> #DIV/0! | M44: =F46/I44 -> #DIV/0!
H45: =C45/G45 -> #DIV/0!
A46: 2015 | C46: 52243 | E46: 59649 | F46: =SUM(C46,E46) -> 111892 | G46: =SUM($F$33:F46) -> 111892 | H46: =C46/G46 -> 0.46690559 | I46: 21060871 | L46: =C46/I46 -> 0.0024805717 | M46: =G46/I46 -> 0.0053127907
A48: 2016
A49: 42370 | B49: 4538 | C49: =SUM($B$49:B49) -> 4538 | D49: 5353 | E49: =SUM($D$49:D49) -> 5353 | F49: 10000 | G49: =SUM(F$49:F49) -> 10000 | H49: 2178077 | I49: =SUM($H$49:H49) -> 2178077 | J49: =F49/H49 -> 0.0045912059 | K49: =B49/H49 -> 0.0020834892 | L49: =C49/I49 -> 0.0020834892
A50: 42401 | B50: 3307 | C50: =SUM($B$49:B50) -> 7845 | D50: 3589 | E50: =SUM($D$49:D50) -> 8942 | F50: 7000 | G50: =SUM(F$49:F50) -> 17000 | H50: 1376700 | I50: =SUM($H$49:H50) -> 3554777 | J50: =F50/H50 -> 0.0050846226 | K50: =B50/H50 -> 0.002402121 | L50: =C50/I50 -> 0.0022068895
A51: 42430 | B51: 6398 | C51: =SUM($B$49:B51) -> 14243 | D51: 4834 | E51: =SUM($D$49:D51) -> 13776 | F51: 11400 | G51: =SUM(F$49:F51) -> 28400 | H51: 2056000 | I51: =SUM($H$49:H51) -> 5610777 | J51: =F51/H51 -> 0.0055447471 | K51: =B51/H51 -> 0.0031118677 | L51: =C51/I51 -> 0.0025385076
A52: 42461 | B52: 6664 | C52: =SUM($B$49:B52) -> 20907 | D52: 6500 | E52: =SUM($D$49:D52) -> 20276 | F52: 13500 | G52: =SUM(F$49:F52) -> 41900 | H52: 1779000 | I52: =SUM($H$49:H52) -> 7389777 | J52: =F52/H52 -> 0.0075885329 | K52: =B52/H52 -> 0.0037459247 | L52: =C52/I52 -> 0.0028291787
A53: 42491 | B53: 7872 | C53: =SUM($B$49:B53) -> 28779 | D53: 8114 | E53: =SUM($D$49:D53) -> 28390 | F53: 16600 | G53: =SUM(F$49:F53) -> 58500 | H53: 1793000 | I53: =SUM($H$49:H53) -> 9182777 | J53: =F53/H53 -> 0.0092582264 | K53: =B53/H53 -> 0.0043904071 | L53: =C53/I53 -> 0.0031340193
A54: 42522 | B54: 10150 | C54: =SUM($B$49:B54) -> 38929 | D54: 9730 | E54: =SUM($D$49:D54) -> 38120 | F54: 20000 | G54: =SUM(F$49:F54) -> 78500 | H54: 1784100 | I54: =SUM($H$49:H54) -> 10966877 | J54: =F54/H54 -> 0.011210134 | K54: =B54/H54 -> 0.005689143 | L54: =C54/I54 -> 0.0035496888
A55: 42552 | B55: 15683 | C55: =SUM($B$49:B55) -> 54612 | D55: 8423 | E55: =SUM($D$49:D55) -> 46543 | F55: 24500 | G55: =SUM(F$49:F55) -> 103000 | H55: 1609178 | I55: =SUM($H$49:H55) -> 12576055 | J55: =F55/H55 -> 0.015225165 | K55: =B55/H55 -> 0.0097459697 | L55: =C55/I55 -> 0.0043425383
A56: 42583 | B56: 14428 | C56: =SUM($B$49:B56) -> 69040 | D56: 7884 | E56: =SUM($D$49:D56) -> 54427 | F56: 22600 | G56: =SUM(F$49:F56) -> 125600 | H56: 1795500 | I56: =SUM($H$49:H56) -> 14371555 | J56: =F56/H56 -> 0.012587023 | K56: =B56/H56 -> 0.0080356447 | L56: =C56/I56 -> 0.0048039339
A57: 42614 | B57: 18545 | C57: =SUM($B$49:B57) -> 87585 | D57: 7119 | E57: =SUM($D$49:D57) -> 61546 | F57: 25700 | G57: =SUM(F$49:F57) -> 151300 | H57: 2268300 | I57: =SUM($H$49:H57) -> 16639855 | J57: =F57/H57 -> 0.011330071 | K57: =B57/H57 -> 0.0081757263 | L57: =C57/I57 -> 0.0052635675
A58: 42644 | B58: 21606 | C58: =SUM($B$49:B58) -> 109191 | D58: 3517 | E58: =SUM($D$49:D58) -> 65063 | F58: 25500 | G58: =SUM(F$49:F58) -> 176800 | H58: 2305000 | I58: =SUM($H$49:H58) -> 18944855 | J58: =F58/H58 -> 0.011062907 | K58: =B58/H58 -> 0.0093735358 | L58: =C58/I58 -> 0.0057636229
A59: 42675 | B59: 25872 | C59: =SUM($B$49:B59) -> 135063 | D59: 3663 | E59: =SUM($D$49:D59) -> 68726 | F59: 29800 | G59: =SUM(F$49:F59) -> 206600 | H59: 2542000 | I59: =SUM($H$49:H59) -> 21486855 | J59: =F59/H59 -> 0.011723053 | K59: =B59/H59 -> 0.010177813 | L59: =C59/I59 -> 0.0062858431
A60: 42705 | B60: 32509 | C60: =SUM($B$49:B60) -> 167572 | D60: 3380 | E60: =SUM($D$49:D60) -> 72106 | F60: 36300 | G60: =SUM(F$49:F60) -> 242900 | H60: 2672300 | I60: =SUM($H$49:H60) -> 24159155 | J60: =F60/H60 -> 0.013583804 | K60: =B60/H60 -> 0.012165176 | L60: =C60/I60 -> 0.0069361697 | M60: =G60/I60 -> 0.01005416
G61: =C60/G60 -> 0.68988061
A62: 2017
A63: 42736 | B63: 1379 | C63: =SUM($B$63:B63) -> 1379 | D63: 2398 | E63: =SUM($D$63:D63) -> 2398 | F63: 2941 | G63: =SUM($F$63:F63) -> 2941 | H63: 2218200 | I63: =SUM($H$63:H63) -> 2218200 | J63: =F63/H63 -> 0.0013258498 | K63: =B63/H63 -> 0.00062167523 | L63: =C63/I63 -> 0.00062167523
A64: 42767 | B64: 2999 | C64: =SUM($B$63:B64) -> 4378 | D64: 1548 | E64: =SUM($D$63:D64) -> 3946 | F64: 4213 | G64: =SUM($F$63:F64) -> 7154 | H64: 1632700 | I64: =SUM($H$63:H64) -> 3850900 | J64: =F64/H64 -> 0.0025803883 | K64: =B64/H64 -> 0.0018368347 | L64: =C64/I64 -> 0.0011368771
A65: 42795 | B65: 13817 | C65: =SUM($B$63:B65) -> 18195 | D65: 3809 | E65: =SUM($D$63:D65) -> 7755 | F65: 17140 | G65: =SUM($F$63:F65) -> 24294 | H65: 2170764 | I65: =SUM($H$63:H65) -> 6021664 | J65: =F65/H65 -> 0.0078958376 | K65: =B65/H65 -> 0.0063650401 | L65: =C65/I65 -> 0.00302159
A66: 42826 | B66: 13007 | C66: =SUM($B$63:B66) -> 31202 | D66: 4216 | E66: =SUM($D$63:D66) -> 11971 | F66: 16832 | G66: =SUM($F$63:F66) -> 41126 | H66: 1722000 | I66: =SUM($H$63:H66) -> 7743664 | J66: =F66/H66 -> 0.0097746806 | K66: =B66/H66 -> 0.0075534262 | L66: =C66/I66 -> 0.0040293587
A67: 42856 | B67: 19852 | C67: =SUM($B$63:B67) -> 51054 | D67: 5061 | E67: =SUM($D$63:D67) -> 17032 | F67: 25143 | G67: =SUM($F$63:F67) -> 66269 | H67: 1751300 | I67: =SUM($H$63:H67) -> 9494964 | J67: =F67/H67 -> 0.014356764 | K67: =B67/H67 -> 0.011335579 | L67: =C67/I67 -> 0.0053769556
A68: 42887 | B68: 24233 | C68: =SUM($B$63:B68) -> 75287 | D68: 6002 | E68: =SUM($D$63:D68) -> 23034 | F68: 30235 | G68: =SUM($F$63:F68) -> 96504 | H68: 1831800 | I68: =SUM($H$63:H68) -> 11326764 | J68: =F68/H68 -> 0.016505623 | K68: =B68/H68 -> 0.013229064 | L68: =C68/I68 -> 0.0066468234
A69: 42917 | B69: 26308 | C69: =SUM($B$63:B69) -> 101595 | D69: 7613 | E69: =SUM($D$63:D69) -> 30647 | F69: 33921 | G69: =SUM($F$63:F69) -> 130425 | H69: 1678400 | I69: =SUM($H$63:H69) -> 13005164 | J69: =F69/H69 -> 0.020210319 | K69: =B69/H69 -> 0.015674452 | L69: =C69/I69 -> 0.0078118969
A70: 42948 | B70: 30876 | C70: =SUM($B$63:B70) -> 132471 | D70: 8010 | E70: =SUM($D$63:D70) -> 38657 | F70: 38886 | G70: =SUM($F$63:F70) -> 169311 | H70: 1875200 | I70: =SUM($H$63:H70) -> 14880364 | J70: =F70/H70 -> 0.020736988 | K70: =B70/H70 -> 0.016465444 | L70: =C70/I70 -> 0.0089024032
A71: 42979 | B71: 33029 | C71: =SUM($B$63:B71) -> 165500 | D71: 9980 | E71: =SUM($D$63:D71) -> 48637 | F71: 43009 | G71: =SUM($F$63:F71) -> 212320 | H71: 2342600 | I71: =SUM($H$63:H71) -> 17222964 | J71: =F71/H71 -> 0.018359515 | K71: =B71/H71 -> 0.014099291 | L71: =C71/I71 -> 0.0096092635
A72: 43009 | B72: 37689 | C72: =SUM($B$63:B72) -> 203189 | D72: 9985 | E72: =SUM($D$63:D72) -> 58622 | F72: 47674 | G72: =SUM($F$63:F72) -> 259994 | H72: 2352500 | I72: =SUM($H$63:H72) -> 19575464 | J72: =F72/H72 -> 0.02026525 | K72: =B72/H72 -> 0.016020829 | L72: =C72/I72 -> 0.01037978
A73: 43040 | B73: 81303 | C73: =SUM($B$63:B73) -> 284492 | D73: 16719 | E73: =SUM($D$63:D73) -> 75341 | F73: 98022 | G73: =SUM($F$63:F73) -> 358016 | H73: 2589500 | I73: =SUM($H$63:H73) -> 22164964 | J73: =F73/H73 -> 0.03785364 | K73: =B73/H73 -> 0.031397181 | L73: =C73/I73 -> 0.012835211
A74: 43070 | B74: 171605 | C74: =SUM($B$63:B74) -> 456097 | D74: 24527 | E74: =SUM($D$63:D74) -> 99868 | F74: 196132 | G74: =SUM($F$63:F74) -> 554148 | H74: 2653300 | I74: =SUM($H$63:H74) -> 24818264 | J74: =F74/H74 -> 0.073920024 | K74: =B74/H74 -> 0.064676064 | L74: =C74/I74 -> 0.018377474 | M74: =G74/I74 -> 0.022328234
G75: =C74/G74 -> 0.8230599
A77: 2018
A78: 43101 | B78: 10835 | C78: =SUM($B$78:B78) -> 10835 | D78: 11149 | E78: =SUM($D$78:D78) -> 11149 | F78: 23231 | G78: =SUM($F$78:F78) -> 23231 | H78: 2248895 | I78: =SUM($H$78:H78) -> 2248895 | J78: =F78/H78 -> 0.010329962 | K78: =B78/H78 -> 0.0048179217 | L78: =C78/I78 -> 0.0048179217
A79: 43132 | B79: 8914 | C79: =SUM($B$78:B79) -> 19749 | D79: 5777 | E79: =SUM($D$78:D79) -> 16926 | F79: 15439 | G79: =SUM($F$78:F79) -> 38670 | H79: 1455500 | I79: =SUM($H$78:H79) -> 3704395 | J79: =F79/H79 -> 0.010607351 | K79: =B79/H79 -> 0.0061243559 | L79: =C79/I79 -> 0.0053312349
A80: 43160 | B80: 25115 | C80: =SUM($B$78:B80) -> 44864 | D80: 10031 | E80: =SUM($D$78:D80) -> 26957 | F80: 36132 | G80: =SUM($F$78:F80) -> 74802 | H80: 2168600 | I80: =SUM($H$78:H80) -> 5872995 | J80: =F80/H80 -> 0.016661441 | K80: =B80/H80 -> 0.011581204 | L80: =C80/I80 -> 0.0076390326
A81: 43191 | B81: 35042 | C81: =SUM($B$78:B81) -> 79906 | D81: 15002 | E81: =SUM($D$78:D81) -> 41959 | F81: 51101 | G81: =SUM($F$78:F81) -> 125903 | H81: 1914400 | I81: =SUM($H$78:H81) -> 7787395 | J81: =F81/H81 -> 0.026692959 | K81: =B81/H81 -> 0.01830443 | L81: =C81/I81 -> 0.010260941
A82: 43221 | B82: 79981 | C82: =SUM($B$78:B82) -> 159887 | D82: 20011 | E82: =SUM($D$78:D82) -> 61970 | F82: 100665 | G82: =SUM($F$78:F82) -> 226568 | H82: 1889400 | I82: =SUM($H$78:H82) -> 9676795 | J82: =F82/H82 -> 0.053278819 | K82: =B82/H82 -> 0.042331428 | L82: =C82/I82 -> 0.016522723
A83: 43252 | B83: 42606 | C83: =SUM($B$78:B83) -> 202493 | D83: 20465 | E83: =SUM($D$78:D83) -> 82435 | F83: 63784 | G83: =SUM($F$78:F83) -> 290352 | H83: 1715989 | I83: =SUM($H$78:H83) -> 11392784 | J83: =F83/H83 -> 0.037170401 | K83: =B83/H83 -> 0.02482883 | L83: =C83/I83 -> 0.017773794
A84: 43282 | B84: 31265 | C84: =SUM($B$78:B84) -> 233758 | D84: 19069 | E84: =SUM($D$78:D84) -> 101504 | F84: 50334 | G84: =SUM($F$78:F84) -> 340686 | H84: 1589500 | I84: =SUM($H$78:H84) -> 12982284 | J84: =F84/H84 -> 0.031666562 | K84: =B84/H84 -> 0.019669707 | L84: =C84/I84 -> 0.018005923
A85: 43313 | B85: 43676 | C85: =SUM($B$78:B85) -> 277434 | D85: 23092 | E85: =SUM($D$78:D85) -> 124596 | F85: 66768 | G85: =SUM($F$78:F85) -> 407454 | H85: 1789900 | I85: =SUM($H$78:H85) -> 14772184 | J85: =F85/H85 -> 0.037302643 | K85: =B85/H85 -> 0.024401363 | L85: =C85/I85 -> 0.018780838
A86: 43344 | B86: 49934 | C86: =SUM($B$78:B86) -> 327368 | D86: 22126 | E86: =SUM($D$78:D86) -> 146722 | F86: 72060 | G86: =SUM($F$78:F86) -> 479514 | H86: 2060500 | I86: =SUM($H$78:H86) -> 16832684 | J86: =F86/H86 -> 0.034972094 | K86: =B86/H86 -> 0.024233924 | L86: =C86/I86 -> 0.019448354
A87: 43374 | B87: 55862 | C87: =SUM($B$78:B87) -> 383230 | D87: 22351 | E87: =SUM($D$78:D87) -> 169073 | F87: 78213 | G87: =SUM($F$78:F87) -> 557727 | H87: 2046800 | I87: =SUM($H$78:H87) -> 18879484 | J87: =F87/H87 -> 0.038212331 | K87: =B87/H87 -> 0.027292359 | L87: =C87/I87 -> 0.020298754
A88: 43405 | B88: 99357 | C88: =SUM($B$78:B88) -> 482587 | D88: 27750 | E88: =SUM($D$78:D88) -> 196823 | F88: 127107 | G88: =SUM($F$78:F88) -> 684834 | H88: 2173500 | I88: =SUM($H$78:H88) -> 21052984 | J88: =F88/H88 -> 0.058480331 | K88: =B88/H88 -> 0.045712905 | L88: =C88/I88 -> 0.022922499
A89: 43435 | B89: 234827 | C89: =SUM($B$78:B89) -> 717414 | D89: 32131 | E89: =SUM($D$78:D89) -> 228954 | F89: 266958 | G89: =SUM($F$78:F89) -> 951792 | H89: 2233100 | I89: =SUM($H$78:H89) -> 23286084 | J89: =F89/H89 -> 0.11954592 | K89: =B89/H89 -> 0.1051574 | L89: =C89/I89 -> 0.030808701 | M89: =G89/I89 -> 0.040873854
G90: =C89/G89 -> 0.75375082
A91: 2019
A92: 43466 | B92: 79787 | C92: =SUM($B$92:B92) -> 79787 | D92: 17948 | E92: =SUM($D$92:D92) -> 17948 | F92: =B92+D92 -> 97735 | G92: =SUM($F$92:F92) -> 97735 | H92: 2021100 | I92: =SUM($H$92:H92) -> 2021100 | J92: =F92/H92 -> 0.04835733 | K92: =B92/H92 -> 0.039477017 | L92: =C92/I92 -> 0.039477017
A93: 43497 | B93: 24979 | C93: =SUM($B$92:B93) -> 104766 | D93: 5592 | E93: =SUM($D$92:D93) -> 23540 | F93: =B93+D93 -> 30571 | G93: =SUM($F$92:F93) -> 128306 | H93: 1170000 | I93: =SUM($H$92:H93) -> 3191100 | J93: =F93/H93 -> 0.02612906 | K93: =B93/H93 -> 0.021349573 | L93: =C93/I93 -> 0.032830685
A94: 43525 | B94: 83058 | C94: =SUM($B$92:B94) -> 187824 | D94: 13590 | E94: =SUM($D$92:D94) -> 37130 | F94: =B94+D94 -> 96648 | G94: =SUM($F$92:F94) -> 224954 | H94: 2019400 | I94: =SUM($H$92:H94) -> 5210500 | J94: =F94/H94 -> 0.04785976 | K94: =B94/H94 -> 0.041130039 | L94: =C94/I94 -> 0.036047212
A95: 43556 | B95: 51333 | C95: =SUM($B$92:B95) -> 239157 | D95: 16597 | E95: =SUM($D$92:D95) -> 53727 | F95: =B95+D95 -> 67930 | G95: =SUM($F$92:F95) -> 292884 | H95: 1574900 | I95: =SUM($H$92:H95) -> 6785400 | J95: =F95/H95 -> 0.043132897 | K95: =B95/H95 -> 0.03259445 | L95: =C95/I95 -> 0.035245822
A96: 43586 | B96: 67364 | C96: =SUM($B$92:B96) -> 306521 | D96: 20541 | E96: =SUM($D$92:D96) -> 74268 | F96: =B96+D96 -> 87905 | G96: =SUM($F$92:F96) -> 380789 | H96: 1611300 | I96: =SUM($H$92:H96) -> 8396700 | J96: =F96/H96 -> 0.054555328 | K96: =B96/H96 -> 0.041807236 | L96: =C96/I96 -> 0.036504936
A97: 43617 | B97: 153705 | C97: =SUM($B$92:B97) -> 460226 | D97: 46000 | E97: =SUM($D$92:D97) -> 120268 | F97: =B97+D97 -> 199705 | G97: =SUM($F$92:F97) -> 580494 | H97: 1796678 | I97: =SUM($H$92:H97) -> 10193378 | J97: =F97/H97 -> 0.11115236 | K97: =B97/H97 -> 0.085549553 | L97: =C97/I97 -> 0.045149508
A98: 43647 | B98: 24356 | C98: =SUM($B$92:B98) -> 484582 | D98: 9213 | E98: =SUM($D$92:D98) -> 129481 | F98: =B98+D98 -> 33569 | G98: =SUM($F$92:F98) -> 614063 | H98: 1528000 | I98: =SUM($H$92:H98) -> 11721378 | J98: =F98/H98 -> 0.021969241 | K98: =B98/H98 -> 0.015939791 | L98: =C98/I98 -> 0.041341726
A99: 43678 | B99: 32044 | C99: =SUM($B$92:B99) -> 516626 | D99: 12196 | E99: =SUM($D$92:D99) -> 141677 | F99: =B99+D99 -> 44240 | G99: =SUM($F$92:F99) -> 658303 | H99: 1588147 | I99: =SUM($H$92:H99) -> 13309525 | J99: =F99/H99 -> 0.027856363 | K99: =B99/H99 -> 0.020176974 | L99: =C99/I99 -> 0.038816261
A100: 43709 | B100: 41196 | C100: =SUM($B$92:B100) -> 557822 | D100: 15966 | E100: =SUM($D$92:D100) -> 157643 | F100: =B100+D100 -> 57162 | G100: =SUM($F$92:F100) -> 715465 | H100: 1800000 | I100: =SUM($H$92:H100) -> 15109525 | J100: =F100/H100 -> 0.031756667 | K100: =B100/H100 -> 0.022886667 | L100: =C100/I100 -> 0.036918566
A101: 43739 | B101: 37941 | C101: =SUM($B$92:B101) -> 595763 | D101: 13417 | E101: =SUM($D$92:D101) -> 171060 | F101: =B101+D101 -> 51358 | G101: =SUM($F$92:F101) -> 766823 | H101: 1868276 | I101: =SUM($H$92:H101) -> 16977801 | J101: =F101/H101 -> 0.027489514 | K101: =B101/H101 -> 0.020308027 | L101: =C101/I101 -> 0.035090705
A102: 43770 | B102: 59093 | C102: =SUM($B$92:B102) -> 654856 | D102: 15255 | E102: =SUM($D$92:D102) -> 186315 | F102: =B102+D102 -> 74348 | G102: =SUM($F$92:F102) -> 841171 | H102: 2057000 | I102: =SUM($H$92:H102) -> 19034801 | J102: =F102/H102 -> 0.036143899 | K102: =B102/H102 -> 0.028727759 | L102: =C102/I102 -> 0.034403091
A103: 43800 | B103: 75653 | C103: =SUM($B$92:B103) -> 730509 | D103: 21222 | E103: =SUM($D$92:D103) -> 207537 | F103: =B103+D103 -> 96875 | G103: =SUM($F$92:F103) -> 938046 | H103: 2213000 | I103: =SUM($H$92:H103) -> 21247801 | J103: =F103/H103 -> 0.043775418 | K103: =B103/H103 -> 0.034185721 | L103: =C103/I103 -> 0.034380452 | M103: =G103/I103 -> 0.04414791
...

Sheet Ratio of Sales
C13: BEV | D13: PHEV | E13: Commercial
B14: 2016 | C14: 0.5 | D14: 0.16 | E14: 0.34
B15: 2017 | C15: 0.6 | D15: 0.14 | E15: 0.26
B16: 2018 | C16: 0.62 | D16: 0.2 | E16: 0.18
B17: 2019 | C17: 0.7 | D17: 0.18 | E17: 0.12

Sheet Annual Comparison
B1: BEV | C1: PHEV | D1: NEV | E1: Passenger Vehicle Sales | F1: BEV/PVS | G1: NEV/PVS | H1: BEV/PVS Annual Growth Rate
A2: 2013 | B2: 14604 | C2: 3290 | D2: =SUM(B2:C2) -> 17894 | E2: 17613900 | F2: =B2/E2 -> 0.00082911791 | G2: =D2/E2 -> 0.0010159022
A3: 2014 | B3: 21732 | C3: 16129 | D3: =SUM(B3:C3) -> 37861 | E3: 19604338 | F3: =B3/E3 -> 0.0011085302 | G3: =D3/E3 -> 0.0019312562 | H3: =(F3-F2)/F2 -> 0.33699941
A4: 2015 | B4: 52243 | C4: 59649 | D4: =SUM(B4:C4) -> 111892 | E4: 21060871 | F4: =B4/E4 -> 0.0024805717 | G4: =D4/E4 -> 0.0053127907 | H4: =(F4-F3)/F3 -> 1.2377124
A5: 2016 | B5: 167572 | C5: 72106 | D5: =SUM(B5:C5) -> 239678 | E5: 24159155 | F5: =B5/E5 -> 0.0069361697 | G5: =D5/E5 -> 0.009920794 | H5: =(F5-F4)/F4 -> 1.7961981
A6: 2017 | B6: 456097 | C6: 99868 | D6: =SUM(B6:C6) -> 555965 | E6: 24818264 | F6: =B6/E6 -> 0.018377474 | G6: =D6/E6 -> 0.022401446 | H6: =(F6-F5)/F5 -> 1.6495133
A7: 2018 | B7: 717414 | C7: 228954 | D7: =SUM(B7:C7) -> 946368 | E7: 23286084 | F7: =B7/E7 -> 0.030808701 | G7: =D7/E7 -> 0.040640925 | H7: =(F7-F6)/F6 -> 0.67643829
A8: 2019 | B8: 730509 | C8: 207537 | D8: =SUM(B8:C8) -> 938046 | E8: 21247801 | F8: =B8/E8 -> 0.034380452 | G8: =D8/E8 -> 0.04414791 | H8: =(F8-F7)/F7 -> 0.11593319

Sheet Battery Price 
A2: 2010 | B2: 1 | C2: 1160
A3: 2011 | B3: 2 | C3: 899
A4: 2012 | B4: 3 | C4: 707
A5: 2013 | B5: 4 | C5: 650
A6: 2014 | B6: 5 | C6: 577
A7: 2015 | B7: 6 | C7: 373
A8: 2016 | B8: 7 | C8: 288
A9: 2017 | B9: 8 | C9: 214
A10: 2018 | B10: 9 | C10: 176
A11: 2019 | B11: 10 | C11: 156
A12: Linear growth (0.9)
A13: 2020 | C13: =C11*$D$13 -> 140.4 | D13: 0.9
A14: 2021 | C14: =C13*$D$13 -> 126.36
A15: 2022 | C15: =C14*$D$13 -> 113.724
A16: 2023 | C16: =C15*$D$13 -> 102.3516
A17: 2024 | C17: =C16*$D$13 -> 92.11644
A18: 2025 | C18: =C17*$D$13 -> 82.904796
A21: simple exopnential growth
A22: 2020 | B22: 11 | C22: 130.48
A23: 2021 | B23: 12 | C23: 104.94
A24: 2022 | B24: 13 | C24: 84.39
A25: 2023 | B25: 14 | C25: 67.86
A26: 2024 | B26: 15 | C26: 54.57
A27: 2025 | B27: 16 | C27: 43.89
A28: 2026 | B28: 17 | C28: 35.29
A29: 2027 | B29: 18 | C29: 28.38
A30: 2028 | B30: 19 | C30: 22.83
A31: 2029 | B31: 20 | C31: 18.36
A32: 2030 | B32: 21 | C32: 14.76

Sheet Battery Installed Capacity
C3: ROEWE Model | D3: Sticker Price (RMB) | E3: National Subsidy | F3: Local Subsidy | G3: Liscense Plate Fee | H3: Purchase Tax | I3: Final Price
C4: ERX5 (EV400) | D4: 282000 | E4: 45000 | F4: 22000 | G4: 0 | H4: 0 | I4: 215000
C5: RX5 (2018) | D5: 158000 | E5: 0 | F5: 0 | G5: 89000 | H5: 13000 | I5: 260000
C9: BEV (Passenger) | D9: Standards | E9: 2018 | F9: 2019 | G9: Percentage Change
C10: Driving Range (KM) | D10: 150≤R<200 | E10: 15000 | F10: 0 | G10: =(F10-E10)/E10 -> -1
D11: 200≤R<250 | E11: 24000 | F11: 0 | G11: =(F11-E11)/E11 -> -1
D12: 250≤R<300 | E12: 34000 | F12: 18000 | G12: =(F12-E12)/E12 -> -0.47058824
D13: 300≤R<400 | E13: 45000 | F13: 18000 | G13: =(F13-E13)/E13 -> -0.6
D14: R≥400 | E14: 50000 | F14: 25000 | G14: =(F14-E14)/E14 -> -0.5
C15: Energy Density (Wh/kg) | D15: E<105 | E15: 0 | F15: 0 | G15: 0
D16: 105≤E<120 | E16: 6000 | F16: 0 | G16: =(F16-E16)/E16 -> -1
D17: 120≤E<125 | E17: 10000 | F17: 0 | G17: =(F17-E17)/E17 -> -1
D18: 125≤E<140 | E18: 10000 | F18: 8000 | G18: =(F18-E18)/E18 -> -0.2
D19: 140≤E<160 | E19: 11000 | F19: 9000 | G19: =(F19-E19)/E19 -> -0.18181818
D20: E≥160 | E20: 12000 | F20: 10000 | G20: =(F20-E20)/E20 -> -0.16666667

Sheet ABC class Vehicle Definition
B1: Wheelbase Length
B2: 乘用车级别：A00级乘用车：轴距在2米至2.3米之间，发动机排量小于1升
B3: A0级乘用车：轴距为2.3米至2.5米，排量为1升至1.5升。
B4: A级乘用车：轴距在2.5米至2.7米之间，排量约在1.6升至2.0升。
B5: B级乘用车：轴距约在2.7米至2.9米之间，排量从1.8升到2.4升。
B6: C级乘用车：轴距约在2.8米至3米之间，发动机排量大于2.4升

Sheet A00
C4: Chery eQ1
D5: 2019 | E5: 2020 | F5: 2021 | G5: 2022 | H5: 2023 | I5: 2024 | J5: 2025 | K5: 2026 | L5: 2027 | M5: 2028 | N5: 2029 | O5: 2030
C6: Retail Price | D6: 65000 | E6: =D6-((D16-E16)+(D17-E17)+(D18-E18)) -> 59928 | F6: =E6-((E16-F16)+(E17-F17)+(E18-F18)) -> 55343.2 | G6: =F6-((F16-G16)+(F17-G17)+(F18-G18)) -> 51196.88 | H6: =G6-((G16-H16)+(G17-H17)+(G18-H18)) -> 47445.192 | I6: =H6-((H16-I16)+(H17-I17)+(H18-I18)) -> 44048.673 | J6: =I6-((I16-J16)+(I17-J17)+(I18-J18)) -> 40971.806 | K6: =J6-((J16-K16)+(J17-K17)+(J18-K18)) -> 38182.625 | L6: =K6-((K16-L16)+(K17-L17)+(K18-L18)) -> 35652.362 | ... O6: =N6-((N16-O16)+(N17-O17)+(N18-O18)) -> 29368.852
C7: Purchase Tax | D7: 0 | E7: 0 | F7: =F6*0.1 -> 5534.32 | G7: =G6*0.1 -> 5119.688 | H7: =H6*0.1 -> 4744.5192 | I7: =I6*0.1 -> 4404.8673 | J7: =J6*0.1 -> 4097.1806 | K7: =K6*0.1 -> 3818.2625 | L7: =L6*0.1 -> 3565.2362 | M7: =M6*0.1 -> 3335.5126 | ... O7: =O6*0.1 -> 2936.8852
C8: Consumer Final Price | D8: =D6+D7 -> 65000 | E8: =E6+E7 -> 59928 | F8: =F6+F7 -> 60877.52 | G8: =G6+G7 -> 56316.568 | H8: =H6+H7 -> 52189.711 | I8: =I6+I7 -> 48453.54 | J8: =J6+J7 -> 45068.986 | K8: =K6+K7 -> 42000.887 | ... O8: =O6+O7 -> 32305.737
C9: Dealer Gross Profit(5%) | D9: =D6*0.05 -> 3250 | E9: =E6*0.05 -> 2996.4 | F9: =F6*0.05 -> 2767.16 | G9: =G6*0.05 -> 2559.844 | H9: =H6*0.05 -> 2372.2596 | I9: =I6*0.05 -> 2202.4336 | J9: =J6*0.05 -> 2048.5903 | K9: =K6*0.05 -> 1909.1312 | ... O9: =O6*0.05 -> 1468.4426
C10: Range (km) | D10: 301 | E10: 301 | F10: 301 | G10: 301 | H10: 301 | I10: 301 | J10: 301 | K10: 301 | L10: 301 | M10: 301 | N10: 301 | O10: 301
C11: Battery (kwh) | D11: 30.6 | E11: 30.6 | F11: 30.6 | G11: 30.6 | H11: 30.6 | I11: 30.6 | J11: 30.6 | K11: 30.6 | L11: 30.6 | M11: 30.6 | N11: 30.6 | O11: 30.6
C12: Battery Price/wh | D12: 1.2 | E12: =D12*0.9 -> 1.08 | F12: =E12*0.9 -> 0.972 | G12: =F12*0.9 -> 0.8748 | H12: =G12*0.9 -> 0.78732 | I12: =H12*0.9 -> 0.708588 | J12: =I12*0.9 -> 0.6377292 | K12: =J12*0.9 -> 0.57395628 | L12: =K12*0.9 -> 0.51656065 | ... O12: =N12*0.9 -> 0.37657272
C13: Subsidies | D13: 27000 | E13: 28000 | F13: 0 | G13: 0 | H13: 0 | I13: 0 | J13: 0 | K13: 0 | L13: 0 | M13: 0 | N13: 0 | O13: 0
C14: Auto Company Revenue | D14: =D6-D9+D13 -> 88750 | E14: =E6-E9+E13 -> 84931.6 | F14: =F6-F9+F13 -> 52576.04 | G14: =G6-G9+G13 -> 48637.036 | H14: =H6-H9+H13 -> 45072.932 | I14: =I6-I9+I13 -> 41846.239 | J14: =J6-J9+J13 -> 38923.215 | K14: =K6-K9+K13 -> 36273.494 | ... O14: =O6-O9+O13 -> 27900.41
C15: Revenue (after vat) | D15: =D14*0.87 -> 77212.5 | E15: =E14*0.87 -> 73890.492 | F15: =F14*0.87 -> 45741.155 | G15: =G14*0.87 -> 42314.221 | H15: =H14*0.87 -> 39213.451 | I15: =I14*0.87 -> 36406.228 | J15: =J14*0.87 -> 33863.197 | K15: =K14*0.87 -> 31557.94 | ... O15: =O14*0.87 -> 24273.356
C16: Power Battery System Cost | D16: =D12*1000*D11 -> 36720 | E16: =E12*1000*E11 -> 33048 | F16: =F12*1000*F11 -> 29743.2 | G16: =G12*1000*G11 -> 26768.88 | H16: =H12*1000*H11 -> 24091.992 | I16: =I12*1000*I11 -> 21682.793 | J16: =J12*1000*J11 -> 19514.514 | K16: =K12*1000*K11 -> 17563.062 | ... O16: =O12*1000*O11 -> 11523.125
C17: Electric Motor & Electric Controlling | D17: 5000 | E17: =D17-200 -> 4800 | F17: =E17-200 -> 4600 | G17: =F17-200 -> 4400 | H17: =G17-200 -> 4200 | I17: =H17-200 -> 4000 | J17: =I17-200 -> 3800 | K17: =J17-200 -> 3600 | L17: =K17-200 -> 3400 | ... O17: =N17-200 -> 2800
C18: Other Cost | D18: 12000 | E18: =D18*0.9 -> 10800 | F18: =E18*0.9 -> 9720 | G18: =F18*0.9 -> 8748 | H18: =G18*0.9 -> 7873.2 | I18: =H18*0.9 -> 7085.88 | J18: =I18*0.9 -> 6377.292 | K18: =J18*0.9 -> 5739.5628 | L18: =K18*0.9 -> 5165.6065 | ... O18: =N18*0.9 -> 3765.7272
C19: Profit Margin(BEV) | D19: =D15-D16-D17-D18 -> 23492.5 | E19: =E15-E16-E17-E18 -> 25242.492 | F19: =F15-F16-F17-F18 -> 1677.9548 | G19: =G15-G16-G17-G18 -> 2397.3413 | H19: =H15-H16-H17-H18 -> 3048.2592 | I19: =I15-I16-I17-I18 -> 3637.5553 | J19: =J15-J16-J17-J18 -> 4171.3917 | K19: =K15-K16-K17-K18 -> 4655.3146 | ... O19: =O15-O16-O17-O18 -> 6184.5041
C20: PM/Revenue | D20: =D19/D14 -> 0.26470423 | E20: =E19/E14 -> 0.29720966 | F20: =F19/F14 -> 0.031914819 | G20: =G19/G14 -> 0.049290449 | H20: =H19/H14 -> 0.067629485 | I20: =I19/I14 -> 0.086926695 | J20: =J19/J14 -> 0.10716976 | K20: =K19/K14 -> 0.12833929 | ... O20: =O19/O14 -> 0.22166356
C21: Chery QQ6
D22: 2019 | E22: 2020 | F22: 2021 | G22: 2022 | H22: 2023 | I22: 2024 | J22: 2025 | K22: 2026 | L22: 2027 | M22: 2028 | N22: 2029 | O22: 2030
C23: Retail Price | D23: 55000 | E23: =D23+(E29-D29)+(E30-D30) -> 55300 | F23: =E23+(F29-E29)+(F30-E30) -> 55606 | G23: =F23+(G29-F29)+(G30-F30) -> 55918.12 | H23: =G23+(H29-G29)+(H30-G30) -> 56236.482 | I23: =H23+(I29-H29)+(I30-H30) -> 56561.212 | J23: =I23+(J29-I29)+(J30-I30) -> 56892.436 | K23: =J23+(K29-J29)+(K30-J30) -> 57230.285 | L23: =K23+(L29-K29)+(L30-K30) -> 57574.891 | ... O23: =N23+(O29-N29)+(O30-N30) -> 58650.615
C24: Purchase Tax | D24: =D23*0.1 -> 5500 | E24: =E23*0.1 -> 5530 | F24: =F23*0.1 -> 5560.6 | G24: =G23*0.1 -> 5591.812 | H24: =H23*0.1 -> 5623.6482 | I24: =I23*0.1 -> 5656.1212 | J24: =J23*0.1 -> 5689.2436 | K24: =K23*0.1 -> 5723.0285 | ... O24: =O23*0.1 -> 5865.0615
C25: Consumer Final Price | D25: =D23+D24 -> 60500 | E25: =E23+E24 -> 60830 | F25: =F23+F24 -> 61166.6 | G25: =G23+G24 -> 61509.932 | H25: =H23+H24 -> 61860.131 | I25: =I23+I24 -> 62217.333 | J25: =J23+J24 -> 62581.68 | K25: =K23+K24 -> 62953.314 | ... O25: =O23+O24 -> 64515.676
C26: Dealer Gross Profit (5%) | D26: =D23*0.05 -> 2750 | E26: =E23*0.05 -> 2765 | F26: =F23*0.05 -> 2780.3 | G26: =G23*0.05 -> 2795.906 | H26: =H23*0.05 -> 2811.8241 | I26: =I23*0.05 -> 2828.0606 | J26: =J23*0.05 -> 2844.6218 | K26: =K23*0.05 -> 2861.5143 | ... O26: =O23*0.05 -> 2932.5307
C27: Auto Company Revenue | D27: =D23-D26 -> 52250 | E27: =E23-E26 -> 52535 | F27: =F23-F26 -> 52825.7 | G27: =G23-G26 -> 53122.214 | H27: =H23-H26 -> 53424.658 | I27: =I23-I26 -> 53733.151 | J27: =J23-J26 -> 54047.814 | K27: =K23-K26 -> 54368.771 | ... O27: =O23-O26 -> 55718.084
C28: Revenue (after vat) | D28: =D27*0.87 -> 45457.5 | E28: =E27*0.87 -> 45705.45 | F28: =F27*0.87 -> 45958.359 | G28: =G27*0.87 -> 46216.326 | H28: =H27*0.87 -> 46479.453 | I28: =I27*0.87 -> 46747.842 | J28: =J27*0.87 -> 47021.599 | K28: =K27*0.87 -> 47300.831 | ... O28: =O27*0.87 -> 48474.733
C29: Motor Cost | D29: 10000 | E29: =D29*1.02 -> 10200 | F29: =E29*1.02 -> 10404 | G29: =F29*1.02 -> 10612.08 | H29: =G29*1.02 -> 10824.322 | I29: =H29*1.02 -> 11040.808 | J29: =I29*1.02 -> 11261.624 | K29: =J29*1.02 -> 11486.857 | L29: =K29*1.02 -> 11716.594 | ... O29: =N29*1.02 -> 12433.743
C30: Transmission Cost | D30: 5000 | E30: =D30*1.02 -> 5100 | F30: =E30*1.02 -> 5202 | G30: =F30*1.02 -> 5306.04 | H30: =G30*1.02 -> 5412.1608 | I30: =H30*1.02 -> 5520.404 | J30: =I30*1.02 -> 5630.8121 | K30: =J30*1.02 -> 5743.4283 | L30: =K30*1.02 -> 5858.2969 | ... O30: =N30*1.02 -> 6216.8715
C31: 48V System Cost | D31: 0 | E31: 0 | F31: 0 | G31: 0 | H31: 0 | I31: 0 | J31: 0 | K31: 0 | L31: 0 | M31: 0 | N31: 0 | O31: 0
C32: Other Cost | D32: 16000 | E32: 16000 | F32: 16000 | G32: 16000 | H32: 16000 | I32: 16000 | J32: 16000 | K32: 16001 | L32: 16002 | M32: 16003 | N32: 16004 | O32: 16005
C33: Profit Margin(ICEV) | D33: =D28-D29-D30-D31-D32 -> 14457.5 | E33: =E28-E29-E30-E31-E32 -> 14405.45 | F33: =F28-F29-F30-F31-F32 -> 14352.359 | G33: =G28-G29-G30-G31-G32 -> 14298.206 | H33: =H28-H29-H30-H31-H32 -> 14242.97 | I33: =I28-I29-I30-I31-I32 -> 14186.63 | J33: =J28-J29-J30-J31-J32 -> 14129.162 | K33: =K28-K29-K30-K31-K32 -> 14069.546 | ... O33: =O28-O29-O30-O31-O32 -> 13819.118
C34: PM/Revenue | D34: =D33/D27 -> 0.27669856 | E34: =E33/E27 -> 0.27420672 | F34: =F33/F27 -> 0.27169274 | G34: =G33/G27 -> 0.26915682 | H34: =H33/H27 -> 0.26659918 | I34: =I33/I27 -> 0.26402006 | J34: =J33/J27 -> 0.26141968 | K34: =K33/K27 -> 0.25877991 | ... O34: =O33/O27 -> 0.24801855
D38: =D8-D25 -> 4500 | E38: =E8-E25 -> -902 | F38: =F8-F25 -> -289.08 | G38: =G8-G25 -> -5193.364 | H38: =H8-H25 -> -9670.4194 | I38: =I8-I25 -> -13763.793 | J38: =J8-J25 -> -17512.694 | K38: =K8-K25 -> -20952.426 | ... O38: =O8-O25 -> -32209.939

Sheet A00 class comparison 
P5: 2030
P6: =O6-((O16-P16)+(O17-P17)+(O18-P18)) -> -200
P7: =P6*0.1 -> -20
P8: =P6+P7 -> -220
P9: =P6*0.05 -> -10
P10: 301
P11: 30.6
P12: =O12*0.9 -> 0
P13: 0
P14: =P6-P9+P13 -> -190
P15: =P14*0.87 -> -165.3
P16: =P12*1000*P11 -> 0
P17: =O17-200 -> -200
P18: =O18*0.9 -> 0
P19: =P15-P16-P17-P18 -> 34.7
P20: =P19/P14 -> -0.18263158
P22: 2030
P23: =O23+(P29-O29)+(P30-O30) -> 0
P24: =P23*0.1 -> 0
P25: =P23+P24 -> 0
P26: =P23*0.05 -> 0
P27: =P23-P26 -> 0
P28: =P27*0.87 -> 0
P29: =O29*1.02 -> 0
P30: =O30*1.02 -> 0
P31: 0
P32: 16005
P33: =P28-P29-P30-P31-P32 -> -16005
P34: =P33/P27 -> #DIV/0!
P38: =P8-P25 -> -220
A42: ICEV BEV | C42: Chery eQ1 奇瑞eQ1 | E42: JAC iEV6E 江淮iEV6E | G42: SGMW E100 上汽通用宝骏E100 | I42: SGMW E200 上汽通用宝骏E200 | K42: Changan EV360 长安EV360 | M42: Zotye E200 众泰E200 | O42: Zhidou D2 知豆D2 | Q42: JMEV E200L 江铃E200L | S42: Changhe EC100 北汽昌河EC100 | U42: BAIC Lite 北汽新能源Lite
C43: 71900 | E43: 70500 | G43: 54800 | I43: 59800 | K43: 75800 | M43: 66900 | O43: 54800 | Q43: 53300 | S43: 47800 | U43: 118800
A44: Chery QQ6 奇瑞QQ6 | B44: 47400 | C44: 2025 | E44: 2025 | G44: 2020 | I44: 2022 | K44: 2026 | M44: 2024 | O44: 2020 | Q44: 2020 | S44: 2019 | U44: Post 2030
A46: Changhe Beidou Star 昌河北斗星 | B46: 53400 | C46: 2023 | E46: 2023 | G46: 2019 | I46: 2020 | K46: 2024 | M46: 2022 | O46: 2019 | Q46: 2019 | S46: 2019 | U46: Post 2030
A48: Changhe Beidou StarX5 昌河北斗星X5 | B48: 48950 | C48: 2025 | E48: 2024 | G48: 2020 | I48: 2022 | K48: 2026 | M48: 2023 | O48: 2020 | Q48: 2019 | S48: 2019 | U48: Post 2030
A50: Suzuki Beidou Star 铃木北斗星 | B50: 42900 | C50: 2026 | E50: 2026 | G50: 2022 | I50: 2023 | K50: 2028 | M50: 2025 | O50: 2022 | Q50: 2022 | S50: 2020 | U50: Post 2030
A52: SGMW Hongguang 上汽五菱宏光 | B52: 49175 | C52: 2025 | E52: 2024 | G52: 2020 | I52: 2022 | K52: 2026 | M52: 2023 | O52: 2020 | Q52: 2019 | S52: 2019 | U52: Post 2030
A54: SGMW Zhiguang 上汽五菱之光 | B54: 35800 | C54: 2029 | E54: 2029 | G54: 2024 | I54: 2025 | K54: Post 2030 | M54: 2027 | O54: 2024 | Q54: 2023 | S54: 2022 | U54: Post 2030
A56: SGMW Lechi 上汽通用乐驰 | B56: 44800 | C56: 2026 | E56: 2025 | G56: 2021 | I56: 2023 | K56: 2027 | M56: 2024 | O56: 2021 | Q56: 2020 | S56: 2019 | U56: Post 2030
A58: Changan Benben 长安奔奔 | B58: 48250 | C58: 2025 | E58: 2024 | G58: 2020 | I58: 2022 | K58: 2026 | M58: 2023 | O58: 2020 | Q58: 2020 | S58: 2019 | U58: Post 2030
A60: Nissan March 东风日产玛驰 | B60: 73650 | C60: 2019 | E60: 2019 | G60: 2019 | I60: 2019 | K60: 2019 | M60: 2019 | O60: 2019 | Q60: 2019 | S60: 2019 | U60: Post 2030
A62: Mercedes Benz Smart 奔驰Smart | B62: 166300 | C62: 2019 | E62: 2019 | G62: 2019 | I62: 2019 | K62: 2019 | M62: 2019 | O62: 2019 | Q62: 2019 | S62: 2019 | U62: 2019

Sheet A
C4: BAIC EU5
D5: 2019 | E5: 2020 | F5: 2021 | G5: 2022 | H5: 2023 | I5: 2024 | J5: 2025 | K5: 2026 | L5: 2027 | M5: 2028 | N5: 2029 | O5: 2030
C6: Retail Price | D6: 132900 | E6: =D6-((D16-E16)+(D17-E17)+(D18-E18)) -> 123376 | F6: =E6-((E16-F16)+(E17-F17)+(E18-F18)) -> 114784.4 | G6: =F6-((F16-G16)+(F17-G17)+(F18-G18)) -> 107031.96 | H6: =G6-((G16-H16)+(G17-H17)+(G18-H18)) -> 100034.76 | I6: =H6-((H16-I16)+(H17-I17)+(H18-I18)) -> 93717.288 | J6: =I6-((I16-J16)+(I17-J17)+(I18-J18)) -> 88011.559 | K6: =J6-((J16-K16)+(J17-K17)+(J18-K18)) -> 82856.403 | L6: =K6-((K16-L16)+(K17-L17)+(K18-L18)) -> 78196.763 | ... O6: =N6-((N16-O16)+(N17-O17)+(N18-O18)) -> 66719.7
C7: Purchase Tax | D7: 0 | E7: 0 | F7: =F6*0.1 -> 11478.44 | G7: =G6*0.1 -> 10703.196 | H7: =H6*0.1 -> 10003.476 | I7: =I6*0.1 -> 9371.7288 | J7: =J6*0.1 -> 8801.1559 | K7: =K6*0.1 -> 8285.6403 | L7: =L6*0.1 -> 7819.6763 | M7: =M6*0.1 -> 7398.3086 | ... O7: =O6*0.1 -> 6671.97
C8: Consumer Final Price | D8: =D6+D7 -> 132900 | E8: =E6+E7 -> 123376 | F8: =F6+F7 -> 126262.84 | G8: =G6+G7 -> 117735.16 | H8: =H6+H7 -> 110038.24 | I8: =I6+I7 -> 103089.02 | J8: =J6+J7 -> 96812.715 | K8: =K6+K7 -> 91142.043 | ... O8: =O6+O7 -> 73391.67
C9: Dealer Gross Profit(5%) | D9: =D6*0.05 -> 6645 | E9: =E6*0.05 -> 6168.8 | F9: =F6*0.05 -> 5739.22 | G9: =G6*0.05 -> 5351.598 | H9: =H6*0.05 -> 5001.7382 | I9: =I6*0.05 -> 4685.8644 | J9: =J6*0.05 -> 4400.5779 | K9: =K6*0.05 -> 4142.8201 | ... O9: =O6*0.05 -> 3335.985
C10: Range (km) | D10: 450 | E10: 450 | F10: 450 | G10: 450 | H10: 450 | I10: 450 | J10: 450 | K10: 450 | L10: 450 | M10: 450 | N10: 450 | O10: 450
C11: Battery (kwh) | D11: 60.2 | E11: 60.2 | F11: 60.2 | G11: 60.2 | H11: 60.2 | I11: 60.2 | J11: 60.2 | K11: 60.2 | L11: 60.2 | M11: 60.2 | N11: 60.2 | O11: 60.2
C12: Battery Price/wh | D12: 1.2 | E12: =D12*0.9 -> 1.08 | F12: =E12*0.9 -> 0.972 | G12: =F12*0.9 -> 0.8748 | H12: =G12*0.9 -> 0.78732 | I12: =H12*0.9 -> 0.708588 | J12: =I12*0.9 -> 0.6377292 | K12: =J12*0.9 -> 0.57395628 | L12: =K12*0.9 -> 0.51656065 | ... O12: =N12*0.9 -> 0.37657272
C13: Subsidies | D13: 34000 | E13: 35000 | F13: 0 | G13: 0 | H13: 0 | I13: 0 | J13: 0 | K13: 0 | L13: 0 | M13: 0 | N13: 0 | O13: 0
C14: Auto Company Revenue | D14: =D6-D9+D13 -> 160255 | E14: =E6-E9+E13 -> 152207.2 | F14: =F6-F9+F13 -> 109045.18 | G14: =G6-G9+G13 -> 101680.36 | H14: =H6-H9+H13 -> 95033.026 | I14: =I6-I9+I13 -> 89031.423 | J14: =J6-J9+J13 -> 83610.981 | K14: =K6-K9+K13 -> 78713.583 | ... O14: =O6-O9+O13 -> 63383.715
C15: Revenue (after vat) | D15: =D14*0.87 -> 139421.85 | E15: =E14*0.87 -> 132420.26 | F15: =F14*0.87 -> 94869.307 | G15: =G14*0.87 -> 88461.915 | H15: =H14*0.87 -> 82678.732 | I15: =I14*0.87 -> 77457.338 | J15: =J14*0.87 -> 72741.553 | K15: =K14*0.87 -> 68480.817 | ... O15: =O14*0.87 -> 55143.832
C16: Power Battery System Cost | D16: =D12*1000*D11 -> 72240 | E16: =E12*1000*E11 -> 65016 | F16: =F12*1000*F11 -> 58514.4 | G16: =G12*1000*G11 -> 52662.96 | H16: =H12*1000*H11 -> 47396.664 | I16: =I12*1000*I11 -> 42656.998 | J16: =J12*1000*J11 -> 38391.298 | K16: =K12*1000*K11 -> 34552.168 | ... O16: =O12*1000*O11 -> 22669.677
C17: Electric Motor & Electric Controlling | D17: 10000 | E17: =D17-200 -> 9800 | F17: =E17-200 -> 9600 | G17: =F17-200 -> 9400 | H17: =G17-200 -> 9200 | I17: =H17-200 -> 9000 | J17: =I17-200 -> 8800 | K17: =J17-200 -> 8600 | L17: =K17-200 -> 8400 | ... O17: =N17-200 -> 7800
C18: Other Cost | D18: 21000 | E18: =D18*0.9 -> 18900 | F18: =E18*0.9 -> 17010 | G18: =F18*0.9 -> 15309 | H18: =G18*0.9 -> 13778.1 | I18: =H18*0.9 -> 12400.29 | J18: =I18*0.9 -> 11160.261 | K18: =J18*0.9 -> 10044.235 | L18: =K18*0.9 -> 9039.8114 | ... O18: =N18*0.9 -> 6590.0225
C19: Profit Margin(BEV) | D19: =D15-D16-D17-D18 -> 36181.85 | E19: =E15-E16-E17-E18 -> 38704.264 | F19: =F15-F16-F17-F18 -> 9744.9066 | G19: =G15-G16-G17-G18 -> 11089.955 | H19: =H15-H16-H17-H18 -> 12303.968 | I19: =I15-I16-I17-I18 -> 13400.051 | J19: =J15-J16-J17-J18 -> 14389.995 | K19: =K15-K16-K17-K18 -> 15284.414 | ... O19: =O15-O16-O17-O18 -> 18084.132
C20: PM/Revenue | D20: =D19/D14 -> 0.22577673 | E20: =E19/E14 -> 0.25428668 | F20: =F19/F14 -> 0.089365771 | G20: =G19/G14 -> 0.10906683 | H20: =H19/H14 -> 0.12947045 | I20: =I19/I14 -> 0.15050923 | J20: =J19/J14 -> 0.17210652 | K20: =K19/K14 -> 0.19417759 | ... O20: =O19/O14 -> 0.28531196
C21: BAIC D50
D22: 2019 | E22: 2020 | F22: 2021 | G22: 2022 | H22: 2023 | I22: 2024 | J22: 2025 | K22: 2026 | L22: 2027 | M22: 2028 | N22: 2029 | O22: 2030
C23: Retail Price | D23: 99900 | E23: =D23+(E29-D29)+(E30-D30) -> 100360 | F23: =E23+(F29-E29)+(F30-E30) -> 100829.2 | G23: =F23+(G29-F29)+(G30-F30) -> 101307.78 | H23: =G23+(H29-G29)+(H30-G30) -> 101795.94 | I23: =H23+(I29-H29)+(I30-H30) -> 102293.86 | J23: =I23+(J29-I29)+(J30-I30) -> 102801.74 | K23: =J23+(K29-J29)+(K30-J30) -> 103319.77 | L23: =K23+(L29-K29)+(L30-K30) -> 103848.17 | ... O23: =N23+(O29-N29)+(O30-N30) -> 105497.61
C24: Purchase Tax | D24: =D23*0.1 -> 9990 | E24: =E23*0.1 -> 10036 | F24: =F23*0.1 -> 10082.92 | G24: =G23*0.1 -> 10130.778 | H24: =H23*0.1 -> 10179.594 | I24: =I23*0.1 -> 10229.386 | J24: =J23*0.1 -> 10280.174 | K24: =K23*0.1 -> 10331.977 | ... O24: =O23*0.1 -> 10549.761
C25: Consumer Final Price | D25: =D23+D24 -> 109890 | E25: =E23+E24 -> 110396 | F25: =F23+F24 -> 110912.12 | G25: =G23+G24 -> 111438.56 | H25: =H23+H24 -> 111975.53 | I25: =I23+I24 -> 112523.24 | J25: =J23+J24 -> 113081.91 | K25: =K23+K24 -> 113651.75 | ... O25: =O23+O24 -> 116047.37
C26: Dealer Gross Profit (5%) | D26: =D23*0.05 -> 4995 | E26: =E23*0.05 -> 5018 | F26: =F23*0.05 -> 5041.46 | G26: =G23*0.05 -> 5065.3892 | H26: =H23*0.05 -> 5089.797 | I26: =I23*0.05 -> 5114.6929 | J26: =J23*0.05 -> 5140.0868 | K26: =K23*0.05 -> 5165.9885 | ... O26: =O23*0.05 -> 5274.8805
C27: Auto Company Revenue | D27: =D23-D26 -> 94905 | E27: =E23-E26 -> 95342 | F27: =F23-F26 -> 95787.74 | G27: =G23-G26 -> 96242.395 | H27: =H23-H26 -> 96706.143 | I27: =I23-I26 -> 97179.166 | J27: =J23-J26 -> 97661.649 | K27: =K23-K26 -> 98153.782 | ... O27: =O23-O26 -> 100222.73
C28: Revenue (after vat) | D28: =D27*0.87 -> 82567.35 | E28: =E27*0.87 -> 82947.54 | F28: =F27*0.87 -> 83335.334 | G28: =G27*0.87 -> 83730.883 | H28: =H27*0.87 -> 84134.344 | I28: =I27*0.87 -> 84545.874 | J28: =J27*0.87 -> 84965.635 | K28: =K27*0.87 -> 85393.79 | ... O28: =O27*0.87 -> 87193.774
C29: Motor Cost | D29: 15000 | E29: =D29*1.02 -> 15300 | F29: =E29*1.02 -> 15606 | G29: =F29*1.02 -> 15918.12 | H29: =G29*1.02 -> 16236.482 | I29: =H29*1.02 -> 16561.212 | J29: =I29*1.02 -> 16892.436 | K29: =J29*1.02 -> 17230.285 | L29: =K29*1.02 -> 17574.891 | ... O29: =N29*1.02 -> 18650.615
C30: Transmission Cost | D30: 8000 | E30: =D30*1.02 -> 8160 | F30: =E30*1.02 -> 8323.2 | G30: =F30*1.02 -> 8489.664 | H30: =G30*1.02 -> 8659.4573 | I30: =H30*1.02 -> 8832.6464 | J30: =I30*1.02 -> 9009.2994 | K30: =J30*1.02 -> 9189.4853 | L30: =K30*1.02 -> 9373.275 | ... O30: =N30*1.02 -> 9946.9945
C31: 48V System Cost | D31: 4000 | E31: 4000 | F31: 4000 | G31: 4000 | H31: 4000 | I31: 4000 | J31: 4000 | K31: 4000 | L31: 4000 | M31: 4000 | N31: 4000 | O31: 4000
C32: Other Cost | D32: 32000 | E32: 32000 | F32: 32000 | G32: 32000 | H32: 32000 | I32: 32000 | J32: 32000 | K32: 32000 | L32: 32000 | M32: 32000 | N32: 32000 | O32: 32000
C33: Profit Margin(ICEV) | D33: =D28-D29-D30-D31-D32 -> 23567.35 | E33: =E28-E29-E30-E31-E32 -> 23487.54 | F33: =F28-F29-F30-F31-F32 -> 23406.134 | G33: =G28-G29-G30-G31-G32 -> 23323.099 | H33: =H28-H29-H30-H31-H32 -> 23238.404 | I33: =I28-I29-I30-I31-I32 -> 23152.016 | J33: =J28-J29-J30-J31-J32 -> 23063.899 | K33: =K28-K29-K30-K31-K32 -> 22974.02 | ... O33: =O28-O29-O30-O31-O32 -> 22596.165
C34: PM/Revenue | D34: =D33/D27 -> 0.24832569 | E34: =E33/E27 -> 0.2463504 | F34: =F33/F27 -> 0.24435417 | G34: =G33/G27 -> 0.24233706 | H34: =H33/H27 -> 0.24029916 | I34: =I33/I27 -> 0.23824053 | J34: =J33/J27 -> 0.23616127 | K34: =K33/K27 -> 0.23406148 | ... O34: =O33/O27 -> 0.22545949
D37: =D8-D25 -> 23010 | E37: =E8-E25 -> 12980 | F37: =F8-F25 -> 15350.72 | G37: =G8-G25 -> 6296.5936 | H37: =H8-H25 -> -1937.2932 | I37: =I8-I25 -> -9434.228 | J37: =J8-J25 -> -16269.194 | K37: =K8-K25 -> -22509.704 | ... O37: =O8-O25 -> -42655.7

Sheet A class comparison
C4: BAIC EU5
D5: 2019 | E5: 2020 | F5: 2021 | G5: 2022 | H5: 2023 | I5: 2024 | J5: 2025 | K5: 2026 | L5: 2027 | M5: 2028 | N5: 2029 | O5: 2030
C6: Retail Price | D6: 182800 | E6: =D6-((D16-E16)+(D17-E17)+(D18-E18)) -> 173276 | F6: =E6-((E16-F16)+(E17-F17)+(E18-F18)) -> 164684.4 | G6: =F6-((F16-G16)+(F17-G17)+(F18-G18)) -> 156931.96 | H6: =G6-((G16-H16)+(G17-H17)+(G18-H18)) -> 149934.76 | I6: =H6-((H16-I16)+(H17-I17)+(H18-I18)) -> 143617.29 | J6: =I6-((I16-J16)+(I17-J17)+(I18-J18)) -> 137911.56 | K6: =J6-((J16-K16)+(J17-K17)+(J18-K18)) -> 132756.4 | L6: =K6-((K16-L16)+(K17-L17)+(K18-L18)) -> 128096.76 | ... O6: =N6-((N16-O16)+(N17-O17)+(N18-O18)) -> 116619.7
C7: Purchase Tax | D7: 0 | E7: 0 | F7: =F6*0.1 -> 16468.44 | G7: =G6*0.1 -> 15693.196 | H7: =H6*0.1 -> 14993.476 | I7: =I6*0.1 -> 14361.729 | J7: =J6*0.1 -> 13791.156 | K7: =K6*0.1 -> 13275.64 | L7: =L6*0.1 -> 12809.676 | M7: =M6*0.1 -> 12388.309 | ... O7: =O6*0.1 -> 11661.97
C8: Consumer Final Price | D8: =D6+D7 -> 182800 | E8: =E6+E7 -> 173276 | F8: =F6+F7 -> 181152.84 | G8: =G6+G7 -> 172625.16 | H8: =H6+H7 -> 164928.24 | I8: =I6+I7 -> 157979.02 | J8: =J6+J7 -> 151702.71 | K8: =K6+K7 -> 146032.04 | ... O8: =O6+O7 -> 128281.67
C9: Dealer Gross Profit(5%) | D9: =D6*0.05 -> 9140 | E9: =E6*0.05 -> 8663.8 | F9: =F6*0.05 -> 8234.22 | G9: =G6*0.05 -> 7846.598 | H9: =H6*0.05 -> 7496.7382 | I9: =I6*0.05 -> 7180.8644 | J9: =J6*0.05 -> 6895.5779 | K9: =K6*0.05 -> 6637.8201 | ... O9: =O6*0.05 -> 5830.985
C10: Range (km) | D10: 450 | E10: 450 | F10: 450 | G10: 450 | H10: 450 | I10: 450 | J10: 450 | K10: 450 | L10: 450 | M10: 450 | N10: 450 | O10: 450
C11: Battery (kwh) | D11: 60.2 | E11: 60.2 | F11: 60.2 | G11: 60.2 | H11: 60.2 | I11: 60.2 | J11: 60.2 | K11: 60.2 | L11: 60.2 | M11: 60.2 | N11: 60.2 | O11: 60.2
C12: Battery Price/wh | D12: 1.2 | E12: =D12*0.9 -> 1.08 | F12: =E12*0.9 -> 0.972 | G12: =F12*0.9 -> 0.8748 | H12: =G12*0.9 -> 0.78732 | I12: =H12*0.9 -> 0.708588 | J12: =I12*0.9 -> 0.6377292 | K12: =J12*0.9 -> 0.57395628 | L12: =K12*0.9 -> 0.51656065 | ... O12: =N12*0.9 -> 0.37657272
C13: Subsidies | D13: 34000 | E13: 35000 | F13: 0 | G13: 0 | H13: 0 | I13: 0 | J13: 0 | K13: 0 | L13: 0 | M13: 0 | N13: 0 | O13: 0
C14: Auto Company Revenue | D14: =D6-D9+D13 -> 207660 | E14: =E6-E9+E13 -> 199612.2 | F14: =F6-F9+F13 -> 156450.18 | G14: =G6-G9+G13 -> 149085.36 | H14: =H6-H9+H13 -> 142438.03 | I14: =I6-I9+I13 -> 136436.42 | J14: =J6-J9+J13 -> 131015.98 | K14: =K6-K9+K13 -> 126118.58 | ... O14: =O6-O9+O13 -> 110788.71
C15: Revenue (after vat) | D15: =D14*0.87 -> 180664.2 | E15: =E14*0.87 -> 173662.61 | F15: =F14*0.87 -> 136111.66 | G15: =G14*0.87 -> 129704.26 | H15: =H14*0.87 -> 123921.08 | I15: =I14*0.87 -> 118699.69 | J15: =J14*0.87 -> 113983.9 | K15: =K14*0.87 -> 109723.17 | ... O15: =O14*0.87 -> 96386.182
C16: Power Battery System Cost | D16: =D12*1000*D11 -> 72240 | E16: =E12*1000*E11 -> 65016 | F16: =F12*1000*F11 -> 58514.4 | G16: =G12*1000*G11 -> 52662.96 | H16: =H12*1000*H11 -> 47396.664 | I16: =I12*1000*I11 -> 42656.998 | J16: =J12*1000*J11 -> 38391.298 | K16: =K12*1000*K11 -> 34552.168 | ... O16: =O12*1000*O11 -> 22669.677
C17: Electric Motor & Electric Controlling | D17: 10000 | E17: =D17-200 -> 9800 | F17: =E17-200 -> 9600 | G17: =F17-200 -> 9400 | H17: =G17-200 -> 9200 | I17: =H17-200 -> 9000 | J17: =I17-200 -> 8800 | K17: =J17-200 -> 8600 | L17: =K17-200 -> 8400 | ... O17: =N17-200 -> 7800
C18: Other Cost | D18: 21000 | E18: =D18*0.9 -> 18900 | F18: =E18*0.9 -> 17010 | G18: =F18*0.9 -> 15309 | H18: =G18*0.9 -> 13778.1 | I18: =H18*0.9 -> 12400.29 | J18: =I18*0.9 -> 11160.261 | K18: =J18*0.9 -> 10044.235 | L18: =K18*0.9 -> 9039.8114 | ... O18: =N18*0.9 -> 6590.0225
C19: Profit Margin(BEV) | D19: =D15-D16-D17-D18 -> 77424.2 | E19: =E15-E16-E17-E18 -> 79946.614 | F19: =F15-F16-F17-F18 -> 50987.257 | G19: =G15-G16-G17-G18 -> 52332.305 | H19: =H15-H16-H17-H18 -> 53546.318 | I19: =I15-I16-I17-I18 -> 54642.401 | J19: =J15-J16-J17-J18 -> 55632.345 | K19: =K15-K16-K17-K18 -> 56526.764 | ... O19: =O15-O16-O17-O18 -> 59326.482
C20: PM/Revenue | D20: =D19/D14 -> 0.37284118 | E20: =E19/E14 -> 0.40050966 | F20: =F19/F14 -> 0.32590091 | G20: =G19/G14 -> 0.35102242 | H20: =H19/H14 -> 0.37592713 | I20: =I19/I14 -> 0.40049716 | J20: =J19/J14 -> 0.42462259 | K20: =K19/K14 -> 0.44820329 | ... O20: =O19/O14 -> 0.5354921
C21: BAIC D50
D22: 2019 | E22: 2020 | F22: 2021 | G22: 2022 | H22: 2023 | I22: 2024 | J22: 2025 | K22: 2026 | L22: 2027 | M22: 2028 | N22: 2029 | O22: 2030
C23: Retail Price | D23: 131400 | E23: =D23+(E29-D29)+(E30-D30) -> 131860 | F23: =E23+(F29-E29)+(F30-E30) -> 132329.2 | G23: =F23+(G29-F29)+(G30-F30) -> 132807.78 | H23: =G23+(H29-G29)+(H30-G30) -> 133295.94 | I23: =H23+(I29-H29)+(I30-H30) -> 133793.86 | J23: =I23+(J29-I29)+(J30-I30) -> 134301.74 | K23: =J23+(K29-J29)+(K30-J30) -> 134819.77 | L23: =K23+(L29-K29)+(L30-K30) -> 135348.17 | ... O23: =N23+(O29-N29)+(O30-N30) -> 136997.61
C24: Purchase Tax | D24: =D23*0.1 -> 13140 | E24: =E23*0.1 -> 13186 | F24: =F23*0.1 -> 13232.92 | G24: =G23*0.1 -> 13280.778 | H24: =H23*0.1 -> 13329.594 | I24: =I23*0.1 -> 13379.386 | J24: =J23*0.1 -> 13430.174 | K24: =K23*0.1 -> 13481.977 | ... O24: =O23*0.1 -> 13699.761
C25: Consumer Final Price | D25: =D23+D24 -> 144540 | E25: =E23+E24 -> 145046 | F25: =F23+F24 -> 145562.12 | G25: =G23+G24 -> 146088.56 | H25: =H23+H24 -> 146625.53 | I25: =I23+I24 -> 147173.24 | J25: =J23+J24 -> 147731.91 | K25: =K23+K24 -> 148301.75 | ... O25: =O23+O24 -> 150697.37
C26: Dealer Gross Profit (5%) | D26: =D23*0.05 -> 6570 | E26: =E23*0.05 -> 6593 | F26: =F23*0.05 -> 6616.46 | G26: =G23*0.05 -> 6640.3892 | H26: =H23*0.05 -> 6664.797 | I26: =I23*0.05 -> 6689.6929 | J26: =J23*0.05 -> 6715.0868 | K26: =K23*0.05 -> 6740.9885 | ... O26: =O23*0.05 -> 6849.8805
C27: Auto Company Revenue | D27: =D23-D26 -> 124830 | E27: =E23-E26 -> 125267 | F27: =F23-F26 -> 125712.74 | G27: =G23-G26 -> 126167.39 | H27: =H23-H26 -> 126631.14 | I27: =I23-I26 -> 127104.17 | J27: =J23-J26 -> 127586.65 | K27: =K23-K26 -> 128078.78 | ... O27: =O23-O26 -> 130147.73
C28: Revenue (after vat) | D28: =D27*0.87 -> 108602.1 | E28: =E27*0.87 -> 108982.29 | F28: =F27*0.87 -> 109370.08 | G28: =G27*0.87 -> 109765.63 | H28: =H27*0.87 -> 110169.09 | I28: =I27*0.87 -> 110580.62 | J28: =J27*0.87 -> 111000.38 | K28: =K27*0.87 -> 111428.54 | ... O28: =O27*0.87 -> 113228.52
C29: Motor Cost | D29: 15000 | E29: =D29*1.02 -> 15300 | F29: =E29*1.02 -> 15606 | G29: =F29*1.02 -> 15918.12 | H29: =G29*1.02 -> 16236.482 | I29: =H29*1.02 -> 16561.212 | J29: =I29*1.02 -> 16892.436 | K29: =J29*1.02 -> 17230.285 | L29: =K29*1.02 -> 17574.891 | ... O29: =N29*1.02 -> 18650.615
C30: Transmission Cost | D30: 8000 | E30: =D30*1.02 -> 8160 | F30: =E30*1.02 -> 8323.2 | G30: =F30*1.02 -> 8489.664 | H30: =G30*1.02 -> 8659.4573 | I30: =H30*1.02 -> 8832.6464 | J30: =I30*1.02 -> 9009.2994 | K30: =J30*1.02 -> 9189.4853 | L30: =K30*1.02 -> 9373.275 | ... O30: =N30*1.02 -> 9946.9945
C31: 48V System Cost | D31: 4000 | E31: 4000 | F31: 4000 | G31: 4000 | H31: 4000 | I31: 4000 | J31: 4000 | K31: 4000 | L31: 4000 | M31: 4000 | N31: 4000 | O31: 4000
C32: Other Cost | D32: 32000 | E32: 32000 | F32: 32000 | G32: 32000 | H32: 32000 | I32: 32000 | J32: 32000 | K32: 32000 | L32: 32000 | M32: 32000 | N32: 32000 | O32: 32000
C33: Profit Margin(ICEV) | D33: =D28-D29-D30-D31-D32 -> 49602.1 | E33: =E28-E29-E30-E31-E32 -> 49522.29 | F33: =F28-F29-F30-F31-F32 -> 49440.884 | G33: =G28-G29-G30-G31-G32 -> 49357.849 | H33: =H28-H29-H30-H31-H32 -> 49273.154 | I33: =I28-I29-I30-I31-I32 -> 49186.766 | J33: =J28-J29-J30-J31-J32 -> 49098.649 | K33: =K28-K29-K30-K31-K32 -> 49008.77 | ... O33: =O28-O29-O30-O31-O32 -> 48630.915
C34: PM/Revenue | D34: =D33/D27 -> 0.39735721 | E34: =E33/E27 -> 0.39533389 | F34: =F33/F27 -> 0.39328459 | G34: =G33/G27 -> 0.39120923 | H34: =H33/H27 -> 0.38910771 | I34: =I33/I27 -> 0.38697997 | J34: =J33/J27 -> 0.38482591 | K34: =K33/K27 -> 0.3826455 | ... O34: =O33/O27 -> 0.37365934
D36: 2019 | E36: 2020 | F36: 2021 | G36: 2022 | H36: 2023 | I36: 2024 | J36: 2025 | K36: 2026 | L36: 2027 | M36: 2028 | N36: 2029 | O36: 2030
D37: =D8-D25 -> 38260 | E37: =E8-E25 -> 28230 | F37: =F8-F25 -> 35590.72 | G37: =G8-G25 -> 26536.594 | H37: =H8-H25 -> 18302.707 | I37: =I8-I25 -> 10805.772 | J37: =J8-J25 -> 3970.8055 | K37: =K8-K25 -> -2269.7041 | ... O37: =O8-O25 -> -22415.7
B40: ICEV BEV | D40: BAIC EU 5 北汽EU5 | F40: JAC iEV7L 江淮iEV7L | H40: Roewe ei5 荣威ei5 | J40: GAC NE Aion S 广汽新能源AionS | L40: BYD Yuan EV360（SUV） 比亚迪 元 EV360 | N40: BYD Yuan EV（SUV） 比亚迪 元 EV | P40: BMW i3 宝马i3 | Q40: Volkswagen e-Golf 大众e高尔夫 | S40: Volkswagen e-Bora 大众e宝来 | U40: Hyundai ENCINO（SUV） 现代昂希诺纯电 | W40: Honda VE-1（SUV） 本田VE-1纯电 | Y40: Honda XNV（SUV） 本田XNV | AA40: Buick Velite 6 别克微蓝6
D41: 152400 | F41: 109150 | H41: 143800 | J41: 173300 | L41: 117900 | N41: 144350 | P41: 305800 | Q41: 158250 | S41: 141800 | U41: 207550 | W41: 169800 | Y41: 174800 | AA41: 182800 | AD41: =_xlfn.STDEV.P(D41,H41,J41,N41,Q41,S41,W41,Y41,AA41) -> 14571.842
B42: BAIC D50 北汽绅宝D50 | C42: 84900 | D42: 2029 | F42: 2022 | H42: 2028 | J42: Post 2030 | L42: 2023 | N42: 2028 | P42: Post 2030 | Q42: Post 2030 | S42: 2027 | U42: Post 2030 | W42: Post 2030 | Y42: Post 2030 | AA42: Post 2030
B44: JAC Heyue A30 江淮和悦A30 | C44: 62900 | D44: Post 2030 | F44: 2025 | H44: Post 2030 | J44: Post 2030 | L44: 2027 | N44: Post 2030 | P44: Post 2030 | Q44: Post 2030 | S44: Post 2030 | U44: Post 2030 | W44: Post 2030 | Y44: Post 2030 | AA44: Post 2030
B46: Roewe i5GL 荣威i5GL | C46: 107900 | D46: 2025 | F46: 2019 | H46: 2024 | J46: 2029 | L46: 2019 | N46: 2024 | P46: Post 2030 | Q46: 2026 | S46: 2023 | U46: Post 2030 | W46: 2028 | Y46: 2029 | AA46: Post 2030
B48: Roewe i6 Plus 荣威i6 Plus | C48: 114800 | D48: 2024 | F48: 2019 | H48: 2023 | J48: 2027 | L48: 2019 | N48: 2023 | P48: Post 2030 | Q48: 2025 | S48: 2022 | U48: Post 2030 | W48: 2027 | Y48: 2028 | AA48: 2030
B50: BYD Tang （SUV） 比亚迪唐 | C50: 149900 | D50: 2019 | F50: 2019 | H50: 2019 | J50: 2020 | L50: 2019 | N50: 2019 | P50: Post 2030 | Q50: 2019 | S50: 2019 | U50: 2027 | W50: 2020 | Y50: 2020 | AA50: 2023
B52: BYD Song （SUV） 比亚迪宋 | C52: 109850 | D52: 2025 | F52: 2019 | H52: 2023 | J52: 2029 | L52: 2019 | N52: 2023 | P52: Post 2030 | Q52: 2026 | S52: 2023 | U52: Post 2030 | W52: 2028 | Y52: 2029 | AA52: Post 2030
B54: BMW 1 宝马1系 | C54: 221300 | D54: 2019 | F54: 2019 | H54: 2019 | J54: 2019 | L54: 2019 | N54: 2019 | P54: Post 2030 | Q54: 2019 | S54: 2019 | U54: 2019 | W54: 2019 | Y54: 2019 | AA54: 2019
B56: BMW 2 宝马2系 | C56: 278800 | D56: 2019 | F56: 2019 | H56: 2019 | J56: 2019 | L56: 2019 | N56: 2019 | P56: 2019 | Q56: 2019 | S56: 2019 | U56: 2019 | W56: 2019 | Y56: 2019 | AA56: 2019
B58: Volkswagen Golf GTI 大众高尔夫GTI | C58: 222700 | D58: 2019 | F58: 2019 | H58: 2019 | J58: 2019 | L58: 2019 | N58: 2019 | P58: Post 2030 | Q58: 2019 | S58: 2019 | U58: 2019 | W58: 2019 | Y58: 2019 | AA58: 2019
B60: Volkswagen Bora 大众宝来 | C60: 133500 | D60: 2020 | F60: 2019 | H60: 2019 | J60: 2024 | L60: 2019 | N60: 2019 | P60: Post 2030 | Q60: 2022 | S60: 2019 | U60: Post 2030 | W60: 2024 | Y60: 2025 | AA60: 2026
B62: Hyundai Encore（SUV） 现代昂希诺 | C62: 142900 | D62: 2019 | F62: 2019 | H62: 2019 | J62: 2023 | L62: 2019 | N62: 2019 | P62: Post 2030 | Q62: 2020 | S62: 2019 | U62: 2028 | W62: 2022 | Y62: 2023 | AA62: 2024
B64: Honda VEZEL （SUV） 本田缤智 | C64: 152300 | D64: 2019 | F64: 2019 | H64: 2019 | J64: 2020 | L64: 2019 | N64: 2019 | P64: Post 2030 | Q64: 2019 | S64: 2019 | U64: 2027 | W64: 2020 | Y64: 2020 | AA64: 2023
B66: Buick EXCELLE GT 别克英朗 | C66: 131400 | D66: 2020 | F66: 2019 | H66: 2019 | J66: 2025 | L66: 2019 | N66: 2019 | P66: Post 2030 | Q66: 2022 | S66: 2019 | U66: Post 2030 | W66: 2024 | Y66: 2025 | AA66: 2026
C69: =_xlfn.STDEV.P(C46,C48,C50,C52,C54,C60,C62,C64,C66) -> 32585.674
A71: Short term | B71: 87 | C71: =B71/169 -> 0.5147929
A72: Middle term | B72: 25 | C72: =B72/169 -> 0.14792899
A73: Long term | B73: 57 | C73: =B73/169 -> 0.33727811
A75: BMW2 | S75: =AVERAGE(D41,H41,J41,N41,Q41,S41,W41,Y41,AA41) -> 160144.44
A76: VK GTI | Q76: =AVERAGE(C46,C48,C50,C52,C54,C60,C62,C64,C66) -> 140427.78
A77: BAIC D50
A78: JAC heyue
A80: BMWi3
A81: Hyundai Encore
A82: JAC iev7l
A83: BYD yuan EV360
A85: Short | B85: 42 | C85: =B85/81 -> 0.51851852
A86: Middle | B86: 23 | C86: =B86/81 -> 0.28395062
A87: Long | B87: 14 | C87: =B87/81 -> 0.17283951
A88: Post 2030 | B88: 2 | C88: =B88/81 -> 0.024691358

Sheet B
C4: BYD Qin Pro EV
D5: 2019 | E5: 2020 | F5: 2021 | G5: 2022 | H5: 2023 | I5: 2024 | J5: 2025 | K5: 2026 | L5: 2027 | M5: 2028 | N5: 2029 | O5: 2030
C6: Retail Price | D6: 174800 | E6: =D6-((D16-E16)+(D17-E17)+(D18-E18)) -> 162760 | F6: =E6-((E16-F16)+(E17-F17)+(E18-F18)) -> 151904 | G6: =F6-((F16-G16)+(F17-G17)+(F18-G18)) -> 142113.6 | H6: =G6-((G16-H16)+(G17-H17)+(G18-H18)) -> 133282.24 | I6: =H6-((H16-I16)+(H17-I17)+(H18-I18)) -> 125314.02 | J6: =I6-((I16-J16)+(I17-J17)+(I18-J18)) -> 118122.61 | K6: =J6-((J16-K16)+(J17-K17)+(J18-K18)) -> 111630.35 | L6: =K6-((K16-L16)+(K17-L17)+(K18-L18)) -> 105767.32 | ... O6: =N6-((N16-O16)+(N17-O17)+(N18-O18)) -> 91355.175
C7: Purchase Tax | D7: 0 | E7: 0 | F7: =F6*0.1 -> 15190.4 | G7: =G6*0.1 -> 14211.36 | H7: =H6*0.1 -> 13328.224 | I7: =I6*0.1 -> 12531.402 | J7: =J6*0.1 -> 11812.261 | K7: =K6*0.1 -> 11163.035 | L7: =L6*0.1 -> 10576.732 | M7: =M6*0.1 -> 10047.059 | ... O7: =O6*0.1 -> 9135.5175
C8: Consumer Final Price | D8: =D6+D7 -> 174800 | E8: =E6+E7 -> 162760 | F8: =F6+F7 -> 167094.4 | G8: =G6+G7 -> 156324.96 | H8: =H6+H7 -> 146610.46 | I8: =I6+I7 -> 137845.42 | J8: =J6+J7 -> 129934.88 | K8: =K6+K7 -> 122793.39 | ... O8: =O6+O7 -> 100490.69
C9: Dealer Gross Profit(5%) | D9: =D6*0.05 -> 8740 | E9: =E6*0.05 -> 8138 | F9: =F6*0.05 -> 7595.2 | G9: =G6*0.05 -> 7105.68 | H9: =H6*0.05 -> 6664.112 | I9: =I6*0.05 -> 6265.7008 | J9: =J6*0.05 -> 5906.1307 | K9: =K6*0.05 -> 5581.5176 | ... O9: =O6*0.05 -> 4567.7587
C10: Range (km) | D10: 420 | E10: 420 | F10: 420 | G10: 420 | H10: 420 | I10: 420 | J10: 420 | K10: 420 | L10: 420 | M10: 420 | N10: 420 | O10: 420
C11: Battery (kwh) | D11: 69.5 | E11: 69.5 | F11: 69.5 | G11: 69.5 | H11: 69.5 | I11: 69.5 | J11: 69.5 | K11: 69.5 | L11: 69.5 | M11: 69.5 | N11: 69.5 | O11: 69.5
C12: Battery Price/wh | D12: 1.2 | E12: =D12*0.9 -> 1.08 | F12: =E12*0.9 -> 0.972 | G12: =F12*0.9 -> 0.8748 | H12: =G12*0.9 -> 0.78732 | I12: =H12*0.9 -> 0.708588 | J12: =I12*0.9 -> 0.6377292 | K12: =J12*0.9 -> 0.57395628 | L12: =K12*0.9 -> 0.51656065 | ... O12: =N12*0.9 -> 0.37657272
C13: Subsidies | D13: 35000 | E13: 35000 | F13: 0 | G13: 0 | H13: 0 | I13: 0 | J13: 0 | K13: 0 | L13: 0 | M13: 0 | N13: 0 | O13: 0
C14: Auto Company Revenue | D14: =D6-D9+D13 -> 201060 | E14: =E6-E9+E13 -> 189622 | F14: =F6-F9+F13 -> 144308.8 | G14: =G6-G9+G13 -> 135007.92 | H14: =H6-H9+H13 -> 126618.13 | I14: =I6-I9+I13 -> 119048.32 | J14: =J6-J9+J13 -> 112216.48 | K14: =K6-K9+K13 -> 106048.84 | ... O14: =O6-O9+O13 -> 86787.416
C15: Revenue (after vat) | D15: =D14*0.87 -> 174922.2 | E15: =E14*0.87 -> 164971.14 | F15: =F14*0.87 -> 125548.66 | G15: =G14*0.87 -> 117456.89 | H15: =H14*0.87 -> 110157.77 | I15: =I14*0.87 -> 103572.03 | J15: =J14*0.87 -> 97628.341 | K15: =K14*0.87 -> 92262.487 | ... O15: =O14*0.87 -> 75505.052
C16: Power Battery System Cost | D16: =D12*1000*D11 -> 83400 | E16: =E12*1000*E11 -> 75060 | F16: =F12*1000*F11 -> 67554 | G16: =G12*1000*G11 -> 60798.6 | H16: =H12*1000*H11 -> 54718.74 | I16: =I12*1000*I11 -> 49246.866 | J16: =J12*1000*J11 -> 44322.179 | K16: =K12*1000*K11 -> 39889.961 | ... O16: =O12*1000*O11 -> 26171.804
C17: Electric Motor & Electric Controlling | D17: 15000 | E17: =D17-200 -> 14800 | F17: =E17-200 -> 14600 | G17: =F17-200 -> 14400 | H17: =G17-200 -> 14200 | I17: =H17-200 -> 14000 | J17: =I17-200 -> 13800 | K17: =J17-200 -> 13600 | L17: =K17-200 -> 13400 | ... O17: =N17-200 -> 12800
C18: Other Cost | D18: 35000 | E18: =D18*0.9 -> 31500 | F18: =E18*0.9 -> 28350 | G18: =F18*0.9 -> 25515 | H18: =G18*0.9 -> 22963.5 | I18: =H18*0.9 -> 20667.15 | J18: =I18*0.9 -> 18600.435 | K18: =J18*0.9 -> 16740.392 | L18: =K18*0.9 -> 15066.352 | ... O18: =N18*0.9 -> 10983.371
C19: Profit Margin(BEV) | D19: =D15-D16-D17-D18 -> 41522.2 | E19: =E15-E16-E17-E18 -> 43611.14 | F19: =F15-F16-F17-F18 -> 15044.656 | G19: =G15-G16-G17-G18 -> 16743.29 | H19: =H15-H16-H17-H18 -> 18275.531 | I19: =I15-I16-I17-I18 -> 19658.018 | J19: =J15-J16-J17-J18 -> 20905.726 | K19: =K15-K16-K17-K18 -> 22032.134 | ... O19: =O15-O16-O17-O18 -> 25549.877
C20: PM/Revenue | D20: =D19/D14 -> 0.20651646 | E20: =E19/E14 -> 0.22998987 | F20: =F19/F14 -> 0.10425321 | G20: =G19/G14 -> 0.1240171 | H20: =H19/H14 -> 0.14433582 | I20: =I19/I14 -> 0.16512639 | J20: =J19/J14 -> 0.18629818 | K20: =K19/K14 -> 0.2077546 | ... O20: =O19/O14 -> 0.29439611
C21: BYD Pro
D22: 2019 | E22: 2020 | F22: 2021 | G22: 2022 | H22: 2023 | I22: 2024 | J22: 2025 | K22: 2026 | L22: 2027 | M22: 2028 | N22: 2029 | O22: 2030
C23: Retail Price | D23: 115800 | E23: =D23+(E29-D29)+(E30-D30) -> 116400 | F23: =E23+(F29-E29)+(F30-E30) -> 117012 | G23: =F23+(G29-F29)+(G30-F30) -> 117636.24 | H23: =G23+(H29-G29)+(H30-G30) -> 118272.96 | I23: =H23+(I29-H29)+(I30-H30) -> 118922.42 | J23: =I23+(J29-I29)+(J30-I30) -> 119584.87 | K23: =J23+(K29-J29)+(K30-J30) -> 120260.57 | L23: =K23+(L29-K29)+(L30-K30) -> 120949.78 | ... O23: =N23+(O29-N29)+(O30-N30) -> 123101.23
C24: Purchase Tax | D24: =D23*0.1 -> 11580 | E24: =E23*0.1 -> 11640 | F24: =F23*0.1 -> 11701.2 | G24: =G23*0.1 -> 11763.624 | H24: =H23*0.1 -> 11827.296 | I24: =I23*0.1 -> 11892.242 | J24: =J23*0.1 -> 11958.487 | K24: =K23*0.1 -> 12026.057 | ... O24: =O23*0.1 -> 12310.123
C25: Consumer Final Price | D25: =D23+D24 -> 127380 | E25: =E23+E24 -> 128040 | F25: =F23+F24 -> 128713.2 | G25: =G23+G24 -> 129399.86 | H25: =H23+H24 -> 130100.26 | I25: =I23+I24 -> 130814.67 | J25: =J23+J24 -> 131543.36 | K25: =K23+K24 -> 132286.63 | ... O25: =O23+O24 -> 135411.35
C26: Dealer Gross Profit (5%) | D26: =D23*0.05 -> 5790 | E26: =E23*0.05 -> 5820 | F26: =F23*0.05 -> 5850.6 | G26: =G23*0.05 -> 5881.812 | H26: =H23*0.05 -> 5913.6482 | I26: =I23*0.05 -> 5946.1212 | J26: =J23*0.05 -> 5979.2436 | K26: =K23*0.05 -> 6013.0285 | ... O26: =O23*0.05 -> 6155.0615
C27: Auto Company Revenue | D27: =D23-D26 -> 110010 | E27: =E23-E26 -> 110580 | F27: =F23-F26 -> 111161.4 | G27: =G23-G26 -> 111754.43 | H27: =H23-H26 -> 112359.32 | I27: =I23-I26 -> 112976.3 | J27: =J23-J26 -> 113605.63 | K27: =K23-K26 -> 114247.54 | ... O27: =O23-O26 -> 116946.17
C28: Revenue (after vat) | D28: =D27*0.87 -> 95708.7 | E28: =E27*0.87 -> 96204.6 | F28: =F27*0.87 -> 96710.418 | G28: =G27*0.87 -> 97226.352 | H28: =H27*0.87 -> 97752.605 | I28: =I27*0.87 -> 98289.384 | J28: =J27*0.87 -> 98836.897 | K28: =K27*0.87 -> 99395.361 | ... O28: =O27*0.87 -> 101743.17
C29: Motor Cost | D29: 20000 | E29: =D29*1.02 -> 20400 | F29: =E29*1.02 -> 20808 | G29: =F29*1.02 -> 21224.16 | H29: =G29*1.02 -> 21648.643 | I29: =H29*1.02 -> 22081.616 | J29: =I29*1.02 -> 22523.248 | K29: =J29*1.02 -> 22973.713 | L29: =K29*1.02 -> 23433.188 | ... O29: =N29*1.02 -> 24867.486
C30: Transmission Cost | D30: 10000 | E30: =D30*1.02 -> 10200 | F30: =E30*1.02 -> 10404 | G30: =F30*1.02 -> 10612.08 | H30: =G30*1.02 -> 10824.322 | I30: =H30*1.02 -> 11040.808 | J30: =I30*1.02 -> 11261.624 | K30: =J30*1.02 -> 11486.857 | L30: =K30*1.02 -> 11716.594 | ... O30: =N30*1.02 -> 12433.743
C31: 48V System Cost | D31: 4000 | E31: 4000 | F31: 4000 | G31: 4000 | H31: 4000 | I31: 4000 | J31: 4000 | K31: 4000 | L31: 4000 | M31: 4000 | N31: 4000 | O31: 4000
C32: Other Cost | D32: 40000 | E32: 40000 | F32: 40000 | G32: 40000 | H32: 40000 | I32: 40000 | J32: 40000 | K32: 40000 | L32: 40000 | M32: 40000 | N32: 40000 | O32: 40000
C33: Profit Margin(ICEV) | D33: =D28-D29-D30-D31-D32 -> 21708.7 | E33: =E28-E29-E30-E31-E32 -> 21604.6 | F33: =F28-F29-F30-F31-F32 -> 21498.418 | G33: =G28-G29-G30-G31-G32 -> 21390.112 | H33: =H28-H29-H30-H31-H32 -> 21279.641 | I33: =I28-I29-I30-I31-I32 -> 21166.959 | J33: =J28-J29-J30-J31-J32 -> 21052.025 | K33: =K28-K29-K30-K31-K32 -> 20934.791 | ... O33: =O28-O29-O30-O31-O32 -> 20441.937
C34: PM/Revenue | D34: =D33/D27 -> 0.19733388 | E34: =E33/E27 -> 0.19537529 | F34: =F33/F27 -> 0.19339823 | G34: =G33/G27 -> 0.19140282 | H34: =H33/H27 -> 0.1893892 | I34: =I33/I27 -> 0.18735752 | J34: =J33/J27 -> 0.18530794 | K34: =K33/K27 -> 0.18324063 | ... O34: =O33/O27 -> 0.17479783

Sheet B class comparison
C4: BYD Qin Pro EV
D5: 2019 | E5: 2020 | F5: 2021 | G5: 2022 | H5: 2023 | I5: 2024 | J5: 2025 | K5: 2026 | L5: 2027 | M5: 2028 | N5: 2029 | O5: 2030
C6: Retail Price | D6: 134900 | E6: =D6-((D16-E16)+(D17-E17)+(D18-E18)) -> 122860 | F6: =E6-((E16-F16)+(E17-F17)+(E18-F18)) -> 112004 | G6: =F6-((F16-G16)+(F17-G17)+(F18-G18)) -> 102213.6 | H6: =G6-((G16-H16)+(G17-H17)+(G18-H18)) -> 93382.24 | I6: =H6-((H16-I16)+(H17-I17)+(H18-I18)) -> 85414.016 | J6: =I6-((I16-J16)+(I17-J17)+(I18-J18)) -> 78222.614 | K6: =J6-((J16-K16)+(J17-K17)+(J18-K18)) -> 71730.353 | L6: =K6-((K16-L16)+(K17-L17)+(K18-L18)) -> 65867.318 | ... O6: =N6-((N16-O16)+(N17-O17)+(N18-O18)) -> 51455.175
C7: Purchase Tax | D7: 0 | E7: 0 | F7: =F6*0.1 -> 11200.4 | G7: =G6*0.1 -> 10221.36 | H7: =H6*0.1 -> 9338.224 | I7: =I6*0.1 -> 8541.4016 | J7: =J6*0.1 -> 7822.2614 | K7: =K6*0.1 -> 7173.0353 | L7: =L6*0.1 -> 6586.7318 | M7: =M6*0.1 -> 6057.0586 | ... O7: =O6*0.1 -> 5145.5175
C8: Consumer Final Price | D8: =D6+D7 -> 134900 | E8: =E6+E7 -> 122860 | F8: =F6+F7 -> 123204.4 | G8: =G6+G7 -> 112434.96 | H8: =H6+H7 -> 102720.46 | I8: =I6+I7 -> 93955.418 | J8: =J6+J7 -> 86044.876 | K8: =K6+K7 -> 78903.388 | ... O8: =O6+O7 -> 56600.692
C9: Dealer Gross Profit(5%) | D9: =D6*0.05 -> 6745 | E9: =E6*0.05 -> 6143 | F9: =F6*0.05 -> 5600.2 | G9: =G6*0.05 -> 5110.68 | H9: =H6*0.05 -> 4669.112 | I9: =I6*0.05 -> 4270.7008 | J9: =J6*0.05 -> 3911.1307 | K9: =K6*0.05 -> 3586.5176 | ... O9: =O6*0.05 -> 2572.7587
C10: Range (km) | D10: 420 | E10: 420 | F10: 420 | G10: 420 | H10: 420 | I10: 420 | J10: 420 | K10: 420 | L10: 420 | M10: 420 | N10: 420 | O10: 420
C11: Battery (kwh) | D11: 69.5 | E11: 69.5 | F11: 69.5 | G11: 69.5 | H11: 69.5 | I11: 69.5 | J11: 69.5 | K11: 69.5 | L11: 69.5 | M11: 69.5 | N11: 69.5 | O11: 69.5
C12: Battery Price/wh | D12: 1.2 | E12: =D12*0.9 -> 1.08 | F12: =E12*0.9 -> 0.972 | G12: =F12*0.9 -> 0.8748 | H12: =G12*0.9 -> 0.78732 | I12: =H12*0.9 -> 0.708588 | J12: =I12*0.9 -> 0.6377292 | K12: =J12*0.9 -> 0.57395628 | L12: =K12*0.9 -> 0.51656065 | ... O12: =N12*0.9 -> 0.37657272
C13: Subsidies | D13: 35000 | E13: 35000 | F13: 0 | G13: 0 | H13: 0 | I13: 0 | J13: 0 | K13: 0 | L13: 0 | M13: 0 | N13: 0 | O13: 0
C14: Auto Company Revenue | D14: =D6-D9+D13 -> 163155 | E14: =E6-E9+E13 -> 151717 | F14: =F6-F9+F13 -> 106403.8 | G14: =G6-G9+G13 -> 97102.92 | H14: =H6-H9+H13 -> 88713.128 | I14: =I6-I9+I13 -> 81143.315 | J14: =J6-J9+J13 -> 74311.484 | K14: =K6-K9+K13 -> 68143.835 | ... O14: =O6-O9+O13 -> 48882.416
C15: Revenue (after vat) | D15: =D14*0.87 -> 141944.85 | E15: =E14*0.87 -> 131993.79 | F15: =F14*0.87 -> 92571.306 | G15: =G14*0.87 -> 84479.54 | H15: =H14*0.87 -> 77180.421 | I15: =I14*0.87 -> 70594.684 | J15: =J14*0.87 -> 64650.991 | K15: =K14*0.87 -> 59285.137 | ... O15: =O14*0.87 -> 42527.702
C16: Power Battery System Cost | D16: =D12*1000*D11 -> 83400 | E16: =E12*1000*E11 -> 75060 | F16: =F12*1000*F11 -> 67554 | G16: =G12*1000*G11 -> 60798.6 | H16: =H12*1000*H11 -> 54718.74 | I16: =I12*1000*I11 -> 49246.866 | J16: =J12*1000*J11 -> 44322.179 | K16: =K12*1000*K11 -> 39889.961 | ... O16: =O12*1000*O11 -> 26171.804
C17: Electric Motor & Electric Controlling | D17: 15000 | E17: =D17-200 -> 14800 | F17: =E17-200 -> 14600 | G17: =F17-200 -> 14400 | H17: =G17-200 -> 14200 | I17: =H17-200 -> 14000 | J17: =I17-200 -> 13800 | K17: =J17-200 -> 13600 | L17: =K17-200 -> 13400 | ... O17: =N17-200 -> 12800
C18: Other Cost | D18: 35000 | E18: =D18*0.9 -> 31500 | F18: =E18*0.9 -> 28350 | G18: =F18*0.9 -> 25515 | H18: =G18*0.9 -> 22963.5 | I18: =H18*0.9 -> 20667.15 | J18: =I18*0.9 -> 18600.435 | K18: =J18*0.9 -> 16740.392 | L18: =K18*0.9 -> 15066.352 | ... O18: =N18*0.9 -> 10983.371
C19: Profit Margin(BEV) | D19: =D15-D16-D17-D18 -> 8544.85 | E19: =E15-E16-E17-E18 -> 10633.79 | F19: =F15-F16-F17-F18 -> -17932.694 | G19: =G15-G16-G17-G18 -> -16234.06 | H19: =H15-H16-H17-H18 -> -14701.819 | I19: =I15-I16-I17-I18 -> -13319.332 | J19: =J15-J16-J17-J18 -> -12071.624 | K19: =K15-K16-K17-K18 -> -10945.216 | ... O19: =O15-O16-O17-O18 -> -7427.4728
C20: PM/Revenue | D20: =D19/D14 -> 0.05237259 | E20: =E19/E14 -> 0.070089641 | F20: =F19/F14 -> -0.16853434 | G20: =G19/G14 -> -0.16718405 | H20: =H19/H14 -> -0.16572315 | I20: =I19/I14 -> -0.16414577 | J20: =J19/J14 -> -0.16244627 | K20: =K19/K14 -> -0.16061932 | ... O20: =O19/O14 -> -0.1519457
C21: BYD Pro
D22: 2019 | E22: 2020 | F22: 2021 | G22: 2022 | H22: 2023 | I22: 2024 | J22: 2025 | K22: 2026 | L22: 2027 | M22: 2028 | N22: 2029 | O22: 2030
C23: Retail Price | D23: 137900 | E23: =D23+(E29-D29)+(E30-D30) -> 138500 | F23: =E23+(F29-E29)+(F30-E30) -> 139112 | G23: =F23+(G29-F29)+(G30-F30) -> 139736.24 | H23: =G23+(H29-G29)+(H30-G30) -> 140372.96 | I23: =H23+(I29-H29)+(I30-H30) -> 141022.42 | J23: =I23+(J29-I29)+(J30-I30) -> 141684.87 | K23: =J23+(K29-J29)+(K30-J30) -> 142360.57 | L23: =K23+(L29-K29)+(L30-K30) -> 143049.78 | ... O23: =N23+(O29-N29)+(O30-N30) -> 145201.23
C24: Purchase Tax | D24: =D23*0.1 -> 13790 | E24: =E23*0.1 -> 13850 | F24: =F23*0.1 -> 13911.2 | G24: =G23*0.1 -> 13973.624 | H24: =H23*0.1 -> 14037.296 | I24: =I23*0.1 -> 14102.242 | J24: =J23*0.1 -> 14168.487 | K24: =K23*0.1 -> 14236.057 | ... O24: =O23*0.1 -> 14520.123
C25: Consumer Final Price | D25: =D23+D24 -> 151690 | E25: =E23+E24 -> 152350 | F25: =F23+F24 -> 153023.2 | G25: =G23+G24 -> 153709.86 | H25: =H23+H24 -> 154410.26 | I25: =I23+I24 -> 155124.67 | J25: =J23+J24 -> 155853.36 | K25: =K23+K24 -> 156596.63 | ... O25: =O23+O24 -> 159721.35
C26: Dealer Gross Profit (5%) | D26: =D23*0.05 -> 6895 | E26: =E23*0.05 -> 6925 | F26: =F23*0.05 -> 6955.6 | G26: =G23*0.05 -> 6986.812 | H26: =H23*0.05 -> 7018.6482 | I26: =I23*0.05 -> 7051.1212 | J26: =J23*0.05 -> 7084.2436 | K26: =K23*0.05 -> 7118.0285 | ... O26: =O23*0.05 -> 7260.0615
C27: Auto Company Revenue | D27: =D23-D26 -> 131005 | E27: =E23-E26 -> 131575 | F27: =F23-F26 -> 132156.4 | G27: =G23-G26 -> 132749.43 | H27: =H23-H26 -> 133354.32 | I27: =I23-I26 -> 133971.3 | J27: =J23-J26 -> 134600.63 | K27: =K23-K26 -> 135242.54 | ... O27: =O23-O26 -> 137941.17
C28: Revenue (after vat) | D28: =D27*0.87 -> 113974.35 | E28: =E27*0.87 -> 114470.25 | F28: =F27*0.87 -> 114976.07 | G28: =G27*0.87 -> 115492 | H28: =H27*0.87 -> 116018.26 | I28: =I27*0.87 -> 116555.03 | J28: =J27*0.87 -> 117102.55 | K28: =K27*0.87 -> 117661.01 | ... O28: =O27*0.87 -> 120008.82
C29: Motor Cost | D29: 20000 | E29: =D29*1.02 -> 20400 | F29: =E29*1.02 -> 20808 | G29: =F29*1.02 -> 21224.16 | H29: =G29*1.02 -> 21648.643 | I29: =H29*1.02 -> 22081.616 | J29: =I29*1.02 -> 22523.248 | K29: =J29*1.02 -> 22973.713 | L29: =K29*1.02 -> 23433.188 | ... O29: =N29*1.02 -> 24867.486
C30: Transmission Cost | D30: 10000 | E30: =D30*1.02 -> 10200 | F30: =E30*1.02 -> 10404 | G30: =F30*1.02 -> 10612.08 | H30: =G30*1.02 -> 10824.322 | I30: =H30*1.02 -> 11040.808 | J30: =I30*1.02 -> 11261.624 | K30: =J30*1.02 -> 11486.857 | L30: =K30*1.02 -> 11716.594 | ... O30: =N30*1.02 -> 12433.743
C31: 48V System Cost | D31: 4000 | E31: 4000 | F31: 4000 | G31: 4000 | H31: 4000 | I31: 4000 | J31: 4000 | K31: 4000 | L31: 4000 | M31: 4000 | N31: 4000 | O31: 4000
C32: Other Cost | D32: 40000 | E32: 40000 | F32: 40000 | G32: 40000 | H32: 40000 | I32: 40000 | J32: 40000 | K32: 40000 | L32: 40000 | M32: 40000 | N32: 40000 | O32: 40000
C33: Profit Margin(ICEV) | D33: =D28-D29-D30-D31-D32 -> 39974.35 | E33: =E28-E29-E30-E31-E32 -> 39870.25 | F33: =F28-F29-F30-F31-F32 -> 39764.068 | G33: =G28-G29-G30-G31-G32 -> 39655.762 | H33: =H28-H29-H30-H31-H32 -> 39545.291 | I33: =I28-I29-I30-I31-I32 -> 39432.609 | J33: =J28-J29-J30-J31-J32 -> 39317.675 | K33: =K28-K29-K30-K31-K32 -> 39200.441 | ... O33: =O28-O29-O30-O31-O32 -> 38707.587
C34: PM/Revenue | D34: =D33/D27 -> 0.30513606 | E34: =E33/E27 -> 0.30302299 | F34: =F33/F27 -> 0.30088643 | G34: =G33/G27 -> 0.29872643 | H34: =H33/H27 -> 0.29654301 | I34: =I33/I27 -> 0.29433624 | J34: =J33/J27 -> 0.29210617 | K34: =K33/K27 -> 0.28985289 | ... O34: =O33/O27 -> 0.28060939
D35: =D8-D25 -> -16790 | E35: =E8-E25 -> -29490 | F35: =F8-F25 -> -29818.8 | G35: =G8-G25 -> -41274.904 | H35: =H8-H25 -> -51689.797 | I35: =I8-I25 -> -61169.249 | J35: =J8-J25 -> -69808.484 | K35: =K8-K25 -> -77693.239 | ... O35: =O8-O25 -> -103120.66
D36: 2019 | E36: 2020 | F36: 2021 | G36: 2022 | H36: 2023 | I36: 2024 | J36: 2025 | K36: 2026 | L36: 2027 | M36: 2028 | N36: 2029 | O36: 2030
B38: ICEV BEV | D38: BYD Qin Pro EV-Supreme 比亚迪秦Pro EV | E38: BYD QIN EV 比亚迪秦EV | F38: BYD QIN EV450 比亚迪秦EV450 | G38: BAIC EU7 北汽EU7 | H38: JAC iC5 江淮iC5 | I38: JAC iEVA50 江淮iEVA50 | J38: Nissan Sylphy 尼桑轩逸 | K38: GAC NE GE3 广汽新能源GE3 | L38: Tesla Model 3 特斯拉 Model 3 | M38: Hyundai lafesta ev 现代菲斯塔 | N38: Toyota IZOA 丰田奕泽 | O38: Ford Territory EV （SUV） 福特领界 | P38: Weltmeister EX6 （SUV） 威马EX6 | Q38: Weltmeister EX5 （SUV） 威马EX5 | R38: Roewe RX5 eMax （SUV） 荣威RX5 | S38: Changan EADO EV460 长安逸动EV460
D39: 199900 | E39: 164850 | F39: 184900 | G39: 167900 | H39: 167500 | I39: 142500 | J39: 169500 | K39: 163300 | L39: 404475 | M39: 186300 | N39: 174800 | O39: 202900 | P39: 214900 | Q39: 164800 | R39: 215800 | S39: 134900 | U39: =_xlfn.STDEV.P(Q39,P39,O39,N39,M39,K39,J39,H39,G39,F39,E39,D39) -> 16786.235
B40: BYD QIN PRO 比亚迪秦Pro | C40: 97800 | D40: Post 2030 | E40: 2026 | F40: 2030 | G40: 2027 | H40: 2027 | I40: 2024 | J40: 2027 | K40: 2026 | L40: Post 2030 | M40: 2030 | N40: 2029 | O40: Post 2030 | P40: Post 2030 | Q40: 2026 | R40: Post 2030 | S40: 2023
B41: BYD QIN 比亚迪秦 | C41: 73400 | D41: Post 2030 | E41: Post 2030 | F41: Post 2030 | G41: Post 2030 | H41: Post 2030 | I41: 2028 | J41: Post 2030 | K41: 2030 | L41: Post 2030 | M41: Post 2030 | N41: Post 2030 | O41: Post 2030 | P41: Post 2030 | Q41: Post 2030 | R41: Post 2030 | S41: 2026
B42: JAC Jiayue A5 江淮嘉悦A5 | C42: 100300 | D42: Post 2030 | E42: 2026 | F42: 2029 | G42: 2026 | H42: 2026 | I42: 2023 | J42: 2027 | K42: 2026 | L42: Post 2030 | M42: 2030 | N42: 2029 | O42: Post 2030 | P42: Post 2030 | Q42: 2026 | R42: Post 2030 | S42: 2023
B43: JAC S7 （SUV） 江淮瑞风 | C43: 124800 | D43: 2028 | E43: 2023 | F43: 2025 | G43: 2023 | H43: 2023 | I43: 2020 | J43: 2024 | K43: 2023 | L43: Post 2030 | M43: 2026 | N43: 2025 | O43: 2028 | P43: 2030 | Q43: 2023 | R43: Post 2030 | S43: 2019
B44: BAIC D70 北汽D70 | C44: 175800 | D44: 2020 | E44: 2019 | F44: 2019 | G44: 2019 | H44: 2019 | I44: 2019 | J44: 2019 | K44: 2019 | L44: Post 2030 | M44: 2019 | N44: 2019 | O44: 2020 | P44: 2023 | Q44: 2019 | R44: 2023 | S44: 2019
B45: Nissan Sylphy 1.6XE 尼桑轩逸1.6XE | C45: 126000 | D45: 2027 | E45: 2023 | F45: 2025 | G45: 2023 | H45: 2023 | I45: 2020 | J45: 2023 | K45: 2023 | L45: Post 2030 | M45: 2025 | N45: 2025 | O45: 2028 | P45: 2030 | Q45: 2023 | R45: 2030 | S45: 2019
B46: Nissan ALTIMA 2.0 XE 尼桑天籁 2.0 XE | C46: 224800 | D46: 2019 | E46: 2019 | F46: 2019 | G46: 2019 | H46: 2019 | I46: 2019 | J46: 2019 | K46: 2019 | L46: Post 2030 | M46: 2019 | N46: 2019 | O46: 2019 | P46: 2019 | Q46: 2019 | R46: 2019 | S46: 2019
B47: Roewe i6 Plus 荣威i6 Plus | C47: 129800 | D47: 2027 | E47: 2023 | F47: 2025 | G47: 2023 | H47: 2023 | I47: 2019 | J47: 2023 | K47: 2022 | L47: Post 2030 | M47: 2025 | N47: 2024 | O47: 2027 | P47: 2029 | Q47: 2023 | R47: 2030 | S47: 2019
B48: Hyundai LA FESTA 现代菲斯塔 | C48: 137300 | D48: 2026 | E48: 2022 | F48: 2024 | G48: 2022 | H48: 2022 | I48: 2019 | J48: 2022 | K48: 2020 | L48: Post 2030 | M48: 2024 | N48: 2024 | O48: 2026 | P48: 2028 | Q48: 2022 | R48: 2028 | S48: 2019
B49: Toyota Camry 丰田凯美瑞 | C49: 211300 | D49: 2019 | E49: 2019 | F49: 2019 | G49: 2019 | H49: 2019 | I49: 2019 | J49: 2019 | K49: 2019 | L49: Post 2030 | M49: 2019 | N49: 2019 | O49: 2019 | P49: 2019 | Q49: 2019 | R49: 2019 | S49: 2019
B50: Ford Frontier （SUV） 福特领界 | C50: 139300 | D50: 2026 | E50: 2020 | F50: 2024 | G50: 2022 | H50: 2022 | I50: 2019 | J50: 2022 | K50: 2020 | L50: Post 2030 | M50: 2024 | N50: 2023 | O50: 2026 | P50: 2028 | Q50: 2020 | R50: 2028 | S50: 2019
B51: Roewe RX5 MAX 荣威RX5 MAX | C51: 142300 | D51: 2025 | E51: 2020 | F51: 2023 | G51: 2020 | H51: 2020 | I51: 2019 | J51: 2022 | K51: 2020 | L51: Post 2030 | M51: 2024 | N51: 2023 | O51: 2026 | P51: 2027 | Q51: 2020 | R51: 2027 | S51: 2019
B52: Changan EADO XT 长安逸动XT | C52: 95900 | D52: Post 2030 | E52: 2027 | F52: 2030 | G52: 2027 | H52: 2027 | I52: 2024 | J52: 2027 | K52: 2026 | L52: Post 2030 | M52: 2030 | N52: 2029 | O52: Post 2030 | P52: Post 2030 | Q52: 2027 | R52: Post 2030 | S52: 2023
B53: Mazda AXELA （SUV） 马自达AXELA | C53: 137900 | D53: 2026 | E53: 2022 | F53: 2024 | G53: 2022 | H53: 2022 | I53: 2019 | J53: 2022 | K53: 2020 | L53: Post 2030 | M53: 2024 | N53: 2023 | O53: 2026 | P53: 2028 | Q53: 2022 | R53: 2028 | S53: 2019
B54: Mazda CX-5 （SUV） 马自达CX-5 | C54: 212800 | D54: 2019 | E54: 2019 | F54: 2019 | G54: 2019 | H54: 2019 | I54: 2019 | J54: 2019 | K54: 2019 | L54: Post 2030 | M54: 2019 | N54: 2019 | O54: 2019 | P54: 2019 | Q54: 2019 | R54: 2019 | S54: 2019
B55: Cadillac ATS-L 凯迪拉克 ATS-L | C55: 351300 | D55: 2019 | E55: 2019 | F55: 2019 | G55: 2019 | H55: 2019 | I55: 2019 | J55: 2019 | K55: 2019 | L55: 2025 | M55: 2019 | N55: 2019 | O55: 2019 | P55: 2019 | Q55: 2019 | R55: 2019 | S55: 2019
C57: =_xlfn.STDEV.P(C40,C42,C43,C44,C45,C47,C48,C49,C50,C51,C53,C54) -> 35724.521
A59: Short | B59: 112 | C59: =B59/256 -> 0.4375
A60: Middle | B60: 47 | C60: =B60/256 -> 0.18359375
A61: Long | B61: 97 | C61: =B61/256 -> 0.37890625
F62: =F64-2*C57 -> 73167.625 | J62: =J64-2*U39 -> 146556.7
A64: BYD Qin | F64: =AVERAGE(C40,C42,C43,C44,C45,C47,C48,C49,C50,C51,C53,C54) -> 144616.67 | J64: =AVERAGE(D39,E39,F39,G39,H39,J39,K39,M39,N39,O39,P39,Q39) -> 180129.17
A65: Changan EADO Xt
A66: Nissan Altima | F66: =F64+2*C57 -> 216065.71 | J66: =J64+2*U39 -> 213701.64
A67: Cadillac
A71: Tesla model 3
A72: Roewe RX5
A73: JAC IEVA50
A74: Changan
A78: Short | B78: 60 | C78: =B78/144 -> 0.41666667
A79: Middle | B79: 39 | C79: =B79/144 -> 0.27083333
A80: Long | B80: 39 | C80: =B80/144 -> 0.27083333
A81: Post 2030 | B81: 6 | C81: =B81/144 -> 0.041666667

Sheet C
C4: Audi e-tron 55 quattro
D5: 2019 | E5: 2020 | F5: 2021 | G5: 2022 | H5: 2023 | I5: 2024 | J5: 2025 | K5: 2026 | L5: 2027 | M5: 2028 | N5: 2029 | O5: 2030
C6: Retail Price | D6: 658800 | E6: =D6-((D16-E16)+(D17-E17)+(D18-E18)) -> 642200 | F6: =E6-((E16-F16)+(E17-F17)+(E18-F18)) -> 627240 | G6: =F6-((F16-G16)+(F17-G17)+(F18-G18)) -> 613756 | H6: =G6-((G16-H16)+(G17-H17)+(G18-H18)) -> 601600.4 | I6: =H6-((H16-I16)+(H17-I17)+(H18-I18)) -> 590640.36 | J6: =I6-((I16-J16)+(I17-J17)+(I18-J18)) -> 580756.32 | K6: =J6-((J16-K16)+(J17-K17)+(J18-K18)) -> 571840.69 | L6: =K6-((K16-L16)+(K17-L17)+(K18-L18)) -> 563796.62 | ... O6: =N6-((N16-O16)+(N17-O17)+(N18-O18)) -> 544064.94
C7: Purchase Tax | D7: 0 | E7: 0 | F7: =F6*0.1 -> 62724 | G7: =G6*0.1 -> 61375.6 | H7: =H6*0.1 -> 60160.04 | I7: =I6*0.1 -> 59064.036 | J7: =J6*0.1 -> 58075.632 | K7: =K6*0.1 -> 57184.069 | L7: =L6*0.1 -> 56379.662 | M7: =M6*0.1 -> 55653.696 | ... O7: =O6*0.1 -> 54406.494
C8: Consumer Final Price | D8: =D6+D7 -> 658800 | E8: =E6+E7 -> 642200 | F8: =F6+F7 -> 689964 | G8: =G6+G7 -> 675131.6 | H8: =H6+H7 -> 661760.44 | I8: =I6+I7 -> 649704.4 | J8: =J6+J7 -> 638831.96 | K8: =K6+K7 -> 629024.76 | ... O8: =O6+O7 -> 598471.43
C9: Dealer Gross Profit(5%) | D9: =D6*0.05 -> 32940 | E9: =E6*0.05 -> 32110 | F9: =F6*0.05 -> 31362 | G9: =G6*0.05 -> 30687.8 | H9: =H6*0.05 -> 30080.02 | I9: =I6*0.05 -> 29532.018 | J9: =J6*0.05 -> 29037.816 | K9: =K6*0.05 -> 28592.035 | ... O9: =O6*0.05 -> 27203.247
C10: Range (km) | D10: 470 | E10: 470 | F10: 470 | G10: 470 | H10: 470 | I10: 470 | J10: 470 | K10: 470 | L10: 470 | M10: 470 | N10: 470 | O10: 470
C11: Battery (kwh) | D11: 95 | E11: 95 | F11: 95 | G11: 95 | H11: 95 | I11: 95 | J11: 95 | K11: 95 | L11: 95 | M11: 95 | N11: 95 | O11: 95
C12: Battery Price/wh | D12: 1.2 | E12: =D12*0.9 -> 1.08 | F12: =E12*0.9 -> 0.972 | G12: =F12*0.9 -> 0.8748 | H12: =G12*0.9 -> 0.78732 | I12: =H12*0.9 -> 0.708588 | J12: =I12*0.9 -> 0.6377292 | K12: =J12*0.9 -> 0.57395628 | L12: =K12*0.9 -> 0.51656065 | ... O12: =N12*0.9 -> 0.37657272
C13: Subsidies | D13: 35000 | E13: 35000 | F13: 0 | G13: 0 | H13: 0 | I13: 0 | J13: 0 | K13: 0 | L13: 0 | M13: 0 | N13: 0 | O13: 0
C14: Auto Company Revenue | D14: =D6-D9+D13 -> 660860 | E14: =E6-E9+E13 -> 645090 | F14: =F6-F9+F13 -> 595878 | G14: =G6-G9+G13 -> 583068.2 | H14: =H6-H9+H13 -> 571520.38 | I14: =I6-I9+I13 -> 561108.34 | J14: =J6-J9+J13 -> 551718.51 | K14: =K6-K9+K13 -> 543248.66 | ... O14: =O6-O9+O13 -> 516861.69
C15: Revenue (after vat) | D15: =D14*0.87 -> 574948.2 | E15: =E14*0.87 -> 561228.3 | F15: =F14*0.87 -> 518413.86 | G15: =G14*0.87 -> 507269.33 | H15: =H14*0.87 -> 497222.73 | I15: =I14*0.87 -> 488164.26 | J15: =J14*0.87 -> 479995.1 | K15: =K14*0.87 -> 472626.33 | ... O15: =O14*0.87 -> 449669.67
C16: Power Battery System Cost | D16: =D12*1000*D11 -> 114000 | E16: =E12*1000*E11 -> 102600 | F16: =F12*1000*F11 -> 92340 | G16: =G12*1000*G11 -> 83106 | H16: =H12*1000*H11 -> 74795.4 | I16: =I12*1000*I11 -> 67315.86 | J16: =J12*1000*J11 -> 60584.274 | K16: =K12*1000*K11 -> 54525.847 | ... O16: =O12*1000*O11 -> 35774.408
C17: Electric Motor & Electric Controlling | D17: 30000 | E17: =D17-200 -> 29800 | F17: =E17-200 -> 29600 | G17: =F17-200 -> 29400 | H17: =G17-200 -> 29200 | I17: =H17-200 -> 29000 | J17: =I17-200 -> 28800 | K17: =J17-200 -> 28600 | L17: =K17-200 -> 28400 | ... O17: =N17-200 -> 27800
C18: Other Cost | D18: 50000 | E18: =D18*0.9 -> 45000 | F18: =E18*0.9 -> 40500 | G18: =F18*0.9 -> 36450 | H18: =G18*0.9 -> 32805 | I18: =H18*0.9 -> 29524.5 | J18: =I18*0.9 -> 26572.05 | K18: =J18*0.9 -> 23914.845 | L18: =K18*0.9 -> 21523.361 | ... O18: =N18*0.9 -> 15690.53
C19: Profit Margin(BEV) | D19: =D15-D16-D17-D18 -> 380948.2 | E19: =E15-E16-E17-E18 -> 383828.3 | F19: =F15-F16-F17-F18 -> 355973.86 | G19: =G15-G16-G17-G18 -> 358313.33 | H19: =H15-H16-H17-H18 -> 360422.33 | I19: =I15-I16-I17-I18 -> 362323.9 | J19: =J15-J16-J17-J18 -> 364038.78 | K19: =K15-K16-K17-K18 -> 365585.64 | ... O19: =O15-O16-O17-O18 -> 370404.73
C20: PM/Revenue | D20: =D19/D14 -> 0.57644312 | E20: =E19/E14 -> 0.59499961 | F20: =F19/F14 -> 0.59739386 | G20: =G19/G14 -> 0.61453074 | H20: =H19/H14 -> 0.63063776 | I20: =I19/I14 -> 0.64572894 | J20: =J19/J14 -> 0.65982702 | K20: =K19/K14 -> 0.67296188 | ... O20: =O19/O14 -> 0.71664188
C21: Audi A6 all-road quattro
D22: 2019 | E22: 2020 | F22: 2021 | G22: 2022 | H22: 2023 | I22: 2024 | J22: 2025 | K22: 2026 | L22: 2027 | M22: 2028 | N22: 2029 | O22: 2030
C23: Retail Price | D23: 546800 | E23: =D23+(E29-D29)+(E30-D30) -> 549400 | F23: =E23+(F29-E29)+(F30-E30) -> 552052 | G23: =F23+(G29-F29)+(G30-F30) -> 554757.04 | H23: =G23+(H29-G29)+(H30-G30) -> 557516.18 | I23: =H23+(I29-H29)+(I30-H30) -> 560330.5 | J23: =I23+(J29-I29)+(J30-I30) -> 563201.11 | K23: =J23+(K29-J29)+(K30-J30) -> 566129.14 | L23: =K23+(L29-K29)+(L30-K30) -> 569115.72 | ... O23: =N23+(O29-N29)+(O30-N30) -> 578438.66
C24: Purchase Tax | D24: =D23*0.1 -> 54680 | E24: =E23*0.1 -> 54940 | F24: =F23*0.1 -> 55205.2 | G24: =G23*0.1 -> 55475.704 | H24: =H23*0.1 -> 55751.618 | I24: =I23*0.1 -> 56033.05 | J24: =J23*0.1 -> 56320.111 | K24: =K23*0.1 -> 56612.914 | ... O24: =O23*0.1 -> 57843.866
C25: Consumer Final Price | D25: =D23+D24 -> 601480 | E25: =E23+E24 -> 604340 | F25: =F23+F24 -> 607257.2 | G25: =G23+G24 -> 610232.74 | H25: =H23+H24 -> 613267.8 | I25: =I23+I24 -> 616363.55 | J25: =J23+J24 -> 619521.23 | K25: =K23+K24 -> 622742.05 | ... O25: =O23+O24 -> 636282.53
C26: Dealer Gross Profit (5%) | D26: =D23*0.05 -> 27340 | E26: =E23*0.05 -> 27470 | F26: =F23*0.05 -> 27602.6 | G26: =G23*0.05 -> 27737.852 | H26: =H23*0.05 -> 27875.809 | I26: =I23*0.05 -> 28016.525 | J26: =J23*0.05 -> 28160.056 | K26: =K23*0.05 -> 28306.457 | ... O26: =O23*0.05 -> 28921.933
C27: Auto Company Revenue | D27: =D23-D26 -> 519460 | E27: =E23-E26 -> 521930 | F27: =F23-F26 -> 524449.4 | G27: =G23-G26 -> 527019.19 | H27: =H23-H26 -> 529640.37 | I27: =I23-I26 -> 532313.98 | J27: =J23-J26 -> 535041.06 | K27: =K23-K26 -> 537822.68 | ... O27: =O23-O26 -> 549516.73
C28: Revenue (after vat) | D28: =D27*0.87 -> 451930.2 | E28: =E27*0.87 -> 454079.1 | F28: =F27*0.87 -> 456270.98 | G28: =G27*0.87 -> 458506.69 | H28: =H27*0.87 -> 460787.12 | I28: =I27*0.87 -> 463113.16 | J28: =J27*0.87 -> 465485.72 | K28: =K27*0.87 -> 467905.73 | ... O28: =O27*0.87 -> 478079.55
C29: Motor Cost | D29: 80000 | E29: =D29*1.02 -> 81600 | F29: =E29*1.02 -> 83232 | G29: =F29*1.02 -> 84896.64 | H29: =G29*1.02 -> 86594.573 | I29: =H29*1.02 -> 88326.464 | J29: =I29*1.02 -> 90092.994 | K29: =J29*1.02 -> 91894.853 | L29: =K29*1.02 -> 93732.75 | ... O29: =N29*1.02 -> 99469.945
C30: Transmission Cost | D30: 50000 | E30: =D30*1.02 -> 51000 | F30: =E30*1.02 -> 52020 | G30: =F30*1.02 -> 53060.4 | H30: =G30*1.02 -> 54121.608 | I30: =H30*1.02 -> 55204.04 | J30: =I30*1.02 -> 56308.121 | K30: =J30*1.02 -> 57434.283 | L30: =K30*1.02 -> 58582.969 | ... O30: =N30*1.02 -> 62168.715
C31: 48V System Cost | D31: 10000 | E31: 10000 | F31: 10000 | G31: 10000 | H31: 10000 | I31: 10000 | J31: 10000 | K31: 10000 | L31: 10000 | M31: 10000 | N31: 10000 | O31: 10000
C32: Other Cost | D32: 80000 | E32: 80000 | F32: 80000 | G32: 80000 | H32: 80000 | I32: 80000 | J32: 80000 | K32: 80000 | L32: 80000 | M32: 80000 | N32: 80000 | O32: 80000
C33: Profit Margin(ICEV) | D33: =D28-D29-D30-D31-D32 -> 231930.2 | E33: =E28-E29-E30-E31-E32 -> 231479.1 | F33: =F28-F29-F30-F31-F32 -> 231018.98 | G33: =G28-G29-G30-G31-G32 -> 230549.65 | H33: =H28-H29-H30-H31-H32 -> 230070.94 | I33: =I28-I29-I30-I31-I32 -> 229582.66 | J33: =J28-J29-J30-J31-J32 -> 229084.61 | K33: =K28-K29-K30-K31-K32 -> 228576.59 | ... O33: =O28-O29-O30-O31-O32 -> 226440.89
C34: PM/Revenue | D34: =D33/D27 -> 0.44648327 | E34: =E33/E27 -> 0.44350603 | F34: =F33/F27 -> 0.44049813 | G34: =G33/G27 -> 0.4374597 | H34: =H33/H27 -> 0.43439087 | I34: =I33/I27 -> 0.43129181 | J34: =J33/J27 -> 0.42816267 | K34: =K33/K27 -> 0.42500364 | ... O34: =O33/O27 -> 0.41207279

Sheet C class comparison
C4: Audi e-tron 55 quattro
D5: 2019 | E5: 2020 | F5: 2021 | G5: 2022 | H5: 2023 | I5: 2024 | J5: 2025 | K5: 2026 | L5: 2027 | M5: 2028 | N5: 2029 | O5: 2030
C6: Retail Price | D6: 288800 | E6: =D6-((D16-E16)+(D17-E17)+(D18-E18)) -> 272200 | F6: =E6-((E16-F16)+(E17-F17)+(E18-F18)) -> 257240 | G6: =F6-((F16-G16)+(F17-G17)+(F18-G18)) -> 243756 | H6: =G6-((G16-H16)+(G17-H17)+(G18-H18)) -> 231600.4 | I6: =H6-((H16-I16)+(H17-I17)+(H18-I18)) -> 220640.36 | J6: =I6-((I16-J16)+(I17-J17)+(I18-J18)) -> 210756.32 | K6: =J6-((J16-K16)+(J17-K17)+(J18-K18)) -> 201840.69 | L6: =K6-((K16-L16)+(K17-L17)+(K18-L18)) -> 193796.62 | ... O6: =N6-((N16-O16)+(N17-O17)+(N18-O18)) -> 174064.94
C7: Purchase Tax | D7: 0 | E7: 0 | F7: =F6*0.1 -> 25724 | G7: =G6*0.1 -> 24375.6 | H7: =H6*0.1 -> 23160.04 | I7: =I6*0.1 -> 22064.036 | J7: =J6*0.1 -> 21075.632 | K7: =K6*0.1 -> 20184.069 | L7: =L6*0.1 -> 19379.662 | M7: =M6*0.1 -> 18653.696 | ... O7: =O6*0.1 -> 17406.494
C8: Consumer Final Price | D8: =D6+D7 -> 288800 | E8: =E6+E7 -> 272200 | F8: =F6+F7 -> 282964 | G8: =G6+G7 -> 268131.6 | H8: =H6+H7 -> 254760.44 | I8: =I6+I7 -> 242704.4 | J8: =J6+J7 -> 231831.96 | K8: =K6+K7 -> 222024.76 | ... O8: =O6+O7 -> 191471.43
C9: Dealer Gross Profit(5%) | D9: =D6*0.05 -> 14440 | E9: =E6*0.05 -> 13610 | F9: =F6*0.05 -> 12862 | G9: =G6*0.05 -> 12187.8 | H9: =H6*0.05 -> 11580.02 | I9: =I6*0.05 -> 11032.018 | J9: =J6*0.05 -> 10537.816 | K9: =K6*0.05 -> 10092.035 | ... O9: =O6*0.05 -> 8703.2469
C10: Range (km) | D10: 470 | E10: 470 | F10: 470 | G10: 470 | H10: 470 | I10: 470 | J10: 470 | K10: 470 | L10: 470 | M10: 470 | N10: 470 | O10: 470
C11: Battery (kwh) | D11: 95 | E11: 95 | F11: 95 | G11: 95 | H11: 95 | I11: 95 | J11: 95 | K11: 95 | L11: 95 | M11: 95 | N11: 95 | O11: 95
C12: Battery Price/wh | D12: 1.2 | E12: =D12*0.9 -> 1.08 | F12: =E12*0.9 -> 0.972 | G12: =F12*0.9 -> 0.8748 | H12: =G12*0.9 -> 0.78732 | I12: =H12*0.9 -> 0.708588 | J12: =I12*0.9 -> 0.6377292 | K12: =J12*0.9 -> 0.57395628 | L12: =K12*0.9 -> 0.51656065 | ... O12: =N12*0.9 -> 0.37657272
C13: Subsidies | D13: 35000 | E13: 35000 | F13: 0 | G13: 0 | H13: 0 | I13: 0 | J13: 0 | K13: 0 | L13: 0 | M13: 0 | N13: 0 | O13: 0
C14: Auto Company Revenue | D14: =D6-D9+D13 -> 309360 | E14: =E6-E9+E13 -> 293590 | F14: =F6-F9+F13 -> 244378 | G14: =G6-G9+G13 -> 231568.2 | H14: =H6-H9+H13 -> 220020.38 | I14: =I6-I9+I13 -> 209608.34 | J14: =J6-J9+J13 -> 200218.51 | K14: =K6-K9+K13 -> 191748.66 | ... O14: =O6-O9+O13 -> 165361.69
C15: Revenue (after vat) | D15: =D14*0.87 -> 269143.2 | E15: =E14*0.87 -> 255423.3 | F15: =F14*0.87 -> 212608.86 | G15: =G14*0.87 -> 201464.33 | H15: =H14*0.87 -> 191417.73 | I15: =I14*0.87 -> 182359.26 | J15: =J14*0.87 -> 174190.1 | K15: =K14*0.87 -> 166821.33 | ... O15: =O14*0.87 -> 143864.67
C16: Power Battery System Cost | D16: =D12*1000*D11 -> 114000 | E16: =E12*1000*E11 -> 102600 | F16: =F12*1000*F11 -> 92340 | G16: =G12*1000*G11 -> 83106 | H16: =H12*1000*H11 -> 74795.4 | I16: =I12*1000*I11 -> 67315.86 | J16: =J12*1000*J11 -> 60584.274 | K16: =K12*1000*K11 -> 54525.847 | ... O16: =O12*1000*O11 -> 35774.408
C17: Electric Motor & Electric Controlling | D17: 30000 | E17: =D17-200 -> 29800 | F17: =E17-200 -> 29600 | G17: =F17-200 -> 29400 | H17: =G17-200 -> 29200 | I17: =H17-200 -> 29000 | J17: =I17-200 -> 28800 | K17: =J17-200 -> 28600 | L17: =K17-200 -> 28400 | ... O17: =N17-200 -> 27800
C18: Other Cost | D18: 50000 | E18: =D18*0.9 -> 45000 | F18: =E18*0.9 -> 40500 | G18: =F18*0.9 -> 36450 | H18: =G18*0.9 -> 32805 | I18: =H18*0.9 -> 29524.5 | J18: =I18*0.9 -> 26572.05 | K18: =J18*0.9 -> 23914.845 | L18: =K18*0.9 -> 21523.361 | ... O18: =N18*0.9 -> 15690.53
C19: Profit Margin(BEV) | D19: =D15-D16-D17-D18 -> 75143.2 | E19: =E15-E16-E17-E18 -> 78023.3 | F19: =F15-F16-F17-F18 -> 50168.86 | G19: =G15-G16-G17-G18 -> 52508.334 | H19: =H15-H16-H17-H18 -> 54617.331 | I19: =I15-I16-I17-I18 -> 56518.898 | J19: =J15-J16-J17-J18 -> 58233.778 | K19: =K15-K16-K17-K18 -> 59780.64 | ... O19: =O15-O16-O17-O18 -> 64599.733
C20: PM/Revenue | D20: =D19/D14 -> 0.24289889 | E20: =E19/E14 -> 0.26575599 | F20: =F19/F14 -> 0.20529205 | G20: =G19/G14 -> 0.22675106 | H20: =H19/H14 -> 0.2482376 | I20: =I19/I14 -> 0.2696405 | J20: =J19/J14 -> 0.29085112 | K20: =K19/K14 -> 0.31176563 | ... O20: =O19/O14 -> 0.39065719
C21: Audi A6 all-road quattro
D22: 2019 | E22: 2020 | F22: 2021 | G22: 2022 | H22: 2023 | I22: 2024 | J22: 2025 | K22: 2026 | L22: 2027 | M22: 2028 | N22: 2029 | O22: 2030
C23: Retail Price | D23: 282800 | E23: =D23+(E29-D29)+(E30-D30) -> 285400 | F23: =E23+(F29-E29)+(F30-E30) -> 288052 | G23: =F23+(G29-F29)+(G30-F30) -> 290757.04 | H23: =G23+(H29-G29)+(H30-G30) -> 293516.18 | I23: =H23+(I29-H29)+(I30-H30) -> 296330.5 | J23: =I23+(J29-I29)+(J30-I30) -> 299201.11 | K23: =J23+(K29-J29)+(K30-J30) -> 302129.14 | L23: =K23+(L29-K29)+(L30-K30) -> 305115.72 | ... O23: =N23+(O29-N29)+(O30-N30) -> 314438.66
C24: Purchase Tax | D24: =D23*0.1 -> 28280 | E24: =E23*0.1 -> 28540 | F24: =F23*0.1 -> 28805.2 | G24: =G23*0.1 -> 29075.704 | H24: =H23*0.1 -> 29351.618 | I24: =I23*0.1 -> 29633.05 | J24: =J23*0.1 -> 29920.111 | K24: =K23*0.1 -> 30212.914 | ... O24: =O23*0.1 -> 31443.866
C25: Consumer Final Price | D25: =D23+D24 -> 311080 | E25: =E23+E24 -> 313940 | F25: =F23+F24 -> 316857.2 | G25: =G23+G24 -> 319832.74 | H25: =H23+H24 -> 322867.8 | I25: =I23+I24 -> 325963.55 | J25: =J23+J24 -> 329121.23 | K25: =K23+K24 -> 332342.05 | ... O25: =O23+O24 -> 345882.53
C26: Dealer Gross Profit (5%) | D26: =D23*0.05 -> 14140 | E26: =E23*0.05 -> 14270 | F26: =F23*0.05 -> 14402.6 | G26: =G23*0.05 -> 14537.852 | H26: =H23*0.05 -> 14675.809 | I26: =I23*0.05 -> 14816.525 | J26: =J23*0.05 -> 14960.056 | K26: =K23*0.05 -> 15106.457 | ... O26: =O23*0.05 -> 15721.933
C27: Auto Company Revenue | D27: =D23-D26 -> 268660 | E27: =E23-E26 -> 271130 | F27: =F23-F26 -> 273649.4 | G27: =G23-G26 -> 276219.19 | H27: =H23-H26 -> 278840.37 | I27: =I23-I26 -> 281513.98 | J27: =J23-J26 -> 284241.06 | K27: =K23-K26 -> 287022.68 | ... O27: =O23-O26 -> 298716.73
C28: Revenue (after vat) | D28: =D27*0.87 -> 233734.2 | E28: =E27*0.87 -> 235883.1 | F28: =F27*0.87 -> 238074.98 | G28: =G27*0.87 -> 240310.69 | H28: =H27*0.87 -> 242591.12 | I28: =I27*0.87 -> 244917.16 | J28: =J27*0.87 -> 247289.72 | K28: =K27*0.87 -> 249709.73 | ... O28: =O27*0.87 -> 259883.55
C29: Motor Cost | D29: 80000 | E29: =D29*1.02 -> 81600 | F29: =E29*1.02 -> 83232 | G29: =F29*1.02 -> 84896.64 | H29: =G29*1.02 -> 86594.573 | I29: =H29*1.02 -> 88326.464 | J29: =I29*1.02 -> 90092.994 | K29: =J29*1.02 -> 91894.853 | L29: =K29*1.02 -> 93732.75 | ... O29: =N29*1.02 -> 99469.945
C30: Transmission Cost | D30: 50000 | E30: =D30*1.02 -> 51000 | F30: =E30*1.02 -> 52020 | G30: =F30*1.02 -> 53060.4 | H30: =G30*1.02 -> 54121.608 | I30: =H30*1.02 -> 55204.04 | J30: =I30*1.02 -> 56308.121 | K30: =J30*1.02 -> 57434.283 | L30: =K30*1.02 -> 58582.969 | ... O30: =N30*1.02 -> 62168.715
C31: 48V System Cost | D31: 10000 | E31: 10000 | F31: 10000 | G31: 10000 | H31: 10000 | I31: 10000 | J31: 10000 | K31: 10000 | L31: 10000 | M31: 10000 | N31: 10000 | O31: 10000
C32: Other Cost | D32: 80000 | E32: 80000 | F32: 80000 | G32: 80000 | H32: 80000 | I32: 80000 | J32: 80000 | K32: 80000 | L32: 80000 | M32: 80000 | N32: 80000 | O32: 80000
C33: Profit Margin(ICEV) | D33: =D28-D29-D30-D31-D32 -> 13734.2 | E33: =E28-E29-E30-E31-E32 -> 13283.1 | F33: =F28-F29-F30-F31-F32 -> 12822.978 | G33: =G28-G29-G30-G31-G32 -> 12353.654 | H33: =H28-H29-H30-H31-H32 -> 11874.943 | I33: =I28-I29-I30-I31-I32 -> 11386.657 | J33: =J28-J29-J30-J31-J32 -> 10888.607 | K33: =K28-K29-K30-K31-K32 -> 10380.595 | ... O33: =O28-O29-O30-O31-O32 -> 8244.8925
C34: PM/Revenue | D34: =D33/D27 -> 0.05112112 | E34: =E33/E27 -> 0.048991628 | F34: =F33/F27 -> 0.046859149 | G34: =G33/G27 -> 0.044724096 | H34: =H33/H27 -> 0.042586884 | I34: =I33/I27 -> 0.040447929 | J34: =J33/J27 -> 0.038307649 | K34: =K33/K27 -> 0.036166462 | ... O34: =O33/O27 -> 0.02760104
D35: 2019 | E35: 2020 | F35: 2021 | G35: 2022 | H35: 2023 | I35: 2024 | J35: 2025 | K35: 2026 | L35: 2027 | M35: 2028 | N35: 2029 | O35: 2030
D36: =D8-D25 -> -22280 | E36: =E8-E25 -> -41740 | F36: =F8-F25 -> -33893.2 | G36: =G8-G25 -> -51701.144 | H36: =H8-H25 -> -68107.359 | I36: =I8-I25 -> -83259.159 | J36: =J8-J25 -> -97289.27 | K36: =K8-K25 -> -110317.29 | ... O36: =O8-O25 -> -154411.09
B37: ICEV BEV | D37: Tesla Model S | E37: Tesla Model Y （SUV） | F37: Mercedes Benz EQC （SUV） | G37: Nio es6 （SUV） | H37: Nio es8 （SUV） | I37: Jaguar I-Pace | J37: Audi e-tron | K37: BYD Tang EV （SUV） | L37: Aiways U5 （SUV） | M37: DENZA X（SUV） | N37: Roewe MarvelX （SUV）
D38: 843900 | E38: 859900 | F38: 601300 | G38: 428000 | H38: 517000 | I38: 673800 | J38: 723000 | K38: 334900 | L38: 245000 | M38: 338800 | N38: 288800
B39: JAC Ruifeng A60 | C39: 184500 | D39: Post 2030 | E39: Post 2030 | F39: Post 2030 | G39: Post 2030 | H39: Post 2030 | I39: Post 2030 | J39: Post 2030 | K39: Post 2030 | L39: 2023 | M39: Post 2030 | N39: 2026
B40: Mercedes Benz GLC （SUV） | C40: 694800 | D40: Post 2030 | E40: Post 2030 | F40: 2019 | G40: 2019 | H40: 2019 | I40: 2019 | J40: 2019 | K40: 2019 | L40: 2019 | M40: 2019 | N40: 2019
B41: Mercedes Benz C Class | C41: 615300 | D41: Post 2030 | E41: Post 2030 | F41: 2019 | G41: 2019 | H41: 2019 | I41: 2019 | J41: 2027 | K41: 2019 | L41: 2019 | M41: 2019 | N41: 2019
B42: BMW X3 （SUV） | C42: 434800 | D42: Post 2030 | E42: Post 2030 | F42: Post 2030 | G42: 2019 | H42: 2025 | I42: Post 2030 | J42: Post 2030 | K42: 2019 | L42: 2019 | M42: 2019 | N42: 2019
B43: BMW X5 （SUV） | C43: 729900 | D43: 2027 | E43: 2029 | F43: 2019 | G43: 2019 | H43: 2019 | I43: 2019 | J43: 2019 | K43: 2019 | L43: 2019 | M43: 2019 | N43: 2019
B44: Jaguar F-Type | C44: 613900 | D44: Post 2030 | E44: Post 2030 | F44: 2019 | G44: 2019 | H44: 2019 | I44: 2019 | J44: 2027 | K44: 2019 | L44: 2019 | M44: 2019 | N44: 2019
B45: Audi SQ5 （SUV） | C45: 668000 | D45: Post 2030 | E45: Post 2030 | F45: 2019 | G45: 2019 | H45: 2019 | I45: 2019 | J45: 2023 | K45: 2019 | L45: 2019 | M45: 2019 | N45: 2019
B46: BYD Tang （SUV） | C46: 149900 | D46: Post 2030 | E46: Post 2030 | F46: Post 2030 | G46: Post 2030 | H46: Post 2030 | I46: Post 2030 | J46: Post 2030 | K46: Post 2030 | L46: 2026 | M46: Post 2030 | N46: 2030
B47: Volvo XC60 | C47: 416400 | D47: Post 2030 | E47: Post 2030 | F47: Post 2030 | G47: 2019 | H47: 2026 | I47: Post 2030 | J47: Post 2030 | K47: 2019 | L47: 2019 | M47: 2019 | N47: 2019
B48: Volvo XC90 | C48: 733900 | D48: 2027 | E48: 2028 | F48: 2019 | G48: 2019 | H48: 2019 | I48: 2019 | J48: 2019 | K48: 2019 | L48: 2019 | M48: 2019 | N48: 2019
B49: Toyota Highlander | C49: 282800 | D49: Post 2030 | E49: Post 2030 | F49: Post 2030 | G49: 2030 | H49: Post 2030 | I49: Post 2030 | J49: Post 2030 | K49: 2022 | L49: 2019 | M49: 2023 | N49: 2019
A51: Short | B51: 64 | C51: =B51/121 -> 0.52892562
A52: Middle | B52: 4 | C52: =B52/121 -> 0.033057851
A53: Long | B53: 53 | C53: =B53/121 -> 0.43801653
G54: =AVERAGE(F38,G38,H38,I38,J38,K38,M38) -> 516685.71
A55: Volvo XC90 | F55: =AVERAGE(C40,C41,C42,C47,C49,C44,C45) -> 532285.71
A56: BMWX5
A57: BYD Tang
A58: JAC A60
A60: Tesla modelx
A61: Tesla model Y
A62: Aiway U5
A63: Roewe MarvelX
A65: Short | B65: 32 | C65: =B65/49 -> 0.65306122
A66: Middle | B66: 3 | C66: =B66/49 -> 0.06122449
A67: Long | B67: 4 | C67: =B67/49 -> 0.081632653
A68: Post 2030 | B68: 10 | C68: =B68/49 -> 0.20408163

Sheet Class Summary
C2: A00 | D2: A0 | E2: A | F2: B | G2: C
B3: 2016 | C3: 0.511 | D3: 0.241 | E3: 0.177 | F3: 0.015 | G3: 0.056
B4: 2017 | C4: 0.578 | D4: 0.079 | E4: 0.27 | F4: 0.044 | G4: 0.029
B5: 2018 | C5: 0.38 | D5: 0.137 | E5: 0.365 | F5: 0.077 | G5: 0.041
B6: 2019 | C6: 0.175 | D6: 0.114 | E6: 0.533 | F6: 0.152 | G6: 0.026
B7: 2020 | C7: 0.1 | D7: 0.05 | E7: 0.57 | F7: 0.23 | G7: 0.05
B8: 2021 | C8: 0.05 | D8: 0.02 | E8: 0.6 | F8: 0.25 | G8: 0.08
B9: 2022 | C9: 0.02 | D9: 0.01 | E9: 0.55 | F9: 0.3 | G9: 0.12
B10: 2023 | C10: 0.015 | D10: 0.005 | E10: 0.5 | F10: 0.35 | G10: 0.13
B11: 2024 | C11: 0.01 | D11: 0 | E11: 0.45 | F11: 0.4 | G11: 0.14
B12: 2025 | C12: 0.005 | D12: 0 | E12: 0.4 | F12: 0.45 | G12: 0.145
B13: 2026 | C13: 0.002 | D13: 0 | E13: 0.35 | F13: 0.5 | G13: 0.148
B14: 2027 | C14: 0.0015 | D14: 0 | E14: 0.32 | F14: 0.5 | G14: 0.1785
... B17: 2030 | C17: 0.0001 | D17: 0 | E17: 0.2 | F17: 0.5799 | G17: 0.22
B27: A00
B28: short | C28: 35 | D28: =C28/64 -> 0.546875
B29: Middle | C29: 20 | D29: =C29/64 -> 0.3125
B30: Long | C30: 9 | D30: =C30/64 -> 0.140625
B31: Post 2030 | C31: 0 | D31: 0
B33: A
B34: Short | C34: 42 | D34: =C34/81 -> 0.51851852
B35: Middle | C35: 23 | D35: =C35/81 -> 0.28395062
B36: Long | C36: 14 | D36: =C36/81 -> 0.17283951
B37: Post 2030 | C37: 2 | D37: =C37/81 -> 0.024691358
B39: B
B40: Short | C40: 60 | D40: =C40/144 -> 0.41666667
B41: Middle | C41: 39 | D41: =C41/144 -> 0.27083333
B42: Long | C42: 39 | D42: =C42/144 -> 0.27083333
C43: 6 | D43: =C43/144 -> 0.041666667
B45: C
B46: Short | C46: 32 | D46: =C46/49 -> 0.65306122
B47: Middle | C47: 3 | D47: =C47/49 -> 0.06122449
B48: Long | C48: 4 | D48: =C48/49 -> 0.081632653
C49: 10 | D49: =C49/49 -> 0.20408163
B51: A00 | C51: A | D51: B | E51: C | J51: A00 | K51: A | L51: B | M51: C | R51: A00 | S51: A0 | T51: A | U51: B | V51: C
A52: Short | B52: 0.546875 | C52: 0.51851852 | D52: 0.41666667 | E52: 0.65306122 | I52: 2019 | Q52: 2016 | R52: 0.511 | S52: 0.241 | T52: 0.177 | U52: 0.015 | V52: 0.056
A53: Middle | B53: 0.3125 | C53: 0.28395062 | D53: 0.27083333 | E53: 0.06122449 | I53: 2020 | Q53: 2017 | R53: 0.578 | S53: 0.079 | T53: 0.27 | U53: 0.044 | V53: 0.029
A54: Long | B54: 0.140625 | C54: 0.17283951 | D54: 0.27083333 | E54: 0.081632653 | I54: 2021 | Q54: 2018 | R54: 0.38 | S54: 0.137 | T54: 0.365 | U54: 0.077 | V54: 0.041
A55: Post 2030 | B55: 0 | C55: 0.024691358 | D55: 0.041666667 | E55: 0.20408163 | I55: 2022 | J55: =(R58+S58)*B59 -> 0.01640625 | K55: =T58*C59 -> 0.28518519 | L55: =U58*D52 -> 0.125 | M55: =V58*E52 -> 0.078367347 | N55: =SUM(J55:M55) -> 0.50495878 | Q55: 2019 | R55: 0.175 | S55: 0.114 | T55: 0.533 | U55: 0.152 | V55: 0.026
I56: 2023 | Q56: 2020 | R56: 0.1 | S56: 0.05 | T56: 0.57 | U56: 0.23 | V56: 0.05
I57: 2024 | Q57: 2021 | R57: 0.05 | S57: 0.02 | T57: 0.6 | U57: 0.25 | V57: 0.08
B58: A00 | C58: A | D58: B | E58: C | I58: 2025 | J58: =(R61+S61)*B60 -> 0.004296875 | K58: =T61*C60 -> 0.32098765 | L58: =U61*D60 -> 0.309375 | M58: =V61*E60 -> 0.10357143 | N58: =SUM(J58:M58) -> 0.73823096 | Q58: 2022 | R58: 0.02 | S58: 0.01 | T58: 0.55 | U58: 0.3 | V58: 0.12
A59: 2022 | B59: 0.546875 | C59: 0.51851852 | D59: 0.41666667 | E59: 0.65306122 | I59: 2026 | Q59: 2023 | R59: 0.015 | S59: 0.005 | T59: 0.5 | U59: 0.35 | V59: 0.13
A60: 2025 | B60: =B59+B53 -> 0.859375 | C60: =C59+C53 -> 0.80246914 | D60: =D59+D53 -> 0.6875 | E60: =E59+E53 -> 0.71428571 | I60: 2027 | Q60: 2024 | R60: 0.01 | S60: 0 | T60: 0.45 | U60: 0.4 | V60: 0.14
A61: 2030 | B61: =B60+B54 -> 1 | C61: =C60+C54 -> 0.97530864 | D61: =D60+D54 -> 0.95833333 | E61: =E60+E54 -> 0.79591837 | I61: 2028 | Q61: 2025 | R61: 0.005 | S61: 0 | T61: 0.4 | U61: 0.45 | V61: 0.145
A62: Post 2030 | B62: 1 | C62: 1 | D62: 1 | E62: 1 | I62: 2029 | Q62: 2026 | R62: 0.002 | S62: 0 | T62: 0.35 | U62: 0.5 | V62: 0.148
I63: 2030 | J63: =(R66+S66)*B61 -> 0.0001 | K63: =T66*C61 -> 0.19506173 | L63: =U66*D61 -> 0.5557375 | M63: =V66*E61 -> 0.17510204 | N63: =SUM(J63:M63) -> 0.92600127 | Q63: 2027 | R63: 0.0015 | S63: 0 | T63: 0.32 | U63: 0.5 | V63: 0.1785
Q64: 2028 | R64: 0.001 | S64: 0 | T64: 0.3 | U64: 0.52 | V64: 0.179
Q65: 2029 | R65: 0.0005 | S65: 0 | T65: 0.25 | U65: 0.5495 | V65: 0.2
Q66: 2030 | R66: 0.0001 | S66: 0 | T66: 0.2 | U66: 0.5799 | V66: 0.22
N70: A00 | O70: A | P70: B | Q70: C | R70: Total
M71: 2022 | N71: 0.01640625 | O71: 0.28518519 | P71: 0.125 | Q71: 0.078367347 | R71: 0.50495878
M72: 2025 | N72: 0.004296875 | O72: 0.32098765 | P72: 0.309375 | Q72: 0.10357143 | R72: 0.73823096
M73: 2030 | N73: 0.0001 | O73: 0.19506173 | P73: 0.5557375 | Q73: 0.17510204 | R73: 0.92600127

Sheet TCO graphing
C1: A00 | F1: A | I1: B | L1: C
C2: BEV | D2: ICEV | E2: A00 TCO | F2: BEV | G2: ICEV | H2: A TCO | I2: BEV | J2: ICEV | K2: B TCO | L2: BEV | M2: ICEV | N2: C TCO
B3: 10 | C3: 83305.032 | D3: 76931.737 | E3: =C3-D3 -> 6373.2953
B4: 20 | C4: 86354.073 | D4: 92122.624 | E4: =C4-D4 -> -5768.551 | F4: 150866.7 | G4: 135614.18 | H4: =F4-G4 -> 15252.517
B5: 40 | C5: 92452.156 | D5: 122504.4 | E5: =C5-D5 -> -30052.243 | F5: 157978.18 | G5: 168582.23 | H5: =F5-G5 -> -10604.052 | I5: 227678.18 | J5: 187896.58 | K5: =I5-J5 -> 39781.599
B6: 60 | C6: 98550.239 | D6: 152886.17 | E6: =C6-D6 -> -54335.936 | F6: 165089.65 | G6: 201550.27 | H6: =F6-G6 -> -36460.62 | I6: 234789.65 | J6: 224559.3 | K6: =I6-J6 -> 10230.357 | L6: 615398.19 | M6: 547809.3 | N6: =L6-M6 -> 67588.895
B7: 80 | F7: 172201.13 | G7: 233918.32 | H7: =F7-G7 -> -61717.188 | I7: 241901.13 | J7: 260622.02 | K7: =I7-J7 -> -18720.886 | L7: 623607.52 | M7: 583872.02 | N7: =L7-M7 -> 39735.498
B8: 90 | L8: 627812.18 | M8: 602203.38 | N8: =L8-M8 -> 25608.8
B9: 120 | L9: 640026.17 | M9: 657197.46 | N9: =L9-M9 -> -17171.295
B10: 300 | F10: 205200.99 | G10: 411834.72 | H10: =F10-G10 -> -206633.73 | I10: 271599.02 | J10: 466667.05 | K10: =I10-J10 -> -195068.03
D13: 83305.032
E16: A00 TCO (diff) | F16: A TCO (diff) | G16: B TCO (diff) | H16: C TCO (diff)
D17: 10 | E17: 6373.2953
D18: 20 | E18: -5768.551 | F18: 15252.517
D19: 40 | E19: -30052.243 | F19: -10604.052 | G19: 39781.599
D20: 60 | E20: -54335.936 | F20: -36460.62 | G20: 10230.357 | H20: 67588.895
D21: 80 | F21: -61717.188 | G21: -18720.886 | H21: 39735.498
D22: 90 | H22: 25608.8
D23: 120 | H23: -17171.295
D24: 300 | F24: -206633.73 | G24: -195068.03
C32: Average Price | D32: ICEV | E32: BEV
C33: A00 | D33: 51066 | E33: 63475
C34: A | D34: 140427.78 | E34: 160144.44
C35: B | D35: 156125 | E35: 180670.83
C36: C | D36: 532285.71 | E36: 516685.71
D39: 2019 | E39: 2020 | F39: 2021 | G39: 2022 | H39: 2023 | I39: 2024 | J39: 2025 | K39: 2026 | L39: 2027 | M39: 2028 | N39: 2029 | O39: 2030
B40: 10 | C40: A00 10km/day | D40: 3700.1453 | E40: -3522.3602 | F40: -1963.4357 | G40: -5841.7896 | H40: -9358.6057 | I40: -12551.212 | J40: -15453.197 | K40: -18094.784 | L40: -20503.169 | M40: -22702.823 | N40: -24715.767 | O40: -26561.818
B41: 20 | C41: A00 20km/day | D41: -8441.701 | E41: -15306.366 | F41: -13400.15 | G41: -16941.449 | H41: -20131.146 | I41: -23006.276 | J41: -25600.143 | K41: -27942.694 | L41: -30060.858 | M41: -31978.846 | N41: -33718.426 | O41: -35299.17
B42: 40 | C42: A00 40km/day | D42: -32725.393 | E42: -38874.378 | F42: -36273.578 | G42: -39140.769 | H42: -41676.228 | I42: -43916.405 | J42: -45894.036 | K42: -47638.515 | L42: -49176.237 | M42: -50530.892 | N42: -51723.744 | O42: -52773.876
B43: 60 | C43: A00 60km/day | D43: -57009.086 | E43: -62442.39 | F43: -59147.007 | G43: -61340.088 | H43: -63221.309 | I43: -64826.534 | J43: -66187.928 | K43: -67334.336 | L43: -68291.615 | M43: -69082.937 | N43: -69729.062 | O43: -70248.581
B44: 300 | C44: A00 300km/day | D44: -217011.1 | E44: -214820.66 | F44: -207036.98 | G44: -204874 | H44: -202527.49 | I44: -200029.54 | J44: -197408.63 | K44: -194690.06 | L44: -191896.23 | M44: -189046.94 | N44: -186159.71 | O44: -183249.96
B46: 20 | C46: A 20km/day | D46: 8014.4611 | E46: 245.37618 | F46: 7445.0348 | G46: 353.61494 | H46: -6046.134 | I46: -12035.969 | J46: -17463.533 | K46: -22386.755 | L46: -26857.761 | M46: -32324.591 | N46: -37387.522 | O46: -42085.735
B47: 30 | C47: A 30km/day | D47: -4813.823 | E47: -12205.162 | F47: -4638.8826 | G47: -11374.48 | H47: -17428.885 | I47: -23083.548 | J47: -28185.812 | K47: -32793.313 | L47: -36957.897 | M47: -40726.201 | N47: -44140.175 | O47: -47237.551
B48: 40 | C48: A 40km/day | D48: -17842.107 | E48: -24849.7 | F48: -16910.98 | G48: -23285.109 | H48: -28988.695 | I48: -34302.874 | J48: -39074.684 | K48: -43361.468 | L48: -47214.782 | M48: -50680.986 | N48: -53801.76 | O48: -56614.574
B49: 60 | C49: A 60km/day | D49: -43698.675 | E49: -49944.776 | F49: -41266.995 | G49: -46923.832 | H49: -51931.257 | I49: -56569.779 | J49: -60685.836 | K49: -64336.18 | L49: -67571.803 | M49: -70438.51 | N49: -72977.445 | O49: -75225.558
B50: 80 | C50: A 80km/day | D50: -68955.243 | E50: -74457.852 | F50: -65058.469 | G50: -70014.952 | H50: -74342.642 | I50: -78321.444 | J50: -81797.204 | K50: -84826.104 | L50: -87458.579 | M50: -89739.896 | N50: -91710.676 | O50: -93407.361
B51: 300 | C51: A 300km/day | D51: -213871.79 | E51: -215109.75 | F51: -201571.25 | G51: -202510.44 | H51: -202939.08 | I51: -202923.19 | J51: -202521.76 | K51: -201787.54 | L51: -204274.48 | M51: -206415.57 | N51: -208251.23 | O51: -209817.74
B53: 20 | C53: B 20km/day | D53: 18625.55 | E53: 8720.4774 | F53: 15567.372 | G53: 6532.0831 | H53: -1623.0684 | I53: -9199.1568 | J53: -16061.212 | K53: -22282.808 | L53: -27930.153 | M53: -33062.831 | N53: -37734.466 | O53: -41993.313
... B67: 300 | C67: C 300km/day | D67: -230118.06 | E67: -238235.44 | F67: -196718.86 | G67: -204075.19 | H67: -210430.18 | I67: -215904.39 | J67: -220605.92 | K67: -224631.74 | L67: -228068.8 | M67: -230995.03 | N67: -233480.26 | O67: -235587.06

Sheet A00 data TCO
C4: Chery eQ1
D5: 2019 | E5: 2020 | F5: 2021 | G5: 2022 | H5: 2023 | I5: 2024 | J5: 2025 | K5: 2026 | L5: 2027 | M5: 2028 | N5: 2029 | O5: 2030
C6: Retail Price | D6: 63475 | E6: =D6-((D16-E16)+(D17-E17)+(D18-E18)) -> 58403 | F6: =E6-((E16-F16)+(E17-F17)+(E18-F18)) -> 53818.2 | G6: =F6-((F16-G16)+(F17-G17)+(F18-G18)) -> 49671.88 | H6: =G6-((G16-H16)+(G17-H17)+(G18-H18)) -> 45920.192 | I6: =H6-((H16-I16)+(H17-I17)+(H18-I18)) -> 42523.673 | J6: =I6-((I16-J16)+(I17-J17)+(I18-J18)) -> 39446.806 | K6: =J6-((J16-K16)+(J17-K17)+(J18-K18)) -> 36657.625 | L6: =K6-((K16-L16)+(K17-L17)+(K18-L18)) -> 34127.362 | ... O6: =N6-((N16-O16)+(N17-O17)+(N18-O18)) -> 27843.852
C7: Purchase Tax | D7: 0 | E7: 0 | F7: =F6*0.1 -> 5381.82 | G7: =G6*0.1 -> 4967.188 | H7: =H6*0.1 -> 4592.0192 | I7: =I6*0.1 -> 4252.3673 | J7: =J6*0.1 -> 3944.6806 | K7: =K6*0.1 -> 3665.7625 | L7: =L6*0.1 -> 3412.7362 | M7: =M6*0.1 -> 3183.0126 | ... O7: =O6*0.1 -> 2784.3852
C8: Consumer Final Price | D8: =D6+D7 -> 63475 | E8: =E6+E7 -> 58403 | F8: =F6+F7 -> 59200.02 | G8: =G6+G7 -> 54639.068 | H8: =H6+H7 -> 50512.211 | I8: =I6+I7 -> 46776.04 | J8: =J6+J7 -> 43391.486 | K8: =K6+K7 -> 40323.387 | ... O8: =O6+O7 -> 30628.237
C9: Dealer Gross Profit(5%) | D9: =D6*0.05 -> 3173.75 | E9: =E6*0.05 -> 2920.15 | F9: =F6*0.05 -> 2690.91 | G9: =G6*0.05 -> 2483.594 | H9: =H6*0.05 -> 2296.0096 | I9: =I6*0.05 -> 2126.1836 | J9: =J6*0.05 -> 1972.3403 | K9: =K6*0.05 -> 1832.8812 | ... O9: =O6*0.05 -> 1392.1926
C10: Range (km) | D10: 301 | E10: 301 | F10: 301 | G10: 301 | H10: 301 | I10: 301 | J10: 301 | K10: 301 | L10: 301 | M10: 301 | N10: 301 | O10: 301
C11: Battery (kwh) | D11: 30.6 | E11: 30.6 | F11: 30.6 | G11: 30.6 | H11: 30.6 | I11: 30.6 | J11: 30.6 | K11: 30.6 | L11: 30.6 | M11: 30.6 | N11: 30.6 | O11: 30.6
C12: Battery Price/wh | D12: 1.2 | E12: =D12*0.9 -> 1.08 | F12: =E12*0.9 -> 0.972 | G12: =F12*0.9 -> 0.8748 | H12: =G12*0.9 -> 0.78732 | I12: =H12*0.9 -> 0.708588 | J12: =I12*0.9 -> 0.6377292 | K12: =J12*0.9 -> 0.57395628 | L12: =K12*0.9 -> 0.51656065 | ... O12: =N12*0.9 -> 0.37657272
C13: Subsidies | D13: 27000 | E13: 28000 | F13: 0 | G13: 0 | H13: 0 | I13: 0 | J13: 0 | K13: 0 | L13: 0 | M13: 0 | N13: 0 | O13: 0
C14: Auto Company Revenue | D14: =D6-D9+D13 -> 87301.25 | E14: =E6-E9+E13 -> 83482.85 | F14: =F6-F9+F13 -> 51127.29 | G14: =G6-G9+G13 -> 47188.286 | H14: =H6-H9+H13 -> 43624.182 | I14: =I6-I9+I13 -> 40397.489 | J14: =J6-J9+J13 -> 37474.465 | K14: =K6-K9+K13 -> 34824.744 | ... O14: =O6-O9+O13 -> 26451.66
C15: Revenue (after vat) | D15: =D14*0.87 -> 75952.087 | E15: =E14*0.87 -> 72630.08 | F15: =F14*0.87 -> 44480.742 | G15: =G14*0.87 -> 41053.809 | H15: =H14*0.87 -> 37953.039 | I15: =I14*0.87 -> 35145.816 | J15: =J14*0.87 -> 32602.785 | K15: =K14*0.87 -> 30297.527 | ... O15: =O14*0.87 -> 23012.944
C16: Power Battery System Cost | D16: =D12*1000*D11 -> 36720 | E16: =E12*1000*E11 -> 33048 | F16: =F12*1000*F11 -> 29743.2 | G16: =G12*1000*G11 -> 26768.88 | H16: =H12*1000*H11 -> 24091.992 | I16: =I12*1000*I11 -> 21682.793 | J16: =J12*1000*J11 -> 19514.514 | K16: =K12*1000*K11 -> 17563.062 | ... O16: =O12*1000*O11 -> 11523.125
C17: Electric Motor & Electric Controlling | D17: 5000 | E17: =D17-200 -> 4800 | F17: =E17-200 -> 4600 | G17: =F17-200 -> 4400 | H17: =G17-200 -> 4200 | I17: =H17-200 -> 4000 | J17: =I17-200 -> 3800 | K17: =J17-200 -> 3600 | L17: =K17-200 -> 3400 | ... O17: =N17-200 -> 2800
C18: Other Cost | D18: 12000 | E18: =D18*0.9 -> 10800 | F18: =E18*0.9 -> 9720 | G18: =F18*0.9 -> 8748 | H18: =G18*0.9 -> 7873.2 | I18: =H18*0.9 -> 7085.88 | J18: =I18*0.9 -> 6377.292 | K18: =J18*0.9 -> 5739.5628 | L18: =K18*0.9 -> 5165.6065 | ... O18: =N18*0.9 -> 3765.7272
C19: Profit Margin(BEV) | D19: =D15-D16-D17-D18 -> 22232.087 | E19: =E15-E16-E17-E18 -> 23982.08 | F19: =F15-F16-F17-F18 -> 417.5423 | G19: =G15-G16-G17-G18 -> 1136.9288 | H19: =H15-H16-H17-H18 -> 1787.8467 | I19: =I15-I16-I17-I18 -> 2377.1428 | J19: =J15-J16-J17-J18 -> 2910.9792 | K19: =K15-K16-K17-K18 -> 3394.9021 | ... O19: =O15-O16-O17-O18 -> 4924.0916
C20: PM/Revenue | D20: =D19/D14 -> 0.25465944 | E20: =E19/E14 -> 0.28726954 | F20: =F19/F14 -> 0.0081667207 | G20: =G19/G14 -> 0.024093454 | H20: =H19/H14 -> 0.040982927 | I20: =I19/I14 -> 0.058843825 | J20: =J19/J14 -> 0.077679007 | K20: =K19/K14 -> 0.097485342 | ... O20: =O19/O14 -> 0.18615435
C21: Chery QQ6
D22: 2019 | E22: 2020 | F22: 2021 | G22: 2022 | H22: 2023 | I22: 2024 | J22: 2025 | K22: 2026 | L22: 2027 | M22: 2028 | N22: 2029 | O22: 2030
C23: Retail Price | D23: 51066 | E23: =D23+(E29-D29)+(E30-D30) -> 51366 | F23: =E23+(F29-E29)+(F30-E30) -> 51672 | G23: =F23+(G29-F29)+(G30-F30) -> 51984.12 | H23: =G23+(H29-G29)+(H30-G30) -> 52302.482 | I23: =H23+(I29-H29)+(I30-H30) -> 52627.212 | J23: =I23+(J29-I29)+(J30-I30) -> 52958.436 | K23: =J23+(K29-J29)+(K30-J30) -> 53296.285 | L23: =K23+(L29-K29)+(L30-K30) -> 53640.891 | ... O23: =N23+(O29-N29)+(O30-N30) -> 54716.615
C24: Purchase Tax | D24: =D23*0.1 -> 5106.6 | E24: =E23*0.1 -> 5136.6 | F24: =F23*0.1 -> 5167.2 | G24: =G23*0.1 -> 5198.412 | H24: =H23*0.1 -> 5230.2482 | I24: =I23*0.1 -> 5262.7212 | J24: =J23*0.1 -> 5295.8436 | K24: =K23*0.1 -> 5329.6285 | ... O24: =O23*0.1 -> 5471.6615
C25: Consumer Final Price | D25: =D23+D24 -> 56172.6 | E25: =E23+E24 -> 56502.6 | F25: =F23+F24 -> 56839.2 | G25: =G23+G24 -> 57182.532 | H25: =H23+H24 -> 57532.731 | I25: =I23+I24 -> 57889.933 | J25: =J23+J24 -> 58254.28 | K25: =K23+K24 -> 58625.914 | ... O25: =O23+O24 -> 60188.276
C26: Dealer Gross Profit (5%) | D26: =D23*0.05 -> 2553.3 | E26: =E23*0.05 -> 2568.3 | F26: =F23*0.05 -> 2583.6 | G26: =G23*0.05 -> 2599.206 | H26: =H23*0.05 -> 2615.1241 | I26: =I23*0.05 -> 2631.3606 | J26: =J23*0.05 -> 2647.9218 | K26: =K23*0.05 -> 2664.8143 | ... O26: =O23*0.05 -> 2735.8307
C27: Auto Company Revenue | D27: =D23-D26 -> 48512.7 | E27: =E23-E26 -> 48797.7 | F27: =F23-F26 -> 49088.4 | G27: =G23-G26 -> 49384.914 | H27: =H23-H26 -> 49687.358 | I27: =I23-I26 -> 49995.851 | J27: =J23-J26 -> 50310.514 | K27: =K23-K26 -> 50631.471 | ... O27: =O23-O26 -> 51980.784
C28: Revenue (after vat) | D28: =D27*0.87 -> 42206.049 | E28: =E27*0.87 -> 42453.999 | F28: =F27*0.87 -> 42706.908 | G28: =G27*0.87 -> 42964.875 | H28: =H27*0.87 -> 43228.002 | I28: =I27*0.87 -> 43496.391 | J28: =J27*0.87 -> 43770.148 | K28: =K27*0.87 -> 44049.38 | ... O28: =O27*0.87 -> 45223.282
C29: Motor Cost | D29: 10000 | E29: =D29*1.02 -> 10200 | F29: =E29*1.02 -> 10404 | G29: =F29*1.02 -> 10612.08 | H29: =G29*1.02 -> 10824.322 | I29: =H29*1.02 -> 11040.808 | J29: =I29*1.02 -> 11261.624 | K29: =J29*1.02 -> 11486.857 | L29: =K29*1.02 -> 11716.594 | ... O29: =N29*1.02 -> 12433.743
C30: Transmission Cost | D30: 5000 | E30: =D30*1.02 -> 5100 | F30: =E30*1.02 -> 5202 | G30: =F30*1.02 -> 5306.04 | H30: =G30*1.02 -> 5412.1608 | I30: =H30*1.02 -> 5520.404 | J30: =I30*1.02 -> 5630.8121 | K30: =J30*1.02 -> 5743.4283 | L30: =K30*1.02 -> 5858.2969 | ... O30: =N30*1.02 -> 6216.8715
C31: 48V System Cost | D31: 0 | E31: 0 | F31: 0 | G31: 0 | H31: 0 | I31: 0 | J31: 0 | K31: 0 | L31: 0 | M31: 0 | N31: 0 | O31: 0
C32: Other Cost | D32: 16000 | E32: 16000 | F32: 16000 | G32: 16000 | H32: 16000 | I32: 16000 | J32: 16000 | K32: 16001 | L32: 16002 | M32: 16003 | N32: 16004 | O32: 16005
C33: Profit Margin(ICEV) | D33: =D28-D29-D30-D31-D32 -> 11206.049 | E33: =E28-E29-E30-E31-E32 -> 11153.999 | F33: =F28-F29-F30-F31-F32 -> 11100.908 | G33: =G28-G29-G30-G31-G32 -> 11046.755 | H33: =H28-H29-H30-H31-H32 -> 10991.519 | I33: =I28-I29-I30-I31-I32 -> 10935.179 | J33: =J28-J29-J30-J31-J32 -> 10877.711 | K33: =K28-K29-K30-K31-K32 -> 10818.095 | ... O33: =O28-O29-O30-O31-O32 -> 10567.667
C34: PM/Revenue | D34: =D33/D27 -> 0.23099207 | E34: =E33/E27 -> 0.22857633 | F34: =F33/F27 -> 0.22614117 | G34: =G33/G27 -> 0.22368684 | H34: =H33/H27 -> 0.2212136 | I34: =I33/I27 -> 0.21872172 | J34: =J33/J27 -> 0.21621149 | K34: =K33/K27 -> 0.21366345 | ... O34: =O33/O27 -> 0.2032995
H45: ='A00 data TCO'!D663475 -> 0

Sheet A00 TCO (10)3
C4: A00 Class BEV Sample Avg
D5: 2019 | E5: 2020 | F5: 2021 | G5: 2022 | H5: 2023 | I5: 2024 | J5: 2025 | K5: 2026 | L5: 2027 | M5: 2028 | N5: 2029 | O5: 2030
C6: Retail Price | D6: ='A00 data TCO'!D6 -> 63475 | E6: ='A00 data TCO'!E6 -> 58403 | F6: ='A00 data TCO'!F6 -> 53818.2 | G6: ='A00 data TCO'!G6 -> 49671.88 | H6: ='A00 data TCO'!H6 -> 45920.192 | I6: ='A00 data TCO'!I6 -> 42523.673 | J6: ='A00 data TCO'!J6 -> 39446.806 | K6: ='A00 data TCO'!K6 -> 36657.625 | ... O6: ='A00 data TCO'!O6 -> 27843.852
C7: Purchase Tax | D7: 0 | E7: 0 | F7: =F6*0.1 -> 5381.82 | G7: =G6*0.1 -> 4967.188 | H7: =H6*0.1 -> 4592.0192 | I7: =I6*0.1 -> 4252.3673 | J7: =J6*0.1 -> 3944.6806 | K7: =K6*0.1 -> 3665.7625 | L7: =L6*0.1 -> 3412.7362 | M7: =M6*0.1 -> 3183.0126 | ... O7: =O6*0.1 -> 2784.3852
C8: Consumer Final Price | D8: =D6+D7 -> 63475 | E8: =E6+E7 -> 58403 | F8: =F6+F7 -> 59200.02 | G8: =G6+G7 -> 54639.068 | H8: =H6+H7 -> 50512.211 | I8: =I6+I7 -> 46776.04 | J8: =J6+J7 -> 43391.486 | K8: =K6+K7 -> 40323.387 | ... O8: =O6+O7 -> 30628.237
C9: Range/Day (km) | D9: 10 | E9: 10 | F9: 10 | G9: 10 | H9: 10 | I9: 10 | J9: 10 | K9: 10 | L9: 10 | M9: 10 | N9: 10 | O9: 10
C10: Years of Usage | D10: 8 | E10: 8 | F10: 8 | G10: 8 | H10: 8 | I10: 8 | J10: 8 | K10: 8 | L10: 8 | M10: 8 | N10: 8 | O10: 8
C11: Electricity/hundred KM (Kwh) | D11: 11.6 | E11: 11.6 | F11: 11.6 | G11: 11.6 | H11: 11.6 | I11: 11.6 | J11: 11.6 | K11: 11.6 | L11: 11.6 | M11: 11.6 | N11: 11.6 | O11: 11.6
C12: Electricity Price (RMB/Kwh) | D12: 0.8 | E12: 0.8 | F12: 0.8 | G12: 0.8 | H12: 0.8 | I12: 0.8 | J12: 0.8 | K12: 0.8 | L12: 0.8 | M12: 0.8 | N12: 0.8 | O12: 0.8
C13: Discount Rate | D13: 0.03 | E13: 0.03 | F13: 0.03 | G13: 0.03 | H13: 0.03 | I13: 0.03 | J13: 0.03 | K13: 0.03 | L13: 0.03 | M13: 0.03 | N13: 0.03 | O13: 0.03
C14: NPV Energy Cost | D14: 2449.0414 | E14: 2377.7101 | F14: 2308.4564 | G14: 2241.2198 | H14: 2175.9416 | I14: 2112.5647 | J14: 2051.0337 | K14: 1991.2948 | L14: 1933.2959 | M14: 1876.9863 | N14: 1822.3168 | O14: 1769.2396
C15: NPV Maintenance Cost | D15: 300 | E15: =D15*(1-$D$13) -> 291 | F15: =E15*(1-$D$13) -> 282.27 | G15: =F15*(1-$D$13) -> 273.8019 | H15: =G15*(1-$D$13) -> 265.58784 | I15: =H15*(1-$D$13) -> 257.62021 | J15: =I15*(1-$D$13) -> 249.8916 | K15: =J15*(1-$D$13) -> 242.39485 | L15: =K15*(1-$D$13) -> 235.12301 | ... O15: =N15*(1-$D$13) -> 214.59042
C16: NPV Insurance Cost | D16: 25305.99 | E16: 21657.072 | F16: 21026.284 | G16: 20413.868 | H16: 19819.289 | I16: 19242.028 | J16: 18681.581 | K16: 18137.457 | L16: 17609.182 | M16: 17096.293 | N16: 16598.343 | O16: 16114.896
C17: NPV Vehicle and Vessel Tax | D17: 0 | E17: 0 | F17: 0 | G17: 0 | H17: 0 | I17: 0 | J17: 0 | K17: 0 | L17: 0 | M17: 0 | N17: 0 | O17: 0
C18: Residual Value after Depreciation | D18: =0.15*D6 -> 9521.25 | E18: =0.15*E6 -> 8760.45 | F18: =0.15*F6 -> 8072.73 | G18: =0.15*G6 -> 7450.782 | H18: =0.15*H6 -> 6888.0288 | I18: =0.15*I6 -> 6378.5509 | J18: =0.15*J6 -> 5917.0208 | K18: =0.15*K6 -> 5498.6437 | ... O18: =0.15*O6 -> 4176.5778
C19: TCO | D19: =D8+D14+D15+D16+D17-D18 -> 82008.782 | E19: =E8+E14+E15+E16+E17-E18 -> 73968.333 | F19: =F8+F14+F15+F16+F17-F18 -> 74744.3 | G19: =G8+G14+G15+G16+G17-G18 -> 70117.176 | H19: =H8+H14+H15+H16+H17-H18 -> 65885.001 | I19: =I8+I14+I15+I16+I17-I18 -> 62009.702 | J19: =J8+J14+J15+J16+J17-J18 -> 58456.971 | K19: =K8+K14+K15+K16+K17-K18 -> 55195.891 | ... O19: =O8+O14+O15+O16+O17-O18 -> 44550.386
C20: A00 Class ICEV Sample Avg
D21: 2019 | E21: 2020 | F21: 2021 | G21: 2022 | H21: 2023 | I21: 2024 | J21: 2025 | K21: 2026 | L21: 2027 | M21: 2028 | N21: 2029 | O21: 2030
C22: Retail Price | D22: ='A00 data TCO'!D23 -> 51066 | E22: ='A00 data TCO'!E23 -> 51366 | F22: ='A00 data TCO'!F23 -> 51672 | G22: ='A00 data TCO'!G23 -> 51984.12 | H22: ='A00 data TCO'!H23 -> 52302.482 | I22: ='A00 data TCO'!I23 -> 52627.212 | J22: ='A00 data TCO'!J23 -> 52958.436 | K22: ='A00 data TCO'!K23 -> 53296.285 | ... O22: ='A00 data TCO'!O23 -> 54716.615
C23: Purchase Tax | D23: 5500 | E23: 5530 | F23: 5560.6 | G23: 5591.812 | H23: 5623.6482 | I23: 5656.1212 | J23: 5689.2436 | K23: 5723.0285 | L23: 5757.4891 | M23: 5792.6389 | N23: 5828.4916 | O23: 5865.0615
C24: Consumer Final Price | D24: 60500 | E24: 60830 | F24: 61166.6 | G24: 61509.932 | H24: 61860.131 | I24: 62217.333 | J24: 62581.68 | K24: 62953.314 | L24: 63332.38 | M24: 63719.027 | N24: 64113.408 | O24: 64515.676
C25: Range/Day (km) | D25: 10 | E25: =D25 -> 10 | F25: =E25 -> 10 | G25: =F25 -> 10 | H25: =G25 -> 10 | I25: =H25 -> 10 | J25: =I25 -> 10 | K25: =J25 -> 10 | L25: =K25 -> 10 | ... O25: =N25 -> 10
C26: Years of Usage | D26: 8 | E26: 8 | F26: 8 | G26: 8 | H26: 8 | I26: 8 | J26: 8 | K26: 8 | L26: 8 | M26: 8 | N26: 8 | O26: 8
C27: Oil/hundred KM (L/100km) | D27: 5.3 | E27: 5.3 | F27: 5.3 | G27: 5.3 | H27: 5.3 | I27: 5.3 | J27: 5.3 | K27: 5.3 | L27: 5.3 | M27: 5.3 | N27: 5.3 | O27: 5.3
C28: Oil Price (RMB/Litre) | D28: 7 | E28: 7 | F28: 7 | G28: 7 | H28: 7 | I28: 7 | J28: 7 | K28: 7 | L28: 7 | M28: 7 | N28: 7 | O28: 7
C29: Discount Rate | D29: 0.03 | E29: 0.03 | F29: 0.03 | G29: 0.03 | H29: 0.03 | I29: 0.03 | J29: 0.03 | K29: 0.03 | L29: 0.03 | M29: 0.03 | N29: 0.03 | O29: 0.03
C30: NPV Energy Cost | D30: 9790.8877 | E30: 9505.7162 | F30: 9228.8507 | G30: 8960.0492 | H30: 8699.0769 | I30: 8445.7057 | J30: 8199.7143 | K30: 7960.8876 | L30: 7729.0171 | M30: 7503.9001 | N30: 7285.3399 | O30: 7073.1456
C31: NPV Maintenance Cost | D31: =2*1200+3*600 -> 4200 | E31: =D31*(1-$D$29) -> 4074 | F31: =E31*(1-$D$29) -> 3951.78 | G31: =F31*(1-$D$29) -> 3833.2266 | H31: =G31*(1-$D$29) -> 3718.2298 | I31: =H31*(1-$D$29) -> 3606.6829 | J31: =I31*(1-$D$29) -> 3498.4824 | K31: =J31*(1-$D$29) -> 3393.5279 | L31: =K31*(1-$D$29) -> 3291.7221 | ... O31: =N31*(1-$D$29) -> 3004.2659
C32: NPV Insurance Cost | D32: 21690.849 | E32: 21059.077 | F32: 20445.705 | G32: 19850.199 | H32: 19272.038 | I32: 18710.717 | J32: 18165.744 | K32: 17636.645 | L32: 17122.956 | M32: 16624.23 | N32: 16140.029 | O32: 15669.931
C33: NPV Vehicle and Vessel Tax | D33: 360 | E33: =D33*(1-$D$29) -> 349.2 | F33: =E33*(1-$D$29) -> 338.724 | G33: =F33*(1-$D$29) -> 328.56228 | H33: =G33*(1-$D$29) -> 318.70541 | I33: =H33*(1-$D$29) -> 309.14425 | J33: =I33*(1-$D$29) -> 299.86992 | K33: =J33*(1-$D$29) -> 290.87382 | L33: =K33*(1-$D$29) -> 282.14761 | ... O33: =N33*(1-$D$29) -> 257.50851
C34: Residual Value after Depreciation | D34: =0.35*D22 -> 17873.1 | E34: =0.35*E22 -> 17978.1 | F34: =0.35*F22 -> 18085.2 | G34: =0.35*G22 -> 18194.442 | H34: =0.35*H22 -> 18305.869 | I34: =0.35*I22 -> 18419.524 | J34: =0.35*J22 -> 18535.453 | K34: =0.35*K22 -> 18653.7 | ... O34: =0.35*O22 -> 19150.815
C35: TCO | D35: =D24+D30+D31+D32-D34 -> 78308.637 | E35: =E24+E30+E31+E32-E34 -> 77490.693 | F35: =F24+F30+F31+F32-F34 -> 76707.736 | G35: =G24+G30+G31+G32-G34 -> 75958.965 | H35: =H24+H30+H31+H32-H34 -> 75243.607 | I35: =I24+I30+I31+I32-I34 -> 74560.914 | J35: =J24+J30+J31+J32-J34 -> 73910.168 | K35: =K24+K30+K31+K32-K34 -> 73290.674 | ... O35: =O24+O30+O31+O32-O34 -> 71112.203
D36: 2019 | E36: 2020 | F36: 2021 | G36: 2022 | H36: 2023 | I36: 2024 | J36: 2025 | K36: 2026 | L36: 2027 | M36: 2028 | N36: 2029 | O36: 2030
C37: A00 (10km/day) | D37: =D19-D35 -> 3700.1453 | E37: =E19-E35 -> -3522.3602 | F37: =F19-F35 -> -1963.4357 | G37: =G19-G35 -> -5841.7896 | H37: =H19-H35 -> -9358.6057 | I37: =I19-I35 -> -12551.212 | J37: =J19-J35 -> -15453.197 | K37: =K19-K35 -> -18094.784 | ... O37: =O19-O35 -> -26561.818
C41: TCO 2019 | D41: Price | E41: 10km/day | F41: 20km/day | G41: 30km/day | H41: 40km/day | I41: 60km/day | J41: 80km/day | K41: 300km/day
C42: A00 BEV | D42: 63475 | E42: 82008.782 | F42: 85057.823 | G42: 88206.865 | H42: 91155.906 | I42: 97253.989 | J42: 103352.07 | K42: 129196.86
C43: A00 ICEV | D43: 51066 | E43: 78308.637 | F43: 93499.524 | G43: 108690.41 | H43: 123881.3 | I43: 154263.07 | J43: 184044.85 | K43: 346207.96
C44: A BEV | D44: 160144.44 | F44: 174024.47 | G44: 177680.21 | H44: 181135.95 | I44: 188247.43 | J44: 195358.91 | K44: 228358.76
C45: A ICEV | D45: 140427.78 | F45: 166010.01 | G45: 182494.04 | H45: 198978.06 | I45: 231946.11 | J45: 264314.16 | K45: 442230.55
C46: B BEV | D46: 180670.83 | F46: 191471.9 | G46: 195127.64 | H46: 198583.38 | I46: 205694.86 | J46: 212806.34 | K46: 242504.23
C47: B ICEV | D47: 144616.67 | F47: 172846.35 | G47: 191177.72 | H47: 209509.08 | I47: 246171.8 | J47: 282234.52 | K47: 488279.55
C48: C BEV | D48: 516685.71 | F48: 478382.4 | G48: 482387.06 | H48: 486391.72 | I48: 494601.05 | J48: 502810.38 | K48: 538860.54
C49: C ICEV | D49: 532285.71 | F49: 463598.14 | G49: 481929.5 | H49: 500260.86 | I49: 536923.58 | J49: 572986.31 | K49: 768978.59
D59: 2019 | E59: 2020 | F59: 2021 | G59: 2022 | H59: 2023 | I59: 2024 | J59: 2025 | K59: 2026 | L59: 2027 | M59: 2028 | N59: 2029 | O59: 2030 | P59: 2031 | Q59: 2032 | R59: 2033 | S59: 2034 | T59: 2035 | U59: 2036 | V59: 2037 | W59: 2038 | X59: 2039 | Y59: 2040 | Z59: 2041
C60: Annual range | D60: =10*365 -> 3650 | E60: =10*365 -> 3650 | F60: =10*365 -> 3650 | G60: =10*365 -> 3650 | H60: =10*365 -> 3650 | I60: =10*365 -> 3650 | J60: =10*365 -> 3650 | K60: =10*365 -> 3650 | ... Z60: =10*365 -> 3650
C61: Electricity amount | D61: =(D11/100)*D60 -> 423.4 | E61: =D61 -> 423.4 | F61: =E61 -> 423.4 | G61: =F61 -> 423.4 | H61: =G61 -> 423.4 | I61: =H61 -> 423.4 | J61: =I61 -> 423.4 | K61: =J61 -> 423.4 | L61: =K61 -> 423.4 | ... Z61: =Y61 -> 423.4
C62: Electricity Cost | D62: =D61*D12 -> 338.72 | E62: =D62 -> 338.72 | F62: =E62 -> 338.72 | G62: =F62 -> 338.72 | H62: =G62 -> 338.72 | I62: =H62 -> 338.72 | J62: =I62 -> 338.72 | K62: =J62 -> 338.72 | L62: =K62 -> 338.72 | ... Z62: =Y62 -> 338.72
C63: Discounted Electricity Cost | D63: =D62/(1+$D$13)^(D59-2019) -> 338.72 | E63: =E62/(1+$D$13)^(E59-2019) -> 328.85437 | F63: =F62/(1+$D$13)^(F59-2019) -> 319.27609 | G63: =G62/(1+$D$13)^(G59-2019) -> 309.97678 | H63: =H62/(1+$D$13)^(H59-2019) -> 300.94833 | I63: =I62/(1+$D$13)^(I59-2019) -> 292.18285 | J63: =J62/(1+$D$13)^(J59-2019) -> 283.67267 | K63: =K62/(1+$D$13)^(K59-2019) -> 275.41036 | ... Z63: =Z62/(1+$D$13)^(Z59-2019) -> 176.77543
C64: Electricity Cost NPV | D64: =SUM(D63:K63) -> 2449.0414 | E64: =SUM(E63:L63) -> 2377.7101 | F64: =SUM(F63:M63) -> 2308.4564 | G64: =SUM(G63:N63) -> 2241.2198 | H64: =SUM(H63:O63) -> 2175.9416 | I64: =SUM(I63:P63) -> 2112.5647 | J64: =SUM(J63:Q63) -> 2051.0337 | K64: =SUM(K63:R63) -> 1991.2948 | ... T64: =SUM(T63:AA63) -> 1354.535 | U64: =SUM(#REF!) -> #REF! | V64: =SUM(#REF!) -> #REF! | W64: =SUM(#REF!) -> #REF! | X64: =SUM(#REF!) -> #REF! | Y64: =SUM(#REF!) -> #REF! | Z64: =SUM(#REF!) -> #REF!
C66: Maintenance Cost | D66: =400 -> 400
C70: Insurance cost | D70: 3500 | E70: 3500 | F70: 3500 | G70: 3500 | H70: 3500 | I70: 3500 | J70: 3500 | K70: 3500 | L70: 3500 | M70: 3500 | N70: 3500 | O70: 3500 | P70: 3500 | Q70: 3500 | R70: 3500 | S70: 3500 | T70: 3500 | U70: 3500 | V70: 3500 | W70: 3500 | X70: 3500 | Y70: 3500 | Z70: 3500
C71: Discounted Insurance Cost | D71: =D70/(1+$D$13)^(D59-2019) -> 3500 | E71: =E70/(1+$D$13)^(E59-2019) -> 3398.0583 | F71: =F70/(1+$D$13)^(F59-2019) -> 3299.0857 | G71: =G70/(1+$D$13)^(G59-2019) -> 3202.9958 | H71: =H70/(1+$D$13)^(H59-2019) -> 3109.7047 | I71: =I70/(1+$D$13)^(I59-2019) -> 3019.1307 | J71: =J70/(1+$D$13)^(J59-2019) -> 2931.1949 | K71: =K70/(1+$D$13)^(K59-2019) -> 2845.8203 | ... Z71: =Z70/(1+$D$13)^(Z59-2019) -> 1826.6238
C72: Insurance cost NPV | D72: =SUM(D71:K71) -> 25305.99 | E72: =NPV(0.03,E71:L71) -> 21657.072 | F72: =NPV(0.03,F71:M71) -> 21026.284 | G72: =NPV(0.03,G71:N71) -> 20413.868 | H72: =NPV(0.03,H71:O71) -> 19819.289 | I72: =NPV(0.03,I71:P71) -> 19242.028 | J72: =NPV(0.03,J71:Q71) -> 18681.581 | K72: =NPV(0.03,K71:R71) -> 18137.457 | L72: =NPV(0.03,L71:S71) -> 17609.182 | ... O72: =NPV(0.03,O71:V71) -> 16114.896
C75: Annual range | D75: =10*365 -> 3650 | E75: =10*365 -> 3650 | F75: =10*365 -> 3650 | G75: =10*365 -> 3650 | H75: =10*365 -> 3650 | I75: =10*365 -> 3650 | J75: =10*365 -> 3650 | K75: =10*365 -> 3650 | ... Z75: =10*365 -> 3650
C76: Oil amount | D76: =(D27/100)*D75 -> 193.45 | E76: =(E27/100)*E75 -> 193.45 | F76: =(F27/100)*F75 -> 193.45 | G76: =(G27/100)*G75 -> 193.45 | H76: =(H27/100)*H75 -> 193.45 | I76: =(I27/100)*I75 -> 193.45 | J76: =(J27/100)*J75 -> 193.45 | K76: =(K27/100)*K75 -> 193.45 | ... O76: =(O27/100)*O75 -> 193.45 | P76: =O76 -> 193.45 | Q76: =P76 -> 193.45 | R76: =Q76 -> 193.45 | S76: =R76 -> 193.45 | T76: =S76 -> 193.45 | U76: =T76 -> 193.45 | V76: =U76 -> 193.45 | W76: =V76 -> 193.45 | ... Z76: =Y76 -> 193.45
C77: Oil cost | D77: =D76*$D$28 -> 1354.15 | E77: =E76*$D$28 -> 1354.15 | F77: =F76*$D$28 -> 1354.15 | G77: =G76*$D$28 -> 1354.15 | H77: =H76*$D$28 -> 1354.15 | I77: =I76*$D$28 -> 1354.15 | J77: =J76*$D$28 -> 1354.15 | K77: =K76*$D$28 -> 1354.15 | ... Z77: =Z76*$D$28 -> 1354.15
D78: =D77/(1+$D$29)^(D59-2019) -> 1354.15 | E78: =E77/(1+$D$29)^(E59-2019) -> 1314.7087 | F78: =F77/(1+$D$29)^(F59-2019) -> 1276.4163 | G78: =G77/(1+$D$29)^(G59-2019) -> 1239.2391 | H78: =H77/(1+$D$29)^(H59-2019) -> 1203.1447 | I78: =I77/(1+$D$29)^(I59-2019) -> 1168.1017 | J78: =J77/(1+$D$29)^(J59-2019) -> 1134.0793 | K78: =K77/(1+$D$29)^(K59-2019) -> 1101.0479 | ... Z78: =Z77/(1+$D$29)^(Z59-2019) -> 706.72073
D79: =SUM(D78:K78) -> 9790.8877 | E79: =SUM(E78:L78) -> 9505.7162 | F79: =SUM(F78:M78) -> 9228.8507 | G79: =SUM(G78:N78) -> 8960.0492 | H79: =SUM(H78:O78) -> 8699.0769 | I79: =SUM(I78:P78) -> 8445.7057 | J79: =SUM(J78:Q78) -> 8199.7143 | K79: =SUM(K78:R78) -> 7960.8876 | ... O79: =SUM(O78:V78) -> 7073.1456
D81: 3000 | E81: 3000 | F81: 3000 | G81: 3000 | H81: 3000 | I81: 3000 | J81: 3000 | K81: 3000 | L81: 3000 | M81: 3000 | N81: 3000 | O81: 3000 | P81: 3000 | Q81: 3000 | R81: 3000 | S81: 3000 | T81: 3000 | U81: 3000 | V81: 3000 | W81: 3000 | X81: 3000 | Y81: 3000 | Z81: 3000 | AA81: 3000
D82: =D81/1.03^(D59-2019) -> 3000 | E82: =E81/1.03^(E59-2019) -> 2912.6214 | F82: =F81/1.03^(F59-2019) -> 2827.7877 | G82: =G81/1.03^(G59-2019) -> 2745.425 | H82: =H81/1.03^(H59-2019) -> 2665.4611 | I82: =I81/1.03^(I59-2019) -> 2587.8264 | J82: =J81/1.03^(J59-2019) -> 2512.4528 | K82: =K81/1.03^(K59-2019) -> 2439.2745 | ... Z82: =Z81/1.03^(Z59-2019) -> 1565.6775
D83: =SUM(D82:K82) -> 21690.849 | E83: =SUM(E82:L82) -> 21059.077 | F83: =SUM(F82:M82) -> 20445.705 | G83: =SUM(G82:N82) -> 19850.199 | H83: =SUM(H82:O82) -> 19272.038 | I83: =SUM(I82:P82) -> 18710.717 | J83: =SUM(J82:Q82) -> 18165.744 | K83: =SUM(K82:R82) -> 17636.645 | ... O83: =SUM(O82:V82) -> 15669.931

Sheet A00 TCO (10)
C4: Chery eQ1
D5: 2019 | E5: 2020 | F5: 2021 | G5: 2022 | H5: 2023 | I5: 2024 | J5: 2025 | K5: 2026 | L5: 2027 | M5: 2028 | N5: 2029 | O5: 2030
C6: Retail Price | D6: 65000 | E6: 59928 | F6: 55343.2 | G6: 51196.88 | H6: 47445.192 | I6: 44048.673 | J6: 40971.806 | K6: 38182.625 | L6: 35652.362 | M6: 33355.126 | N6: 31267.614 | O6: 29368.852
C7: Purchase Tax | D7: 0 | E7: 0 | F7: =F6*0.1 -> 5534.32 | G7: =G6*0.1 -> 5119.688 | H7: =H6*0.1 -> 4744.5192 | I7: =I6*0.1 -> 4404.8673 | J7: =J6*0.1 -> 4097.1806 | K7: =K6*0.1 -> 3818.2625 | L7: =L6*0.1 -> 3565.2362 | M7: =M6*0.1 -> 3335.5126 | ... O7: =O6*0.1 -> 2936.8852
C8: Consumer Final Price | D8: =D6+D7 -> 65000 | E8: =E6+E7 -> 59928 | F8: =F6+F7 -> 60877.52 | G8: =G6+G7 -> 56316.568 | H8: =H6+H7 -> 52189.711 | I8: =I6+I7 -> 48453.54 | J8: =J6+J7 -> 45068.986 | K8: =K6+K7 -> 42000.887 | ... O8: =O6+O7 -> 32305.737
C9: Range/Day (km) | D9: 10 | E9: 10 | F9: 10 | G9: 10 | H9: 10 | I9: 10 | J9: 10 | K9: 10 | L9: 10 | M9: 10 | N9: 10 | O9: 10
C10: Years of Usage | D10: 8 | E10: 8 | F10: 8 | G10: 8 | H10: 8 | I10: 8 | J10: 8 | K10: 8 | L10: 8 | M10: 8 | N10: 8 | O10: 8
C11: Electricity/hundred KM (Kwh) | D11: 11.6 | E11: 11.6 | F11: 11.6 | G11: 11.6 | H11: 11.6 | I11: 11.6 | J11: 11.6 | K11: 11.6 | L11: 11.6 | M11: 11.6 | N11: 11.6 | O11: 11.6
C12: Electricity Price (RMB/Kwh) | D12: 0.8 | E12: 0.8 | F12: 0.8 | G12: 0.8 | H12: 0.8 | I12: 0.8 | J12: 0.8 | K12: 0.8 | L12: 0.8 | M12: 0.8 | N12: 0.8 | O12: 0.8
C13: Discount Rate | D13: 0.03 | E13: 0.03 | F13: 0.03 | G13: 0.03 | H13: 0.03 | I13: 0.03 | J13: 0.03 | K13: 0.03 | L13: 0.03 | M13: 0.03 | N13: 0.03 | O13: 0.03
C14: NPV Energy Cost | D14: 2449.0414 | E14: 2377.7101 | F14: 2308.4564 | G14: 2241.2198 | H14: 2175.9416 | I14: 2112.5647 | J14: 2051.0337 | K14: 1991.2948 | L14: 1933.2959 | M14: 1876.9863 | N14: 1822.3168 | O14: 1769.2396
C15: NPV Maintenance Cost | D15: 300 | E15: =D15*(1-$D$13) -> 291 | F15: =E15*(1-$D$13) -> 282.27 | G15: =F15*(1-$D$13) -> 273.8019 | H15: =G15*(1-$D$13) -> 265.58784 | I15: =H15*(1-$D$13) -> 257.62021 | J15: =I15*(1-$D$13) -> 249.8916 | K15: =J15*(1-$D$13) -> 242.39485 | L15: =K15*(1-$D$13) -> 235.12301 | ... O15: =N15*(1-$D$13) -> 214.59042
C16: NPV Insurance Cost | D16: 25305.99 | E16: 21657.072 | F16: 21026.284 | G16: 20413.868 | H16: 19819.289 | I16: 19242.028 | J16: 18681.581 | K16: 18137.457 | L16: 17609.182 | M16: 17096.293 | N16: 16598.343 | O16: 16114.896
C17: NPV Vehicle and Vessel Tax | D17: 0 | E17: 0 | F17: 0 | G17: 0 | H17: 0 | I17: 0 | J17: 0 | K17: 0 | L17: 0 | M17: 0 | N17: 0 | O17: 0
C18: Residual Value after Depreciation | D18: =0.15*D6 -> 9750 | E18: =0.15*E6 -> 8989.2 | F18: =0.15*F6 -> 8301.48 | G18: =0.15*G6 -> 7679.532 | H18: =0.15*H6 -> 7116.7788 | I18: =0.15*I6 -> 6607.3009 | J18: =0.15*J6 -> 6145.7708 | K18: =0.15*K6 -> 5727.3937 | ... O18: =0.15*O6 -> 4405.3278
C19: TCO | D19: =D8+D14+D15+D16+D17-D18 -> 83305.032 | E19: =E8+E14+E15+E16+E17-E18 -> 75264.583 | F19: =F8+F14+F15+F16+F17-F18 -> 76193.05 | G19: =G8+G14+G15+G16+G17-G18 -> 71565.926 | H19: =H8+H14+H15+H16+H17-H18 -> 67333.751 | I19: =I8+I14+I15+I16+I17-I18 -> 63458.452 | J19: =J8+J14+J15+J16+J17-J18 -> 59905.721 | K19: =K8+K14+K15+K16+K17-K18 -> 56644.641 | ... O19: =O8+O14+O15+O16+O17-O18 -> 45999.136
C20: Chery QQ6
D21: 2019 | E21: 2020 | F21: 2021 | G21: 2022 | H21: 2023 | I21: 2024 | J21: 2025 | K21: 2026 | L21: 2027 | M21: 2028 | N21: 2029 | O21: 2030
C22: Retail Price | D22: 55000 | E22: 55300 | F22: 55606 | G22: 55918.12 | H22: 56236.482 | I22: 56561.212 | J22: 56892.436 | K22: 57230.285 | L22: 57574.891 | M22: 57926.389 | N22: 58284.916 | O22: 58650.615
C23: Purchase Tax | D23: 5500 | E23: 5530 | F23: 5560.6 | G23: 5591.812 | H23: 5623.6482 | I23: 5656.1212 | J23: 5689.2436 | K23: 5723.0285 | L23: 5757.4891 | M23: 5792.6389 | N23: 5828.4916 | O23: 5865.0615
C24: Consumer Final Price | D24: 60500 | E24: 60830 | F24: 61166.6 | G24: 61509.932 | H24: 61860.131 | I24: 62217.333 | J24: 62581.68 | K24: 62953.314 | L24: 63332.38 | M24: 63719.027 | N24: 64113.408 | O24: 64515.676
C25: Range/Day (km) | D25: 10 | E25: =D25 -> 10 | F25: =E25 -> 10 | G25: =F25 -> 10 | H25: =G25 -> 10 | I25: =H25 -> 10 | J25: =I25 -> 10 | K25: =J25 -> 10 | L25: =K25 -> 10 | ... O25: =N25 -> 10
C26: Years of Usage | D26: 8 | E26: 8 | F26: 8 | G26: 8 | H26: 8 | I26: 8 | J26: 8 | K26: 8 | L26: 8 | M26: 8 | N26: 8 | O26: 8
C27: Oil/hundred KM (L/100km) | D27: 5.3 | E27: 5.3 | F27: 5.3 | G27: 5.3 | H27: 5.3 | I27: 5.3 | J27: 5.3 | K27: 5.3 | L27: 5.3 | M27: 5.3 | N27: 5.3 | O27: 5.3
C28: Oil Price (RMB/Litre) | D28: 7 | E28: 7 | F28: 7 | G28: 7 | H28: 7 | I28: 7 | J28: 7 | K28: 7 | L28: 7 | M28: 7 | N28: 7 | O28: 7
C29: Discount Rate | D29: 0.03 | E29: 0.03 | F29: 0.03 | G29: 0.03 | H29: 0.03 | I29: 0.03 | J29: 0.03 | K29: 0.03 | L29: 0.03 | M29: 0.03 | N29: 0.03 | O29: 0.03
C30: NPV Energy Cost | D30: 9790.8877 | E30: 9505.7162 | F30: 9228.8507 | G30: 8960.0492 | H30: 8699.0769 | I30: 8445.7057 | J30: 8199.7143 | K30: 7960.8876 | L30: 7729.0171 | M30: 7503.9001 | N30: 7285.3399 | O30: 7073.1456
C31: NPV Maintenance Cost | D31: =2*1200+3*600 -> 4200 | E31: =D31*(1-$D$29) -> 4074 | F31: =E31*(1-$D$29) -> 3951.78 | G31: =F31*(1-$D$29) -> 3833.2266 | H31: =G31*(1-$D$29) -> 3718.2298 | I31: =H31*(1-$D$29) -> 3606.6829 | J31: =I31*(1-$D$29) -> 3498.4824 | K31: =J31*(1-$D$29) -> 3393.5279 | L31: =K31*(1-$D$29) -> 3291.7221 | ... O31: =N31*(1-$D$29) -> 3004.2659
C32: NPV Insurance Cost | D32: 21690.849 | E32: 21059.077 | F32: 20445.705 | G32: 19850.199 | H32: 19272.038 | I32: 18710.717 | J32: 18165.744 | K32: 17636.645 | L32: 17122.956 | M32: 16624.23 | N32: 16140.029 | O32: 15669.931
C33: NPV Vehicle and Vessel Tax | D33: 360 | E33: =D33*(1-$D$29) -> 349.2 | F33: =E33*(1-$D$29) -> 338.724 | G33: =F33*(1-$D$29) -> 328.56228 | H33: =G33*(1-$D$29) -> 318.70541 | I33: =H33*(1-$D$29) -> 309.14425 | J33: =I33*(1-$D$29) -> 299.86992 | K33: =J33*(1-$D$29) -> 290.87382 | L33: =K33*(1-$D$29) -> 282.14761 | ... O33: =N33*(1-$D$29) -> 257.50851
C34: Residual Value after Depreciation | D34: =0.35*D22 -> 19250 | E34: =0.35*E22 -> 19355 | F34: =0.35*F22 -> 19462.1 | G34: =0.35*G22 -> 19571.342 | H34: =0.35*H22 -> 19682.769 | I34: =0.35*I22 -> 19796.424 | J34: =0.35*J22 -> 19912.353 | K34: =0.35*K22 -> 20030.6 | ... O34: =0.35*O22 -> 20527.715
C35: TCO | D35: =D24+D30+D31+D32-D34 -> 76931.737 | E35: =E24+E30+E31+E32-E34 -> 76113.793 | F35: =F24+F30+F31+F32-F34 -> 75330.836 | G35: =G24+G30+G31+G32-G34 -> 74582.065 | H35: =H24+H30+H31+H32-H34 -> 73866.707 | I35: =I24+I30+I31+I32-I34 -> 73184.014 | J35: =J24+J30+J31+J32-J34 -> 72533.268 | K35: =K24+K30+K31+K32-K34 -> 71913.774 | ... O35: =O24+O30+O31+O32-O34 -> 69735.303
D37: 2019 | E37: 2020 | F37: 2021 | G37: 2022 | H37: 2023 | I37: 2024 | J37: 2025 | K37: 2026 | L37: 2027 | M37: 2028 | N37: 2029 | O37: 2030 | P37: 2031 | Q37: 2032 | R37: 2033 | S37: 2034 | T37: 2035 | U37: 2036 | V37: 2037 | W37: 2038 | X37: 2039 | Y37: 2040 | Z37: 2041
C38: Annual range | D38: =10*365 -> 3650 | E38: =10*365 -> 3650 | F38: =10*365 -> 3650 | G38: =10*365 -> 3650 | H38: =10*365 -> 3650 | I38: =10*365 -> 3650 | J38: =10*365 -> 3650 | K38: =10*365 -> 3650 | ... Z38: =10*365 -> 3650
C39: Electricity amount | D39: =(D11/100)*D38 -> 423.4 | E39: =D39 -> 423.4 | F39: =E39 -> 423.4 | G39: =F39 -> 423.4 | H39: =G39 -> 423.4 | I39: =H39 -> 423.4 | J39: =I39 -> 423.4 | K39: =J39 -> 423.4 | L39: =K39 -> 423.4 | ... Z39: =Y39 -> 423.4
C40: Electricity Cost | D40: =D39*D12 -> 338.72 | E40: =D40 -> 338.72 | F40: =E40 -> 338.72 | G40: =F40 -> 338.72 | H40: =G40 -> 338.72 | I40: =H40 -> 338.72 | J40: =I40 -> 338.72 | K40: =J40 -> 338.72 | L40: =K40 -> 338.72 | ... Z40: =Y40 -> 338.72
C41: Discounted Electricity Cost | D41: =D40/(1+$D$13)^(D37-2019) -> 338.72 | E41: =E40/(1+$D$13)^(E37-2019) -> 328.85437 | F41: =F40/(1+$D$13)^(F37-2019) -> 319.27609 | G41: =G40/(1+$D$13)^(G37-2019) -> 309.97678 | H41: =H40/(1+$D$13)^(H37-2019) -> 300.94833 | I41: =I40/(1+$D$13)^(I37-2019) -> 292.18285 | J41: =J40/(1+$D$13)^(J37-2019) -> 283.67267 | K41: =K40/(1+$D$13)^(K37-2019) -> 275.41036 | ... Z41: =Z40/(1+$D$13)^(Z37-2019) -> 176.77543
C42: Electricity Cost NPV | D42: =SUM(D41:K41) -> 2449.0414 | E42: =SUM(E41:L41) -> 2377.7101 | F42: =SUM(F41:M41) -> 2308.4564 | G42: =SUM(G41:N41) -> 2241.2198 | H42: =SUM(H41:O41) -> 2175.9416 | I42: =SUM(I41:P41) -> 2112.5647 | J42: =SUM(J41:Q41) -> 2051.0337 | K42: =SUM(K41:R41) -> 1991.2948 | ... Z42: =SUM(Z41:AG41) -> 176.77543
C44: Maintenance Cost | D44: =400 -> 400
C48: Insurance cost | D48: 3500 | E48: 3500 | F48: 3500 | G48: 3500 | H48: 3500 | I48: 3500 | J48: 3500 | K48: 3500 | L48: 3500 | M48: 3500 | N48: 3500 | O48: 3500 | P48: 3500 | Q48: 3500 | R48: 3500 | S48: 3500 | T48: 3500 | U48: 3500 | V48: 3500 | W48: 3500 | X48: 3500 | Y48: 3500 | Z48: 3500
C49: Discounted Insurance Cost | D49: =D48/(1+$D$13)^(D37-2019) -> 3500 | E49: =E48/(1+$D$13)^(E37-2019) -> 3398.0583 | F49: =F48/(1+$D$13)^(F37-2019) -> 3299.0857 | G49: =G48/(1+$D$13)^(G37-2019) -> 3202.9958 | H49: =H48/(1+$D$13)^(H37-2019) -> 3109.7047 | I49: =I48/(1+$D$13)^(I37-2019) -> 3019.1307 | J49: =J48/(1+$D$13)^(J37-2019) -> 2931.1949 | K49: =K48/(1+$D$13)^(K37-2019) -> 2845.8203 | ... Z49: =Z48/(1+$D$13)^(Z37-2019) -> 1826.6238
C50: Insurance cost NPV | D50: =SUM(D49:K49) -> 25305.99 | E50: =NPV(0.03,E49:L49) -> 21657.072 | F50: =NPV(0.03,F49:M49) -> 21026.284 | G50: =NPV(0.03,G49:N49) -> 20413.868 | H50: =NPV(0.03,H49:O49) -> 19819.289 | I50: =NPV(0.03,I49:P49) -> 19242.028 | J50: =NPV(0.03,J49:Q49) -> 18681.581 | K50: =NPV(0.03,K49:R49) -> 18137.457 | L50: =NPV(0.03,L49:S49) -> 17609.182 | ... O50: =NPV(0.03,O49:V49) -> 16114.896
C53: Annual range | D53: =10*365 -> 3650 | E53: =10*365 -> 3650 | F53: =10*365 -> 3650 | G53: =10*365 -> 3650 | H53: =10*365 -> 3650 | I53: =10*365 -> 3650 | J53: =10*365 -> 3650 | K53: =10*365 -> 3650 | ... Z53: =10*365 -> 3650
C54: Oil amount | D54: =(D27/100)*D53 -> 193.45 | E54: =(E27/100)*E53 -> 193.45 | F54: =(F27/100)*F53 -> 193.45 | G54: =(G27/100)*G53 -> 193.45 | H54: =(H27/100)*H53 -> 193.45 | I54: =(I27/100)*I53 -> 193.45 | J54: =(J27/100)*J53 -> 193.45 | K54: =(K27/100)*K53 -> 193.45 | ... O54: =(O27/100)*O53 -> 193.45 | P54: =O54 -> 193.45 | Q54: =P54 -> 193.45 | R54: =Q54 -> 193.45 | S54: =R54 -> 193.45 | T54: =S54 -> 193.45 | U54: =T54 -> 193.45 | V54: =U54 -> 193.45 | W54: =V54 -> 193.45 | ... Z54: =Y54 -> 193.45
C55: Oil cost | D55: =D54*$D$28 -> 1354.15 | E55: =E54*$D$28 -> 1354.15 | F55: =F54*$D$28 -> 1354.15 | G55: =G54*$D$28 -> 1354.15 | H55: =H54*$D$28 -> 1354.15 | I55: =I54*$D$28 -> 1354.15 | J55: =J54*$D$28 -> 1354.15 | K55: =K54*$D$28 -> 1354.15 | ... Z55: =Z54*$D$28 -> 1354.15
D56: =D55/(1+$D$29)^(D37-2019) -> 1354.15 | E56: =E55/(1+$D$29)^(E37-2019) -> 1314.7087 | F56: =F55/(1+$D$29)^(F37-2019) -> 1276.4163 | G56: =G55/(1+$D$29)^(G37-2019) -> 1239.2391 | H56: =H55/(1+$D$29)^(H37-2019) -> 1203.1447 | I56: =I55/(1+$D$29)^(I37-2019) -> 1168.1017 | J56: =J55/(1+$D$29)^(J37-2019) -> 1134.0793 | K56: =K55/(1+$D$29)^(K37-2019) -> 1101.0479 | ... Z56: =Z55/(1+$D$29)^(Z37-2019) -> 706.72073
D57: =SUM(D56:K56) -> 9790.8877 | E57: =SUM(E56:L56) -> 9505.7162 | F57: =SUM(F56:M56) -> 9228.8507 | G57: =SUM(G56:N56) -> 8960.0492 | H57: =SUM(H56:O56) -> 8699.0769 | I57: =SUM(I56:P56) -> 8445.7057 | J57: =SUM(J56:Q56) -> 8199.7143 | K57: =SUM(K56:R56) -> 7960.8876 | ... O57: =SUM(O56:V56) -> 7073.1456
D59: 3000 | E59: 3000 | F59: 3000 | G59: 3000 | H59: 3000 | I59: 3000 | J59: 3000 | K59: 3000 | L59: 3000 | M59: 3000 | N59: 3000 | O59: 3000 | P59: 3000 | Q59: 3000 | R59: 3000 | S59: 3000 | T59: 3000 | U59: 3000 | V59: 3000 | W59: 3000 | X59: 3000 | Y59: 3000 | Z59: 3000 | AA59: 3000
D60: =D59/1.03^(D37-2019) -> 3000 | E60: =E59/1.03^(E37-2019) -> 2912.6214 | F60: =F59/1.03^(F37-2019) -> 2827.7877 | G60: =G59/1.03^(G37-2019) -> 2745.425 | H60: =H59/1.03^(H37-2019) -> 2665.4611 | I60: =I59/1.03^(I37-2019) -> 2587.8264 | J60: =J59/1.03^(J37-2019) -> 2512.4528 | K60: =K59/1.03^(K37-2019) -> 2439.2745 | ... Z60: =Z59/1.03^(Z37-2019) -> 1565.6775
D61: =SUM(D60:K60) -> 21690.849 | E61: =SUM(E60:L60) -> 21059.077 | F61: =SUM(F60:M60) -> 20445.705 | G61: =SUM(G60:N60) -> 19850.199 | H61: =SUM(H60:O60) -> 19272.038 | I61: =SUM(I60:P60) -> 18710.717 | J61: =SUM(J60:Q60) -> 18165.744 | K61: =SUM(K60:R60) -> 17636.645 | ... O61: =SUM(O60:V60) -> 15669.931

Sheet A00 TCO (20)
C4: A00 Class BEV Sample Avg
D5: 2019 | E5: 2020 | F5: 2021 | G5: 2022 | H5: 2023 | I5: 2024 | J5: 2025 | K5: 2026 | L5: 2027 | M5: 2028 | N5: 2029 | O5: 2030
C6: Retail Price | D6: 63475 | E6: 58403 | F6: 53818.2 | G6: 49671.88 | H6: 45920.192 | I6: 42523.673 | J6: 39446.806 | K6: 36657.625 | L6: 34127.362 | M6: 31830.126 | N6: 29742.614 | O6: 27843.852
C7: Purchase Tax | D7: 0 | E7: 0 | F7: =F6*0.1 -> 5381.82 | G7: =G6*0.1 -> 4967.188 | H7: =H6*0.1 -> 4592.0192 | I7: =I6*0.1 -> 4252.3673 | J7: =J6*0.1 -> 3944.6806 | K7: =K6*0.1 -> 3665.7625 | L7: =L6*0.1 -> 3412.7362 | M7: =M6*0.1 -> 3183.0126 | ... O7: =O6*0.1 -> 2784.3852
C8: Consumer Final Price | D8: =D6+D7 -> 63475 | E8: =E6+E7 -> 58403 | F8: =F6+F7 -> 59200.02 | G8: =G6+G7 -> 54639.068 | H8: =H6+H7 -> 50512.211 | I8: =I6+I7 -> 46776.04 | J8: =J6+J7 -> 43391.486 | K8: =K6+K7 -> 40323.387 | ... O8: =O6+O7 -> 30628.237
C9: Range/Day (km) | D9: 20 | E9: 20 | F9: 20 | G9: 20 | H9: 20 | I9: 20 | J9: 20 | K9: 20 | L9: 20 | M9: 20 | N9: 20 | O9: 20
C10: Years of Usage | D10: 8 | E10: 8 | F10: 8 | G10: 8 | H10: 8 | I10: 8 | J10: 8 | K10: 8 | L10: 8 | M10: 8 | N10: 8 | O10: 8
C11: Electricity/hundred KM (Kwh) | D11: 11.6 | E11: 11.6 | F11: 11.6 | G11: 11.6 | H11: 11.6 | I11: 11.6 | J11: 11.6 | K11: 11.6 | L11: 11.6 | M11: 11.6 | N11: 11.6 | O11: 11.6
C12: Electricity Price (RMB/Kwh) | D12: 0.8 | E12: 0.8 | F12: 0.8 | G12: 0.8 | H12: 0.8 | I12: 0.8 | J12: 0.8 | K12: 0.8 | L12: 0.8 | M12: 0.8 | N12: 0.8 | O12: 0.8
C13: Discount Rate | D13: 0.03 | E13: 0.03 | F13: 0.03 | G13: 0.03 | H13: 0.03 | I13: 0.03 | J13: 0.03 | K13: 0.03 | L13: 0.03 | M13: 0.03 | N13: 0.03 | O13: 0.03
C14: NPV Energy Cost | D14: 4898.0829 | E14: 4755.4203 | F14: 4616.9129 | G14: 4482.4397 | H14: 4351.8832 | I14: 4225.1293 | J14: 4102.0673 | K14: 3982.5896 | L14: 3866.5919 | M14: 3753.9727 | N14: 3644.6337 | O14: 3538.4793
C15: NPV Maintenance Cost | D15: =3*100+2*300 -> 900 | E15: =D15*(1-$D$13) -> 873 | F15: =E15*(1-$D$13) -> 846.81 | G15: =F15*(1-$D$13) -> 821.4057 | H15: =G15*(1-$D$13) -> 796.76353 | I15: =H15*(1-$D$13) -> 772.86062 | J15: =I15*(1-$D$13) -> 749.6748 | K15: =J15*(1-$D$13) -> 727.18456 | L15: =K15*(1-$D$13) -> 705.36902 | ... O15: =N15*(1-$D$13) -> 643.77126
C16: NPV Insurance Cost | D16: 25305.99 | E16: 21657.072 | F16: 21026.284 | G16: 20413.868 | H16: 19819.289 | I16: 19242.028 | J16: 18681.581 | K16: 18137.457 | L16: 17609.182 | M16: 17096.293 | N16: 16598.343 | O16: 16114.896
C17: NPV Vehicle and Vessel Tax | D17: 0 | E17: 0 | F17: 0 | G17: 0 | H17: 0 | I17: 0 | J17: 0 | K17: 0 | L17: 0 | M17: 0 | N17: 0 | O17: 0
C18: Residual Value after Depreciation | D18: =0.15*D6 -> 9521.25 | E18: =0.15*E6 -> 8760.45 | F18: =0.15*F6 -> 8072.73 | G18: =0.15*G6 -> 7450.782 | H18: =0.15*H6 -> 6888.0288 | I18: =0.15*I6 -> 6378.5509 | J18: =0.15*J6 -> 5917.0208 | K18: =0.15*K6 -> 5498.6437 | ... O18: =0.15*O6 -> 4176.5778
C19: TCO | D19: =D8+D14+D15+D16+D17-D18 -> 85057.823 | E19: =E8+E14+E15+E16+E17-E18 -> 76928.043 | F19: =F8+F14+F15+F16+F17-F18 -> 77617.297 | G19: =G8+G14+G15+G16+G17-G18 -> 72905.999 | H19: =H8+H14+H15+H16+H17-H18 -> 68592.118 | I19: =I8+I14+I15+I16+I17-I18 -> 64637.507 | J19: =J8+J14+J15+J16+J17-J18 -> 61007.788 | K19: =K8+K14+K15+K16+K17-K18 -> 57671.975 | ... O19: =O8+O14+O15+O16+O17-O18 -> 46748.806
C20: A00 Class ICEV Sample Avg
D21: 2019 | E21: 2020 | F21: 2021 | G21: 2022 | H21: 2023 | I21: 2024 | J21: 2025 | K21: 2026 | L21: 2027 | M21: 2028 | N21: 2029 | O21: 2030
C22: Retail Price | D22: 51066 | E22: 51366 | F22: 51672 | G22: 51984.12 | H22: 52302.482 | I22: 52627.212 | J22: 52958.436 | K22: 53296.285 | L22: 53640.891 | M22: 53992.389 | N22: 54350.916 | O22: 54716.615
C23: Purchase Tax | D23: 5500 | E23: 5530 | F23: 5560.6 | G23: 5591.812 | H23: 5623.6482 | I23: 5656.1212 | J23: 5689.2436 | K23: 5723.0285 | L23: 5757.4891 | M23: 5792.6389 | N23: 5828.4916 | O23: 5865.0615
C24: Consumer Final Price | D24: 60500 | E24: 60830 | F24: 61166.6 | G24: 61509.932 | H24: 61860.131 | I24: 62217.333 | J24: 62581.68 | K24: 62953.314 | L24: 63332.38 | M24: 63719.027 | N24: 64113.408 | O24: 64515.676
C25: Range/Day (km) | D25: 20 | E25: =D25 -> 20 | F25: =E25 -> 20 | G25: =F25 -> 20 | H25: =G25 -> 20 | I25: =H25 -> 20 | J25: =I25 -> 20 | K25: =J25 -> 20 | L25: =K25 -> 20 | ... O25: =N25 -> 20
C26: Years of Usage | D26: 8 | E26: 8 | F26: 8 | G26: 8 | H26: 8 | I26: 8 | J26: 8 | K26: 8 | L26: 8 | M26: 8 | N26: 8 | O26: 8
C27: Oil/hundred KM (L/100km) | D27: 5.3 | E27: 5.3 | F27: 5.3 | G27: 5.3 | H27: 5.3 | I27: 5.3 | J27: 5.3 | K27: 5.3 | L27: 5.3 | M27: 5.3 | N27: 5.3 | O27: 5.3
C28: Oil Price (RMB/Litre) | D28: 7 | E28: 7 | F28: 7 | G28: 7 | H28: 7 | I28: 7 | J28: 7 | K28: 7 | L28: 7 | M28: 7 | N28: 7 | O28: 7
C29: Discount Rate | D29: 0.03 | E29: 0.03 | F29: 0.03 | G29: 0.03 | H29: 0.03 | I29: 0.03 | J29: 0.03 | K29: 0.03 | L29: 0.03 | M29: 0.03 | N29: 0.03 | O29: 0.03
C30: NPV Energy Cost | D30: 19581.775 | E30: 19011.432 | F30: 18457.701 | G30: 17920.098 | H30: 17398.154 | I30: 16891.411 | J30: 16399.429 | K30: 15921.775 | L30: 15458.034 | M30: 15007.8 | N30: 14570.68 | O30: 14146.291
C31: NPV Maintenance Cost | D31: =5*1200+6*600 -> 9600 | E31: =D31*(1-$D$29) -> 9312 | F31: =E31*(1-$D$29) -> 9032.64 | G31: =F31*(1-$D$29) -> 8761.6608 | H31: =G31*(1-$D$29) -> 8498.811 | I31: =H31*(1-$D$29) -> 8243.8466 | J31: =I31*(1-$D$29) -> 7996.5312 | K31: =J31*(1-$D$29) -> 7756.6353 | L31: =K31*(1-$D$29) -> 7523.9363 | ... O31: =N31*(1-$D$29) -> 6866.8935
C32: NPV Insurance Cost | D32: 21690.849 | E32: 21059.077 | F32: 20445.705 | G32: 19850.199 | H32: 19272.038 | I32: 18710.717 | J32: 18165.744 | K32: 17636.645 | L32: 17122.956 | M32: 16624.23 | N32: 16140.029 | O32: 15669.931
C33: NPV Vehicle and Vessel Tax | D33: 360 | E33: =D33*(1-$D$29) -> 349.2 | F33: =E33*(1-$D$29) -> 338.724 | G33: =F33*(1-$D$29) -> 328.56228 | H33: =G33*(1-$D$29) -> 318.70541 | I33: =H33*(1-$D$29) -> 309.14425 | J33: =I33*(1-$D$29) -> 299.86992 | K33: =J33*(1-$D$29) -> 290.87382 | L33: =K33*(1-$D$29) -> 282.14761 | ... O33: =N33*(1-$D$29) -> 257.50851
C34: Residual Value after Depreciation | D34: =0.35*D22 -> 17873.1 | E34: =0.35*E22 -> 17978.1 | F34: =0.35*F22 -> 18085.2 | G34: =0.35*G22 -> 18194.442 | H34: =0.35*H22 -> 18305.869 | I34: =0.35*I22 -> 18419.524 | J34: =0.35*J22 -> 18535.453 | K34: =0.35*K22 -> 18653.7 | ... O34: =0.35*O22 -> 19150.815
C35: TCO | D35: =D24+D30+D31+D32-D34 -> 93499.524 | E35: =E24+E30+E31+E32-E34 -> 92234.409 | F35: =F24+F30+F31+F32-F34 -> 91017.447 | G35: =G24+G30+G31+G32-G34 -> 89847.449 | H35: =H24+H30+H31+H32-H34 -> 88723.265 | I35: =I24+I30+I31+I32-I34 -> 87643.784 | J35: =J24+J30+J31+J32-J34 -> 86607.931 | K35: =K24+K30+K31+K32-K34 -> 85614.669 | ... O35: =O24+O30+O31+O32-O34 -> 82047.976
D37: 2019 | E37: 2020 | F37: 2021 | G37: 2022 | H37: 2023 | I37: 2024 | J37: 2025 | K37: 2026 | L37: 2027 | M37: 2028 | N37: 2029 | O37: 2030
C38: A00 (20km/day) | D38: =D19-D35 -> -8441.701 | E38: =E19-E35 -> -15306.366 | F38: =F19-F35 -> -13400.15 | G38: =G19-G35 -> -16941.449 | H38: =H19-H35 -> -20131.146 | I38: =I19-I35 -> -23006.276 | J38: =J19-J35 -> -25600.143 | K38: =K19-K35 -> -27942.694 | ... O38: =O19-O35 -> -35299.17
D57: 2019 | E57: 2020 | F57: 2021 | G57: 2022 | H57: 2023 | I57: 2024 | J57: 2025 | K57: 2026 | L57: 2027 | M57: 2028 | N57: 2029 | O57: 2030 | P57: 2031 | Q57: 2032 | R57: 2033 | S57: 2034 | T57: 2035 | U57: 2036 | V57: 2037 | W57: 2038 | X57: 2039 | Y57: 2040 | Z57: 2041
C58: Annual range | D58: =20*365 -> 7300 | E58: =60*365 -> 21900 | F58: =60*365 -> 21900 | G58: =60*365 -> 21900 | H58: =60*365 -> 21900 | I58: =60*365 -> 21900 | J58: =60*365 -> 21900 | K58: =60*365 -> 21900 | L58: =60*365 -> 21900 | ... Z58: =60*365 -> 21900
C59: Electricity amount | D59: =(D11/100)*D58 -> 846.8 | E59: =D59 -> 846.8 | F59: =E59 -> 846.8 | G59: =F59 -> 846.8 | H59: =G59 -> 846.8 | I59: =H59 -> 846.8 | J59: =I59 -> 846.8 | K59: =J59 -> 846.8 | L59: =K59 -> 846.8 | ... Z59: =Y59 -> 846.8
C60: Electricity Cost | D60: =D59*D12 -> 677.44 | E60: =D60 -> 677.44 | F60: =E60 -> 677.44 | G60: =F60 -> 677.44 | H60: =G60 -> 677.44 | I60: =H60 -> 677.44 | J60: =I60 -> 677.44 | K60: =J60 -> 677.44 | L60: =K60 -> 677.44 | ... Z60: =Y60 -> 677.44
C61: Discounted Electricity Cost | D61: =D60/(1+$D$13)^(D57-2019) -> 677.44 | E61: =E60/(1+$D$13)^(E57-2019) -> 657.70874 | F61: =F60/(1+$D$13)^(F57-2019) -> 638.55217 | G61: =G60/(1+$D$13)^(G57-2019) -> 619.95357 | H61: =H60/(1+$D$13)^(H57-2019) -> 601.89667 | I61: =I60/(1+$D$13)^(I57-2019) -> 584.36569 | J61: =J60/(1+$D$13)^(J57-2019) -> 567.34533 | K61: =K60/(1+$D$13)^(K57-2019) -> 550.82071 | ... Z61: =Z60/(1+$D$13)^(Z57-2019) -> 353.55086
C62: Electricity Cost NPV | D62: =SUM(D61:K61) -> 4898.0829 | E62: =SUM(E61:L61) -> 4755.4203 | F62: =SUM(F61:M61) -> 4616.9129 | G62: =SUM(G61:N61) -> 4482.4397 | H62: =SUM(H61:O61) -> 4351.8832 | I62: =SUM(I61:P61) -> 4225.1293 | J62: =SUM(J61:Q61) -> 4102.0673 | K62: =SUM(K61:R61) -> 3982.5896 | ... S62: =SUM(S61:Z61) -> 3143.893 | T62: =SUM(T41:AA41) -> 0 | U62: =SUM(U41:AB41) -> 0 | V62: =SUM(V41:AC41) -> 0 | W62: =SUM(W41:AD41) -> 0 | X62: =SUM(X41:AE41) -> 0 | Y62: =SUM(Y41:AF41) -> 0 | Z62: =SUM(Z41:AG41) -> 0
C64: Maintenance Cost | D64: =400 -> 400
C68: Insurance cost | D68: 3500 | E68: 3500 | F68: 3500 | G68: 3500 | H68: 3500 | I68: 3500 | J68: 3500 | K68: 3500 | L68: 3500 | M68: 3500 | N68: 3500 | O68: 3500 | P68: 3500 | Q68: 3500 | R68: 3500 | S68: 3500 | T68: 3500 | U68: 3500 | V68: 3500 | W68: 3500 | X68: 3500 | Y68: 3500 | Z68: 3500
C69: Discounted Insurance Cost | D69: =D68/(1+$D$13)^(D57-2019) -> 3500 | E69: =E68/(1+$D$13)^(E57-2019) -> 3398.0583 | F69: =F68/(1+$D$13)^(F57-2019) -> 3299.0857 | G69: =G68/(1+$D$13)^(G57-2019) -> 3202.9958 | H69: =H68/(1+$D$13)^(H57-2019) -> 3109.7047 | I69: =I68/(1+$D$13)^(I57-2019) -> 3019.1307 | J69: =J68/(1+$D$13)^(J57-2019) -> 2931.1949 | K69: =K68/(1+$D$13)^(K57-2019) -> 2845.8203 | ... Z69: =Z68/(1+$D$13)^(Z57-2019) -> 1826.6238
C70: Insurance cost NPV | D70: =SUM(D69:K69) -> 25305.99 | E70: =NPV(0.03,E69:L69) -> 21657.072 | F70: =NPV(0.03,F69:M69) -> 21026.284 | G70: =NPV(0.03,G69:N69) -> 20413.868 | H70: =NPV(0.03,H69:O69) -> 19819.289 | I70: =NPV(0.03,I69:P69) -> 19242.028 | J70: =NPV(0.03,J69:Q69) -> 18681.581 | K70: =NPV(0.03,K69:R69) -> 18137.457 | L70: =NPV(0.03,L69:S69) -> 17609.182 | ... O70: =NPV(0.03,O69:V69) -> 16114.896
C73: Annual range | D73: =20*365 -> 7300 | E73: =20*365 -> 7300 | F73: =20*365 -> 7300 | G73: =20*365 -> 7300 | H73: =20*365 -> 7300 | I73: =20*365 -> 7300 | J73: =20*365 -> 7300 | K73: =20*365 -> 7300 | ... Z73: =20*365 -> 7300
C74: Oil amount | D74: =(D27/100)*D73 -> 386.9 | E74: =(E27/100)*E73 -> 386.9 | F74: =(F27/100)*F73 -> 386.9 | G74: =(G27/100)*G73 -> 386.9 | H74: =(H27/100)*H73 -> 386.9 | I74: =(I27/100)*I73 -> 386.9 | J74: =(J27/100)*J73 -> 386.9 | K74: =(K27/100)*K73 -> 386.9 | ... O74: =(O27/100)*O73 -> 386.9 | P74: =O74 -> 386.9 | Q74: =P74 -> 386.9 | R74: =Q74 -> 386.9 | S74: =R74 -> 386.9 | T74: =S74 -> 386.9 | U74: =T74 -> 386.9 | V74: =U74 -> 386.9 | W74: =V74 -> 386.9 | ... Z74: =Y74 -> 386.9
C75: Oil cost | D75: =D74*$D$28 -> 2708.3 | E75: =E74*$D$28 -> 2708.3 | F75: =F74*$D$28 -> 2708.3 | G75: =G74*$D$28 -> 2708.3 | H75: =H74*$D$28 -> 2708.3 | I75: =I74*$D$28 -> 2708.3 | J75: =J74*$D$28 -> 2708.3 | K75: =K74*$D$28 -> 2708.3 | ... Z75: =Z74*$D$28 -> 2708.3
D76: =D75/(1+$D$29)^(D57-2019) -> 2708.3 | E76: =E75/(1+$D$29)^(E57-2019) -> 2629.4175 | F76: =F75/(1+$D$29)^(F57-2019) -> 2552.8325 | G76: =G75/(1+$D$29)^(G57-2019) -> 2478.4782 | H76: =H75/(1+$D$29)^(H57-2019) -> 2406.2895 | I76: =I75/(1+$D$29)^(I57-2019) -> 2336.2034 | J76: =J75/(1+$D$29)^(J57-2019) -> 2268.1586 | K76: =K75/(1+$D$29)^(K57-2019) -> 2202.0957 | ... Z76: =Z75/(1+$D$29)^(Z57-2019) -> 1413.4415
D77: =SUM(D76:K76) -> 19581.775 | E77: =SUM(E76:L76) -> 19011.432 | F77: =SUM(F76:M76) -> 18457.701 | G77: =SUM(G76:N76) -> 17920.098 | H77: =SUM(H76:O76) -> 17398.154 | I77: =SUM(I76:P76) -> 16891.411 | J77: =SUM(J76:Q76) -> 16399.429 | K77: =SUM(K76:R76) -> 15921.775 | ... O77: =SUM(O76:V76) -> 14146.291

Sheet A00 TCO (30)
C4: A00 Class BEV Sample Avg
D5: 2019 | E5: 2020 | F5: 2021 | G5: 2022 | H5: 2023 | I5: 2024 | J5: 2025 | K5: 2026 | L5: 2027 | M5: 2028 | N5: 2029 | O5: 2030
C6: Retail Price | D6: 63475 | E6: 58403 | F6: 53818.2 | G6: 49671.88 | H6: 45920.192 | I6: 42523.673 | J6: 39446.806 | K6: 36657.625 | L6: 34127.362 | M6: 31830.126 | N6: 29742.614 | O6: 27843.852
C7: Purchase Tax | D7: 0 | E7: 0 | F7: =F6*0.1 -> 5381.82 | G7: =G6*0.1 -> 4967.188 | H7: =H6*0.1 -> 4592.0192 | I7: =I6*0.1 -> 4252.3673 | J7: =J6*0.1 -> 3944.6806 | K7: =K6*0.1 -> 3665.7625 | L7: =L6*0.1 -> 3412.7362 | M7: =M6*0.1 -> 3183.0126 | ... O7: =O6*0.1 -> 2784.3852
C8: Consumer Final Price | D8: =D6+D7 -> 63475 | E8: =E6+E7 -> 58403 | F8: =F6+F7 -> 59200.02 | G8: =G6+G7 -> 54639.068 | H8: =H6+H7 -> 50512.211 | I8: =I6+I7 -> 46776.04 | J8: =J6+J7 -> 43391.486 | K8: =K6+K7 -> 40323.387 | ... O8: =O6+O7 -> 30628.237
C9: Range/Day (km) | D9: 30 | E9: 30 | F9: 30 | G9: 30 | H9: 30 | I9: 30 | J9: 30 | K9: 30 | L9: 30 | M9: 30 | N9: 30 | O9: 30
C10: Years of Usage | D10: 8 | E10: 8 | F10: 8 | G10: 8 | H10: 8 | I10: 8 | J10: 8 | K10: 8 | L10: 8 | M10: 8 | N10: 8 | O10: 8
C11: Electricity/hundred KM (Kwh) | D11: 11.6 | E11: 11.6 | F11: 11.6 | G11: 11.6 | H11: 11.6 | I11: 11.6 | J11: 11.6 | K11: 11.6 | L11: 11.6 | M11: 11.6 | N11: 11.6 | O11: 11.6
C12: Electricity Price (RMB/Kwh) | D12: 0.8 | E12: 0.8 | F12: 0.8 | G12: 0.8 | H12: 0.8 | I12: 0.8 | J12: 0.8 | K12: 0.8 | L12: 0.8 | M12: 0.8 | N12: 0.8 | O12: 0.8
C13: Discount Rate | D13: 0.03 | E13: 0.03 | F13: 0.03 | G13: 0.03 | H13: 0.03 | I13: 0.03 | J13: 0.03 | K13: 0.03 | L13: 0.03 | M13: 0.03 | N13: 0.03 | O13: 0.03
C14: NPV Energy Cost | D14: 7347.1243 | E14: 7133.1304 | F14: 6925.3693 | G14: 6723.6595 | H14: 6527.8248 | I14: 6337.694 | J14: 6153.101 | K14: 5973.8844 | L14: 5799.8878 | M14: 5630.959 | N14: 5466.9505 | O14: 5307.7189
C15: NPV Maintenance Cost | D15: =4*100+4*300 -> 1600 | E15: =D15*(1-$D$13) -> 1552 | F15: =E15*(1-$D$13) -> 1505.44 | G15: =F15*(1-$D$13) -> 1460.2768 | H15: =G15*(1-$D$13) -> 1416.4685 | I15: =H15*(1-$D$13) -> 1373.9744 | J15: =I15*(1-$D$13) -> 1332.7552 | K15: =J15*(1-$D$13) -> 1292.7726 | L15: =K15*(1-$D$13) -> 1253.9894 | ... O15: =N15*(1-$D$13) -> 1144.4822
C16: NPV Insurance Cost | D16: 25305.99 | E16: 21657.072 | F16: 21026.284 | G16: 20413.868 | H16: 19819.289 | I16: 19242.028 | J16: 18681.581 | K16: 18137.457 | L16: 17609.182 | M16: 17096.293 | N16: 16598.343 | O16: 16114.896
C17: NPV Vehicle and Vessel Tax | D17: 0 | E17: 0 | F17: 0 | G17: 0 | H17: 0 | I17: 0 | J17: 0 | K17: 0 | L17: 0 | M17: 0 | N17: 0 | O17: 0
C18: Residual Value after Depreciation | D18: =0.15*D6 -> 9521.25 | E18: =0.15*E6 -> 8760.45 | F18: =0.15*F6 -> 8072.73 | G18: =0.15*G6 -> 7450.782 | H18: =0.15*H6 -> 6888.0288 | I18: =0.15*I6 -> 6378.5509 | J18: =0.15*J6 -> 5917.0208 | K18: =0.15*K6 -> 5498.6437 | ... O18: =0.15*O6 -> 4176.5778
C19: TCO | D19: =D8+D14+D15+D16+D17-D18 -> 88206.865 | E19: =E8+E14+E15+E16+E17-E18 -> 79984.753 | F19: =F8+F14+F15+F16+F17-F18 -> 80584.383 | G19: =G8+G14+G15+G16+G17-G18 -> 75786.09 | H19: =H8+H14+H15+H16+H17-H18 -> 71387.765 | I19: =I8+I14+I15+I16+I17-I18 -> 67351.186 | J19: =J8+J14+J15+J16+J17-J18 -> 63641.902 | K19: =K8+K14+K15+K16+K17-K18 -> 60228.858 | ... O19: =O8+O14+O15+O16+O17-O18 -> 49018.757
C20: A00 Class ICEV Sample Avg
D21: 2019 | E21: 2020 | F21: 2021 | G21: 2022 | H21: 2023 | I21: 2024 | J21: 2025 | K21: 2026 | L21: 2027 | M21: 2028 | N21: 2029 | O21: 2030
C22: Retail Price | D22: 51066 | E22: 51366 | F22: 51672 | G22: 51984.12 | H22: 52302.482 | I22: 52627.212 | J22: 52958.436 | K22: 53296.285 | L22: 53640.891 | M22: 53992.389 | N22: 54350.916 | O22: 54716.615
C23: Purchase Tax | D23: 5500 | E23: 5530 | F23: 5560.6 | G23: 5591.812 | H23: 5623.6482 | I23: 5656.1212 | J23: 5689.2436 | K23: 5723.0285 | L23: 5757.4891 | M23: 5792.6389 | N23: 5828.4916 | O23: 5865.0615
C24: Consumer Final Price | D24: 60500 | E24: 60830 | F24: 61166.6 | G24: 61509.932 | H24: 61860.131 | I24: 62217.333 | J24: 62581.68 | K24: 62953.314 | L24: 63332.38 | M24: 63719.027 | N24: 64113.408 | O24: 64515.676
C25: Range/Day (km) | D25: 30 | E25: =D25 -> 30 | F25: =E25 -> 30 | G25: =F25 -> 30 | H25: =G25 -> 30 | I25: =H25 -> 30 | J25: =I25 -> 30 | K25: =J25 -> 30 | L25: =K25 -> 30 | ... O25: =N25 -> 30
C26: Years of Usage | D26: 8 | E26: 8 | F26: 8 | G26: 8 | H26: 8 | I26: 8 | J26: 8 | K26: 8 | L26: 8 | M26: 8 | N26: 8 | O26: 8
C27: Oil/hundred KM (L/100km) | D27: 5.3 | E27: 5.3 | F27: 5.3 | G27: 5.3 | H27: 5.3 | I27: 5.3 | J27: 5.3 | K27: 5.3 | L27: 5.3 | M27: 5.3 | N27: 5.3 | O27: 5.3
C28: Oil Price (RMB/Litre) | D28: 7 | E28: 7 | F28: 7 | G28: 7 | H28: 7 | I28: 7 | J28: 7 | K28: 7 | L28: 7 | M28: 7 | N28: 7 | O28: 7
C29: Discount Rate | D29: 0.03 | E29: 0.03 | F29: 0.03 | G29: 0.03 | H29: 0.03 | I29: 0.03 | J29: 0.03 | K29: 0.03 | L29: 0.03 | M29: 0.03 | N29: 0.03 | O29: 0.03
C30: NPV Energy Cost | D30: 29372.663 | E30: 28517.149 | F30: 27686.552 | G30: 26880.148 | H30: 26097.231 | I30: 25337.117 | J30: 24599.143 | K30: 23882.663 | L30: 23187.051 | M30: 22511.7 | N30: 21856.02 | O30: 21219.437
C31: NPV Maintenance Cost | D31: =8*1200+9*600 -> 15000 | E31: =D31*(1-$D$29) -> 14550 | F31: =E31*(1-$D$29) -> 14113.5 | G31: =F31*(1-$D$29) -> 13690.095 | H31: =G31*(1-$D$29) -> 13279.392 | I31: =H31*(1-$D$29) -> 12881.01 | J31: =I31*(1-$D$29) -> 12494.58 | K31: =J31*(1-$D$29) -> 12119.743 | L31: =K31*(1-$D$29) -> 11756.15 | ... O31: =N31*(1-$D$29) -> 10729.521
C32: NPV Insurance Cost | D32: 21690.849 | E32: 21059.077 | F32: 20445.705 | G32: 19850.199 | H32: 19272.038 | I32: 18710.717 | J32: 18165.744 | K32: 17636.645 | L32: 17122.956 | M32: 16624.23 | N32: 16140.029 | O32: 15669.931
C33: NPV Vehicle and Vessel Tax | D33: 360 | E33: =D33*(1-$D$29) -> 349.2 | F33: =E33*(1-$D$29) -> 338.724 | G33: =F33*(1-$D$29) -> 328.56228 | H33: =G33*(1-$D$29) -> 318.70541 | I33: =H33*(1-$D$29) -> 309.14425 | J33: =I33*(1-$D$29) -> 299.86992 | K33: =J33*(1-$D$29) -> 290.87382 | L33: =K33*(1-$D$29) -> 282.14761 | ... O33: =N33*(1-$D$29) -> 257.50851
C34: Residual Value after Depreciation | D34: =0.35*D22 -> 17873.1 | E34: =0.35*E22 -> 17978.1 | F34: =0.35*F22 -> 18085.2 | G34: =0.35*G22 -> 18194.442 | H34: =0.35*H22 -> 18305.869 | I34: =0.35*I22 -> 18419.524 | J34: =0.35*J22 -> 18535.453 | K34: =0.35*K22 -> 18653.7 | ... O34: =0.35*O22 -> 19150.815
C35: TCO | D35: =D24+D30+D31+D32-D34 -> 108690.41 | E35: =E24+E30+E31+E32-E34 -> 106978.13 | F35: =F24+F30+F31+F32-F34 -> 105327.16 | G35: =G24+G30+G31+G32-G34 -> 103735.93 | H35: =H24+H30+H31+H32-H34 -> 102202.92 | I35: =I24+I30+I31+I32-I34 -> 100726.65 | J35: =J24+J30+J31+J32-J34 -> 99305.695 | K35: =K24+K30+K31+K32-K34 -> 97938.664 | ... O35: =O24+O30+O31+O32-O34 -> 92983.749
D37: 2019 | E37: 2020 | F37: 2021 | G37: 2022 | H37: 2023 | I37: 2024 | J37: 2025 | K37: 2026 | L37: 2027 | M37: 2028 | N37: 2029 | O37: 2030
C38: A00 (20km/day) | D38: =D19-D35 -> -20483.547 | E38: =E19-E35 -> -26993.372 | F38: =F19-F35 -> -24742.774 | G38: =G19-G35 -> -27949.842 | H38: =H19-H35 -> -30815.158 | I38: =I19-I35 -> -33375.467 | J38: =J19-J35 -> -35663.792 | K38: =K19-K35 -> -37709.807 | ... O38: =O19-O35 -> -43964.993
D57: 2019 | E57: 2020 | F57: 2021 | G57: 2022 | H57: 2023 | I57: 2024 | J57: 2025 | K57: 2026 | L57: 2027 | M57: 2028 | N57: 2029 | O57: 2030 | P57: 2031 | Q57: 2032 | R57: 2033 | S57: 2034 | T57: 2035 | U57: 2036 | V57: 2037 | W57: 2038 | X57: 2039 | Y57: 2040 | Z57: 2041
C58: Annual range | D58: =30*365 -> 10950 | E58: =30*365 -> 10950 | F58: =30*365 -> 10950 | G58: =30*365 -> 10950 | H58: =30*365 -> 10950 | I58: =30*365 -> 10950 | J58: =30*365 -> 10950 | K58: =30*365 -> 10950 | ... Z58: =30*365 -> 10950
C59: Electricity amount | D59: =(D11/100)*D58 -> 1270.2 | E59: =D59 -> 1270.2 | F59: =E59 -> 1270.2 | G59: =F59 -> 1270.2 | H59: =G59 -> 1270.2 | I59: =H59 -> 1270.2 | J59: =I59 -> 1270.2 | K59: =J59 -> 1270.2 | L59: =K59 -> 1270.2 | ... Z59: =Y59 -> 1270.2
C60: Electricity Cost | D60: =D59*D12 -> 1016.16 | E60: =D60 -> 1016.16 | F60: =E60 -> 1016.16 | G60: =F60 -> 1016.16 | H60: =G60 -> 1016.16 | I60: =H60 -> 1016.16 | J60: =I60 -> 1016.16 | K60: =J60 -> 1016.16 | L60: =K60 -> 1016.16 | ... Z60: =Y60 -> 1016.16
C61: Discounted Electricity Cost | D61: =D60/(1+$D$13)^(D57-2019) -> 1016.16 | E61: =E60/(1+$D$13)^(E57-2019) -> 986.56311 | F61: =F60/(1+$D$13)^(F57-2019) -> 957.82826 | G61: =G60/(1+$D$13)^(G57-2019) -> 929.93035 | H61: =H60/(1+$D$13)^(H57-2019) -> 902.845 | I61: =I60/(1+$D$13)^(I57-2019) -> 876.54854 | J61: =J60/(1+$D$13)^(J57-2019) -> 851.018 | K61: =K60/(1+$D$13)^(K57-2019) -> 826.23107 | ... Z61: =Z60/(1+$D$13)^(Z57-2019) -> 530.32628
C62: Electricity Cost NPV | D62: =SUM(D61:K61) -> 7347.1243 | E62: =SUM(E61:L61) -> 7133.1304 | F62: =SUM(F61:M61) -> 6925.3693 | G62: =SUM(G61:N61) -> 6723.6595 | H62: =SUM(H61:O61) -> 6527.8248 | I62: =SUM(I61:P61) -> 6337.694 | J62: =SUM(J61:Q61) -> 6153.101 | K62: =SUM(K61:R61) -> 5973.8844 | ... S62: =SUM(S61:Z61) -> 4715.8395 | T62: =SUM(T41:AA41) -> 0 | U62: =SUM(U41:AB41) -> 0 | V62: =SUM(V41:AC41) -> 0 | W62: =SUM(W41:AD41) -> 0 | X62: =SUM(X41:AE41) -> 0 | Y62: =SUM(Y41:AF41) -> 0 | Z62: =SUM(Z41:AG41) -> 0
C64: Maintenance Cost | D64: =400 -> 400
C68: Insurance cost | D68: 3500 | E68: 3500 | F68: 3500 | G68: 3500 | H68: 3500 | I68: 3500 | J68: 3500 | K68: 3500 | L68: 3500 | M68: 3500 | N68: 3500 | O68: 3500 | P68: 3500 | Q68: 3500 | R68: 3500 | S68: 3500 | T68: 3500 | U68: 3500 | V68: 3500 | W68: 3500 | X68: 3500 | Y68: 3500 | Z68: 3500
C69: Discounted Insurance Cost | D69: =D68/(1+$D$13)^(D57-2019) -> 3500 | E69: =E68/(1+$D$13)^(E57-2019) -> 3398.0583 | F69: =F68/(1+$D$13)^(F57-2019) -> 3299.0857 | G69: =G68/(1+$D$13)^(G57-2019) -> 3202.9958 | H69: =H68/(1+$D$13)^(H57-2019) -> 3109.7047 | I69: =I68/(1+$D$13)^(I57-2019) -> 3019.1307 | J69: =J68/(1+$D$13)^(J57-2019) -> 2931.1949 | K69: =K68/(1+$D$13)^(K57-2019) -> 2845.8203 | ... Z69: =Z68/(1+$D$13)^(Z57-2019) -> 1826.6238
C70: Insurance cost NPV | D70: =SUM(D69:K69) -> 25305.99 | E70: =NPV(0.03,E69:L69) -> 21657.072 | F70: =NPV(0.03,F69:M69) -> 21026.284 | G70: =NPV(0.03,G69:N69) -> 20413.868 | H70: =NPV(0.03,H69:O69) -> 19819.289 | I70: =NPV(0.03,I69:P69) -> 19242.028 | J70: =NPV(0.03,J69:Q69) -> 18681.581 | K70: =NPV(0.03,K69:R69) -> 18137.457 | L70: =NPV(0.03,L69:S69) -> 17609.182 | ... O70: =NPV(0.03,O69:V69) -> 16114.896
C73: Annual range | D73: =30*365 -> 10950 | E73: =30*365 -> 10950 | F73: =30*365 -> 10950 | G73: =30*365 -> 10950 | H73: =30*365 -> 10950 | I73: =30*365 -> 10950 | J73: =30*365 -> 10950 | K73: =30*365 -> 10950 | ... Z73: =30*365 -> 10950
C74: Oil amount | D74: =(D27/100)*D73 -> 580.35 | E74: =(E27/100)*E73 -> 580.35 | F74: =(F27/100)*F73 -> 580.35 | G74: =(G27/100)*G73 -> 580.35 | H74: =(H27/100)*H73 -> 580.35 | I74: =(I27/100)*I73 -> 580.35 | J74: =(J27/100)*J73 -> 580.35 | K74: =(K27/100)*K73 -> 580.35 | ... O74: =(O27/100)*O73 -> 580.35 | P74: =O74 -> 580.35 | Q74: =P74 -> 580.35 | R74: =Q74 -> 580.35 | S74: =R74 -> 580.35 | T74: =S74 -> 580.35 | U74: =T74 -> 580.35 | V74: =U74 -> 580.35 | W74: =V74 -> 580.35 | ... Z74: =Y74 -> 580.35
C75: Oil cost | D75: =D74*$D$28 -> 4062.45 | E75: =E74*$D$28 -> 4062.45 | F75: =F74*$D$28 -> 4062.45 | G75: =G74*$D$28 -> 4062.45 | H75: =H74*$D$28 -> 4062.45 | I75: =I74*$D$28 -> 4062.45 | J75: =J74*$D$28 -> 4062.45 | K75: =K74*$D$28 -> 4062.45 | ... Z75: =Z74*$D$28 -> 4062.45
D76: =D75/(1+$D$29)^(D57-2019) -> 4062.45 | E76: =E75/(1+$D$29)^(E57-2019) -> 3944.1262 | F76: =F75/(1+$D$29)^(F57-2019) -> 3829.2488 | G76: =G75/(1+$D$29)^(G57-2019) -> 3717.7172 | H76: =H75/(1+$D$29)^(H57-2019) -> 3609.4342 | I76: =I75/(1+$D$29)^(I57-2019) -> 3504.3051 | J76: =J75/(1+$D$29)^(J57-2019) -> 3402.2379 | K76: =K75/(1+$D$29)^(K57-2019) -> 3303.1436 | ... Z76: =Z75/(1+$D$29)^(Z57-2019) -> 2120.1622
D77: =SUM(D76:K76) -> 29372.663 | E77: =SUM(E76:L76) -> 28517.149 | F77: =SUM(F76:M76) -> 27686.552 | G77: =SUM(G76:N76) -> 26880.148 | H77: =SUM(H76:O76) -> 26097.231 | I77: =SUM(I76:P76) -> 25337.117 | J77: =SUM(J76:Q76) -> 24599.143 | K77: =SUM(K76:R76) -> 23882.663 | ... O77: =SUM(O76:V76) -> 21219.437

Sheet A00 TCO (40)
C4: A00 Class BEV Sample Avg
D5: 2019 | E5: 2020 | F5: 2021 | G5: 2022 | H5: 2023 | I5: 2024 | J5: 2025 | K5: 2026 | L5: 2027 | M5: 2028 | N5: 2029 | O5: 2030
C6: Retail Price | D6: 63475 | E6: 58403 | F6: 53818.2 | G6: 49671.88 | H6: 45920.192 | I6: 42523.673 | J6: 39446.806 | K6: 36657.625 | L6: 34127.362 | M6: 31830.126 | N6: 29742.614 | O6: 27843.852
C7: Purchase Tax | D7: 0 | E7: 0 | F7: =F6*0.1 -> 5381.82 | G7: =G6*0.1 -> 4967.188 | H7: =H6*0.1 -> 4592.0192 | I7: =I6*0.1 -> 4252.3673 | J7: =J6*0.1 -> 3944.6806 | K7: =K6*0.1 -> 3665.7625 | L7: =L6*0.1 -> 3412.7362 | M7: =M6*0.1 -> 3183.0126 | ... O7: =O6*0.1 -> 2784.3852
C8: Consumer Final Price | D8: =D6+D7 -> 63475 | E8: =E6+E7 -> 58403 | F8: =F6+F7 -> 59200.02 | G8: =G6+G7 -> 54639.068 | H8: =H6+H7 -> 50512.211 | I8: =I6+I7 -> 46776.04 | J8: =J6+J7 -> 43391.486 | K8: =K6+K7 -> 40323.387 | ... O8: =O6+O7 -> 30628.237
C9: Range/Day (km) | D9: 40 | E9: 40 | F9: 40 | G9: 40 | H9: 40 | I9: 40 | J9: 40 | K9: 40 | L9: 40 | M9: 40 | N9: 40 | O9: 40
C10: Years of Usage | D10: 8 | E10: 8 | F10: 8 | G10: 8 | H10: 8 | I10: 8 | J10: 8 | K10: 8 | L10: 8 | M10: 8 | N10: 8 | O10: 8
C11: Electricity/hundred KM (Kwh) | D11: 11.6 | E11: 11.6 | F11: 11.6 | G11: 11.6 | H11: 11.6 | I11: 11.6 | J11: 11.6 | K11: 11.6 | L11: 11.6 | M11: 11.6 | N11: 11.6 | O11: 11.6
C12: Electricity Price (RMB/Kwh) | D12: 0.8 | E12: 0.8 | F12: 0.8 | G12: 0.8 | H12: 0.8 | I12: 0.8 | J12: 0.8 | K12: 0.8 | L12: 0.8 | M12: 0.8 | N12: 0.8 | O12: 0.8
C13: Discount Rate | D13: 0.03 | E13: 0.03 | F13: 0.03 | G13: 0.03 | H13: 0.03 | I13: 0.03 | J13: 0.03 | K13: 0.03 | L13: 0.03 | M13: 0.03 | N13: 0.03 | O13: 0.03
C14: NPV Energy Cost | D14: 9796.1658 | E14: 9510.8406 | F14: 9233.8258 | G14: 8964.8794 | H14: 8703.7664 | I14: 8450.2586 | J14: 8204.1346 | K14: 7965.1792 | L14: 7733.1837 | M14: 7507.9454 | N14: 7289.2673 | O14: 7076.9586
C15: NPV Maintenance Cost | D15: =6*100+5*300 -> 2100 | E15: =D15*(1-$D$13) -> 2037 | F15: =E15*(1-$D$13) -> 1975.89 | G15: =F15*(1-$D$13) -> 1916.6133 | H15: =G15*(1-$D$13) -> 1859.1149 | I15: =H15*(1-$D$13) -> 1803.3415 | J15: =I15*(1-$D$13) -> 1749.2412 | K15: =J15*(1-$D$13) -> 1696.764 | L15: =K15*(1-$D$13) -> 1645.8611 | ... O15: =N15*(1-$D$13) -> 1502.1329
C16: NPV Insurance Cost | D16: 25305.99 | E16: 21657.072 | F16: 21026.284 | G16: 20413.868 | H16: 19819.289 | I16: 19242.028 | J16: 18681.581 | K16: 18137.457 | L16: 17609.182 | M16: 17096.293 | N16: 16598.343 | O16: 16114.896
C17: NPV Vehicle and Vessel Tax | D17: 0 | E17: 0 | F17: 0 | G17: 0 | H17: 0 | I17: 0 | J17: 0 | K17: 0 | L17: 0 | M17: 0 | N17: 0 | O17: 0
C18: Residual Value after Depreciation | D18: =0.15*D6 -> 9521.25 | E18: =0.15*E6 -> 8760.45 | F18: =0.15*F6 -> 8072.73 | G18: =0.15*G6 -> 7450.782 | H18: =0.15*H6 -> 6888.0288 | I18: =0.15*I6 -> 6378.5509 | J18: =0.15*J6 -> 5917.0208 | K18: =0.15*K6 -> 5498.6437 | ... O18: =0.15*O6 -> 4176.5778
C19: TCO | D19: =D8+D14+D15+D16+D17-D18 -> 91155.906 | E19: =E8+E14+E15+E16+E17-E18 -> 82847.463 | F19: =F8+F14+F15+F16+F17-F18 -> 83363.29 | G19: =G8+G14+G15+G16+G17-G18 -> 78483.647 | H19: =H8+H14+H15+H16+H17-H18 -> 74006.353 | I19: =I8+I14+I15+I16+I17-I18 -> 69893.118 | J19: =J8+J14+J15+J16+J17-J18 -> 66109.422 | K19: =K8+K14+K15+K16+K17-K18 -> 62624.144 | ... O19: =O8+O14+O15+O16+O17-O18 -> 51145.647
C20: A00 Class ICEV Sample Avg
D21: 2019 | E21: 2020 | F21: 2021 | G21: 2022 | H21: 2023 | I21: 2024 | J21: 2025 | K21: 2026 | L21: 2027 | M21: 2028 | N21: 2029 | O21: 2030
C22: Retail Price | D22: 51066 | E22: 51366 | F22: 51672 | G22: 51984.12 | H22: 52302.482 | I22: 52627.212 | J22: 52958.436 | K22: 53296.285 | L22: 53640.891 | M22: 53992.389 | N22: 54350.916 | O22: 54716.615
C23: Purchase Tax | D23: 5500 | E23: 5530 | F23: 5560.6 | G23: 5591.812 | H23: 5623.6482 | I23: 5656.1212 | J23: 5689.2436 | K23: 5723.0285 | L23: 5757.4891 | M23: 5792.6389 | N23: 5828.4916 | O23: 5865.0615
C24: Consumer Final Price | D24: 60500 | E24: 60830 | F24: 61166.6 | G24: 61509.932 | H24: 61860.131 | I24: 62217.333 | J24: 62581.68 | K24: 62953.314 | L24: 63332.38 | M24: 63719.027 | N24: 64113.408 | O24: 64515.676
C25: Range/Day (km) | D25: 40 | E25: =D25 -> 40 | F25: =E25 -> 40 | G25: =F25 -> 40 | H25: =G25 -> 40 | I25: =H25 -> 40 | J25: =I25 -> 40 | K25: =J25 -> 40 | L25: =K25 -> 40 | ... O25: =N25 -> 40
C26: Years of Usage | D26: 8 | E26: 8 | F26: 8 | G26: 8 | H26: 8 | I26: 8 | J26: 8 | K26: 8 | L26: 8 | M26: 8 | N26: 8 | O26: 8
C27: Oil/hundred KM (L/100km) | D27: 5.3 | E27: 5.3 | F27: 5.3 | G27: 5.3 | H27: 5.3 | I27: 5.3 | J27: 5.3 | K27: 5.3 | L27: 5.3 | M27: 5.3 | N27: 5.3 | O27: 5.3
C28: Oil Price (RMB/Litre) | D28: 7 | E28: 7 | F28: 7 | G28: 7 | H28: 7 | I28: 7 | J28: 7 | K28: 7 | L28: 7 | M28: 7 | N28: 7 | O28: 7
C29: Discount Rate | D29: 0.03 | E29: 0.03 | F29: 0.03 | G29: 0.03 | H29: 0.03 | I29: 0.03 | J29: 0.03 | K29: 0.03 | L29: 0.03 | M29: 0.03 | N29: 0.03 | O29: 0.03
C30: NPV Energy Cost | D30: 39163.551 | E30: 38022.865 | F30: 36915.403 | G30: 35840.197 | H30: 34796.308 | I30: 33782.823 | J30: 32798.857 | K30: 31843.551 | L30: 30916.069 | M30: 30015.601 | N30: 29141.36 | O30: 28292.582
C31: NPV Maintenance Cost | D31: =11*1200+12*600 -> 20400 | E31: =D31*(1-$D$29) -> 19788 | F31: =E31*(1-$D$29) -> 19194.36 | G31: =F31*(1-$D$29) -> 18618.529 | H31: =G31*(1-$D$29) -> 18059.973 | I31: =H31*(1-$D$29) -> 17518.174 | J31: =I31*(1-$D$29) -> 16992.629 | K31: =J31*(1-$D$29) -> 16482.85 | L31: =K31*(1-$D$29) -> 15988.365 | ... O31: =N31*(1-$D$29) -> 14592.149
C32: NPV Insurance Cost | D32: 21690.849 | E32: 21059.077 | F32: 20445.705 | G32: 19850.199 | H32: 19272.038 | I32: 18710.717 | J32: 18165.744 | K32: 17636.645 | L32: 17122.956 | M32: 16624.23 | N32: 16140.029 | O32: 15669.931
C33: NPV Vehicle and Vessel Tax | D33: 360 | E33: =D33*(1-$D$29) -> 349.2 | F33: =E33*(1-$D$29) -> 338.724 | G33: =F33*(1-$D$29) -> 328.56228 | H33: =G33*(1-$D$29) -> 318.70541 | I33: =H33*(1-$D$29) -> 309.14425 | J33: =I33*(1-$D$29) -> 299.86992 | K33: =J33*(1-$D$29) -> 290.87382 | L33: =K33*(1-$D$29) -> 282.14761 | ... O33: =N33*(1-$D$29) -> 257.50851
C34: Residual Value after Depreciation | D34: =0.35*D22 -> 17873.1 | E34: =0.35*E22 -> 17978.1 | F34: =0.35*F22 -> 18085.2 | G34: =0.35*G22 -> 18194.442 | H34: =0.35*H22 -> 18305.869 | I34: =0.35*I22 -> 18419.524 | J34: =0.35*J22 -> 18535.453 | K34: =0.35*K22 -> 18653.7 | ... O34: =0.35*O22 -> 19150.815
C35: TCO | D35: =D24+D30+D31+D32-D34 -> 123881.3 | E35: =E24+E30+E31+E32-E34 -> 121721.84 | F35: =F24+F30+F31+F32-F34 -> 119636.87 | G35: =G24+G30+G31+G32-G34 -> 117624.42 | H35: =H24+H30+H31+H32-H34 -> 115682.58 | I35: =I24+I30+I31+I32-I34 -> 113809.52 | J35: =J24+J30+J31+J32-J34 -> 112003.46 | K35: =K24+K30+K31+K32-K34 -> 110262.66 | ... O35: =O24+O30+O31+O32-O34 -> 103919.52
D36: 2019 | E36: 2020 | F36: 2021 | G36: 2022 | H36: 2023 | I36: 2024 | J36: 2025 | K36: 2026 | L36: 2027 | M36: 2028 | N36: 2029 | O36: 2030
C37: A00 (40km/day) | D37: =D19-D35 -> -32725.393 | E37: =E19-E35 -> -38874.378 | F37: =F19-F35 -> -36273.578 | G37: =G19-G35 -> -39140.769 | H37: =H19-H35 -> -41676.228 | I37: =I19-I35 -> -43916.405 | J37: =J19-J35 -> -45894.036 | K37: =K19-K35 -> -47638.515 | ... O37: =O19-O35 -> -52773.876
D58: 2019 | E58: 2020 | F58: 2021 | G58: 2022 | H58: 2023 | I58: 2024 | J58: 2025 | K58: 2026 | L58: 2027 | M58: 2028 | N58: 2029 | O58: 2030 | P58: 2031 | Q58: 2032 | R58: 2033 | S58: 2034 | T58: 2035 | U58: 2036 | V58: 2037 | W58: 2038 | X58: 2039 | Y58: 2040 | Z58: 2041
C59: Annual range | D59: =40*365 -> 14600 | E59: =40*365 -> 14600 | F59: =40*365 -> 14600 | G59: =40*365 -> 14600 | H59: =40*365 -> 14600 | I59: =40*365 -> 14600 | J59: =40*365 -> 14600 | K59: =40*365 -> 14600 | ... Z59: =40*365 -> 14600
C60: Electricity amount | D60: =(D11/100)*D59 -> 1693.6 | E60: =D60 -> 1693.6 | F60: =E60 -> 1693.6 | G60: =F60 -> 1693.6 | H60: =G60 -> 1693.6 | I60: =H60 -> 1693.6 | J60: =I60 -> 1693.6 | K60: =J60 -> 1693.6 | L60: =K60 -> 1693.6 | ... Z60: =Y60 -> 1693.6
C61: Electricity Cost | D61: =D60*D12 -> 1354.88 | E61: =D61 -> 1354.88 | F61: =E61 -> 1354.88 | G61: =F61 -> 1354.88 | H61: =G61 -> 1354.88 | I61: =H61 -> 1354.88 | J61: =I61 -> 1354.88 | K61: =J61 -> 1354.88 | L61: =K61 -> 1354.88 | ... Z61: =Y61 -> 1354.88
C62: Discounted Electricity Cost | D62: =D61/(1+$D$13)^(D58-2019) -> 1354.88 | E62: =E61/(1+$D$13)^(E58-2019) -> 1315.4175 | F62: =F61/(1+$D$13)^(F58-2019) -> 1277.1043 | G62: =G61/(1+$D$13)^(G58-2019) -> 1239.9071 | H62: =H61/(1+$D$13)^(H58-2019) -> 1203.7933 | I62: =I61/(1+$D$13)^(I58-2019) -> 1168.7314 | J62: =J61/(1+$D$13)^(J58-2019) -> 1134.6907 | K62: =K61/(1+$D$13)^(K58-2019) -> 1101.6414 | ... Z62: =Z61/(1+$D$13)^(Z58-2019) -> 707.10171
C63: Electricity Cost NPV | D63: =SUM(D62:K62) -> 9796.1658 | E63: =SUM(E62:L62) -> 9510.8406 | F63: =SUM(F62:M62) -> 9233.8258 | G63: =SUM(G62:N62) -> 8964.8794 | H63: =SUM(H62:O62) -> 8703.7664 | I63: =SUM(I62:P62) -> 8450.2586 | J63: =SUM(J62:Q62) -> 8204.1346 | K63: =SUM(K62:R62) -> 7965.1792 | ... S63: =SUM(S62:Z62) -> 6287.786 | T63: =SUM(T41:AA41) -> 0 | U63: =SUM(U41:AB41) -> 0 | V63: =SUM(V41:AC41) -> 0 | W63: =SUM(W41:AD41) -> 0 | X63: =SUM(X41:AE41) -> 0 | Y63: =SUM(Y41:AF41) -> 0 | Z63: =SUM(Z41:AG41) -> 0
C65: Maintenance Cost | D65: =400 -> 400
C69: Insurance cost | D69: 3500 | E69: 3500 | F69: 3500 | G69: 3500 | H69: 3500 | I69: 3500 | J69: 3500 | K69: 3500 | L69: 3500 | M69: 3500 | N69: 3500 | O69: 3500 | P69: 3500 | Q69: 3500 | R69: 3500 | S69: 3500 | T69: 3500 | U69: 3500 | V69: 3500 | W69: 3500 | X69: 3500 | Y69: 3500 | Z69: 3500
C70: Discounted Insurance Cost | D70: =D69/(1+$D$13)^(D58-2019) -> 3500 | E70: =E69/(1+$D$13)^(E58-2019) -> 3398.0583 | F70: =F69/(1+$D$13)^(F58-2019) -> 3299.0857 | G70: =G69/(1+$D$13)^(G58-2019) -> 3202.9958 | H70: =H69/(1+$D$13)^(H58-2019) -> 3109.7047 | I70: =I69/(1+$D$13)^(I58-2019) -> 3019.1307 | J70: =J69/(1+$D$13)^(J58-2019) -> 2931.1949 | K70: =K69/(1+$D$13)^(K58-2019) -> 2845.8203 | ... Z70: =Z69/(1+$D$13)^(Z58-2019) -> 1826.6238
C71: Insurance cost NPV | D71: =SUM(D70:K70) -> 25305.99 | E71: =NPV(0.03,E70:L70) -> 21657.072 | F71: =NPV(0.03,F70:M70) -> 21026.284 | G71: =NPV(0.03,G70:N70) -> 20413.868 | H71: =NPV(0.03,H70:O70) -> 19819.289 | I71: =NPV(0.03,I70:P70) -> 19242.028 | J71: =NPV(0.03,J70:Q70) -> 18681.581 | K71: =NPV(0.03,K70:R70) -> 18137.457 | L71: =NPV(0.03,L70:S70) -> 17609.182 | ... O71: =NPV(0.03,O70:V70) -> 16114.896
C74: Annual range | D74: =40*365 -> 14600 | E74: =40*365 -> 14600 | F74: =40*365 -> 14600 | G74: =40*365 -> 14600 | H74: =40*365 -> 14600 | I74: =40*365 -> 14600 | J74: =40*365 -> 14600 | K74: =40*365 -> 14600 | ... Z74: =40*365 -> 14600
C75: Oil amount | D75: =(D27/100)*D74 -> 773.8 | E75: =(E27/100)*E74 -> 773.8 | F75: =(F27/100)*F74 -> 773.8 | G75: =(G27/100)*G74 -> 773.8 | H75: =(H27/100)*H74 -> 773.8 | I75: =(I27/100)*I74 -> 773.8 | J75: =(J27/100)*J74 -> 773.8 | K75: =(K27/100)*K74 -> 773.8 | ... O75: =(O27/100)*O74 -> 773.8 | P75: =O75 -> 773.8 | Q75: =P75 -> 773.8 | R75: =Q75 -> 773.8 | S75: =R75 -> 773.8 | T75: =S75 -> 773.8 | U75: =T75 -> 773.8 | V75: =U75 -> 773.8 | W75: =V75 -> 773.8 | ... Z75: =Y75 -> 773.8
C76: Oil cost | D76: =D75*$D$28 -> 5416.6 | E76: =E75*$D$28 -> 5416.6 | F76: =F75*$D$28 -> 5416.6 | G76: =G75*$D$28 -> 5416.6 | H76: =H75*$D$28 -> 5416.6 | I76: =I75*$D$28 -> 5416.6 | J76: =J75*$D$28 -> 5416.6 | K76: =K75*$D$28 -> 5416.6 | ... Z76: =Z75*$D$28 -> 5416.6
D77: =D76/(1+$D$29)^(D58-2019) -> 5416.6 | E77: =E76/(1+$D$29)^(E58-2019) -> 5258.835 | F77: =F76/(1+$D$29)^(F58-2019) -> 5105.665 | G77: =G76/(1+$D$29)^(G58-2019) -> 4956.9563 | H77: =H76/(1+$D$29)^(H58-2019) -> 4812.5789 | I77: =I76/(1+$D$29)^(I58-2019) -> 4672.4067 | J77: =J76/(1+$D$29)^(J58-2019) -> 4536.3172 | K77: =K76/(1+$D$29)^(K58-2019) -> 4404.1915 | ... Z77: =Z76/(1+$D$29)^(Z58-2019) -> 2826.8829
D78: =SUM(D77:K77) -> 39163.551 | E78: =SUM(E77:L77) -> 38022.865 | F78: =SUM(F77:M77) -> 36915.403 | G78: =SUM(G77:N77) -> 35840.197 | H78: =SUM(H77:O77) -> 34796.308 | I78: =SUM(I77:P77) -> 33782.823 | J78: =SUM(J77:Q77) -> 32798.857 | K78: =SUM(K77:R77) -> 31843.551 | ... O78: =SUM(O77:V77) -> 28292.582

Sheet A00 TCO (60)
C4: A00 Class BEV Sample Avg
D5: 2019 | E5: 2020 | F5: 2021 | G5: 2022 | H5: 2023 | I5: 2024 | J5: 2025 | K5: 2026 | L5: 2027 | M5: 2028 | N5: 2029 | O5: 2030
C6: Retail Price | D6: 63475 | E6: 58403 | F6: 53818.2 | G6: 49671.88 | H6: 45920.192 | I6: 42523.673 | J6: 39446.806 | K6: 36657.625 | L6: 34127.362 | M6: 31830.126 | N6: 29742.614 | O6: 27843.852
C7: Purchase Tax | D7: 0 | E7: 0 | F7: =F6*0.1 -> 5381.82 | G7: =G6*0.1 -> 4967.188 | H7: =H6*0.1 -> 4592.0192 | I7: =I6*0.1 -> 4252.3673 | J7: =J6*0.1 -> 3944.6806 | K7: =K6*0.1 -> 3665.7625 | L7: =L6*0.1 -> 3412.7362 | M7: =M6*0.1 -> 3183.0126 | ... O7: =O6*0.1 -> 2784.3852
C8: Consumer Final Price | D8: =D6+D7 -> 63475 | E8: =E6+E7 -> 58403 | F8: =F6+F7 -> 59200.02 | G8: =G6+G7 -> 54639.068 | H8: =H6+H7 -> 50512.211 | I8: =I6+I7 -> 46776.04 | J8: =J6+J7 -> 43391.486 | K8: =K6+K7 -> 40323.387 | ... O8: =O6+O7 -> 30628.237
C9: Range/Day (km) | D9: 60 | E9: 60 | F9: 60 | G9: 60 | H9: 60 | I9: 60 | J9: 60 | K9: 60 | L9: 60 | M9: 60 | N9: 60 | O9: 60
C10: Years of Usage | D10: 8 | E10: 8 | F10: 8 | G10: 8 | H10: 8 | I10: 8 | J10: 8 | K10: 8 | L10: 8 | M10: 8 | N10: 8 | O10: 8
C11: Electricity/hundred KM (Kwh) | D11: 11.6 | E11: 11.6 | F11: 11.6 | G11: 11.6 | H11: 11.6 | I11: 11.6 | J11: 11.6 | K11: 11.6 | L11: 11.6 | M11: 11.6 | N11: 11.6 | O11: 11.6
C12: Electricity Price (RMB/Kwh) | D12: 0.8 | E12: 0.8 | F12: 0.8 | G12: 0.8 | H12: 0.8 | I12: 0.8 | J12: 0.8 | K12: 0.8 | L12: 0.8 | M12: 0.8 | N12: 0.8 | O12: 0.8
C13: Discount Rate | D13: 0.03 | E13: 0.03 | F13: 0.03 | G13: 0.03 | H13: 0.03 | I13: 0.03 | J13: 0.03 | K13: 0.03 | L13: 0.03 | M13: 0.03 | N13: 0.03 | O13: 0.03
C14: NPV Energy Cost | D14: 14694.249 | E14: 14266.261 | F14: 13850.739 | G14: 13447.319 | H14: 13055.65 | I14: 12675.388 | J14: 12306.202 | K14: 11947.769 | L14: 11599.776 | M14: 11261.918 | N14: 10933.901 | O14: 10615.438
C15: NPV Maintenance Cost | D15: 3300 | E15: =D15*(1-$D$13) -> 3201 | F15: =E15*(1-$D$13) -> 3104.97 | G15: =F15*(1-$D$13) -> 3011.8209 | H15: =G15*(1-$D$13) -> 2921.4663 | I15: =H15*(1-$D$13) -> 2833.8223 | J15: =I15*(1-$D$13) -> 2748.8076 | K15: =J15*(1-$D$13) -> 2666.3434 | L15: =K15*(1-$D$13) -> 2586.3531 | ... O15: =N15*(1-$D$13) -> 2360.4946
C16: NPV Insurance Cost | D16: 25305.99 | E16: 21657.072 | F16: 21026.284 | G16: 20413.868 | H16: 19819.289 | I16: 19242.028 | J16: 18681.581 | K16: 18137.457 | L16: 17609.182 | M16: 17096.293 | N16: 16598.343 | O16: 16114.896
C17: NPV Vehicle and Vessel Tax | D17: 0 | E17: 0 | F17: 0 | G17: 0 | H17: 0 | I17: 0 | J17: 0 | K17: 0 | L17: 0 | M17: 0 | N17: 0 | O17: 0
C18: Residual Value after Depreciation | D18: =0.15*D6 -> 9521.25 | E18: =0.15*E6 -> 8760.45 | F18: =0.15*F6 -> 8072.73 | G18: =0.15*G6 -> 7450.782 | H18: =0.15*H6 -> 6888.0288 | I18: =0.15*I6 -> 6378.5509 | J18: =0.15*J6 -> 5917.0208 | K18: =0.15*K6 -> 5498.6437 | ... O18: =0.15*O6 -> 4176.5778
C19: TCO | D19: =D8+D14+D15+D16+D17-D18 -> 97253.989 | E19: =E8+E14+E15+E16+E17-E18 -> 88766.883 | F19: =F8+F14+F15+F16+F17-F18 -> 89109.283 | G19: =G8+G14+G15+G16+G17-G18 -> 84061.294 | H19: =H8+H14+H15+H16+H17-H18 -> 79420.588 | I19: =I8+I14+I15+I16+I17-I18 -> 75148.728 | J19: =J8+J14+J15+J16+J17-J18 -> 71211.056 | K19: =K8+K14+K15+K16+K17-K18 -> 67576.313 | ... O19: =O8+O14+O15+O16+O17-O18 -> 55542.488
C20: A00 Class ICEV Sample Avg
D21: 2019 | E21: 2020 | F21: 2021 | G21: 2022 | H21: 2023 | I21: 2024 | J21: 2025 | K21: 2026 | L21: 2027 | M21: 2028 | N21: 2029 | O21: 2030
C22: Retail Price | D22: 51066 | E22: 51366 | F22: 51672 | G22: 51984.12 | H22: 52302.482 | I22: 52627.212 | J22: 52958.436 | K22: 53296.285 | L22: 53640.891 | M22: 53992.389 | N22: 54350.916 | O22: 54716.615
C23: Purchase Tax | D23: 5500 | E23: 5530 | F23: 5560.6 | G23: 5591.812 | H23: 5623.6482 | I23: 5656.1212 | J23: 5689.2436 | K23: 5723.0285 | L23: 5757.4891 | M23: 5792.6389 | N23: 5828.4916 | O23: 5865.0615
C24: Consumer Final Price | D24: 60500 | E24: 60830 | F24: 61166.6 | G24: 61509.932 | H24: 61860.131 | I24: 62217.333 | J24: 62581.68 | K24: 62953.314 | L24: 63332.38 | M24: 63719.027 | N24: 64113.408 | O24: 64515.676
C25: Range/Day (km) | D25: 60 | E25: =D25 -> 60 | F25: =E25 -> 60 | G25: =F25 -> 60 | H25: =G25 -> 60 | I25: =H25 -> 60 | J25: =I25 -> 60 | K25: =J25 -> 60 | L25: =K25 -> 60 | ... O25: =N25 -> 60
C26: Years of Usage | D26: 8 | E26: 8 | F26: 8 | G26: 8 | H26: 8 | I26: 8 | J26: 8 | K26: 8 | L26: 8 | M26: 8 | N26: 8 | O26: 8
C27: Oil/hundred KM (L/100km) | D27: 5.3 | E27: 5.3 | F27: 5.3 | G27: 5.3 | H27: 5.3 | I27: 5.3 | J27: 5.3 | K27: 5.3 | L27: 5.3 | M27: 5.3 | N27: 5.3 | O27: 5.3
C28: Oil Price (RMB/Litre) | D28: 7 | E28: 7 | F28: 7 | G28: 7 | H28: 7 | I28: 7 | J28: 7 | K28: 7 | L28: 7 | M28: 7 | N28: 7 | O28: 7
C29: Discount Rate | D29: 0.03 | E29: 0.03 | F29: 0.03 | G29: 0.03 | H29: 0.03 | I29: 0.03 | J29: 0.03 | K29: 0.03 | L29: 0.03 | M29: 0.03 | N29: 0.03 | O29: 0.03
C30: NPV Energy Cost | D30: 58745.326 | E30: 57034.297 | F30: 55373.104 | G30: 53760.295 | H30: 52194.461 | I30: 50674.234 | J30: 49198.286 | K30: 47765.326 | L30: 46374.103 | M30: 45023.401 | N30: 43712.04 | O30: 42438.873
C31: NPV Maintenance Cost | D31: =17*1200+18*600 -> 31200 | E31: =D31*(1-$D$29) -> 30264 | F31: =E31*(1-$D$29) -> 29356.08 | G31: =F31*(1-$D$29) -> 28475.398 | H31: =G31*(1-$D$29) -> 27621.136 | I31: =H31*(1-$D$29) -> 26792.502 | J31: =I31*(1-$D$29) -> 25988.727 | K31: =J31*(1-$D$29) -> 25209.065 | L31: =K31*(1-$D$29) -> 24452.793 | ... O31: =N31*(1-$D$29) -> 22317.404
C32: NPV Insurance Cost | D32: 21690.849 | E32: 21059.077 | F32: 20445.705 | G32: 19850.199 | H32: 19272.038 | I32: 18710.717 | J32: 18165.744 | K32: 17636.645 | L32: 17122.956 | M32: 16624.23 | N32: 16140.029 | O32: 15669.931
C33: NPV Vehicle and Vessel Tax | D33: 360 | E33: =D33*(1-$D$29) -> 349.2 | F33: =E33*(1-$D$29) -> 338.724 | G33: =F33*(1-$D$29) -> 328.56228 | H33: =G33*(1-$D$29) -> 318.70541 | I33: =H33*(1-$D$29) -> 309.14425 | J33: =I33*(1-$D$29) -> 299.86992 | K33: =J33*(1-$D$29) -> 290.87382 | L33: =K33*(1-$D$29) -> 282.14761 | ... O33: =N33*(1-$D$29) -> 257.50851
C34: Residual Value after Depreciation | D34: =0.35*D22 -> 17873.1 | E34: =0.35*E22 -> 17978.1 | F34: =0.35*F22 -> 18085.2 | G34: =0.35*G22 -> 18194.442 | H34: =0.35*H22 -> 18305.869 | I34: =0.35*I22 -> 18419.524 | J34: =0.35*J22 -> 18535.453 | K34: =0.35*K22 -> 18653.7 | ... O34: =0.35*O22 -> 19150.815
C35: TCO | D35: =D24+D30+D31+D32-D34 -> 154263.07 | E35: =E24+E30+E31+E32-E34 -> 151209.27 | F35: =F24+F30+F31+F32-F34 -> 148256.29 | G35: =G24+G30+G31+G32-G34 -> 145401.38 | H35: =H24+H30+H31+H32-H34 -> 142641.9 | I35: =I24+I30+I31+I32-I34 -> 139975.26 | J35: =J24+J30+J31+J32-J34 -> 137398.98 | K35: =K24+K30+K31+K32-K34 -> 134910.65 | ... O35: =O24+O30+O31+O32-O34 -> 125791.07
D36: 2019 | E36: 2020 | F36: 2021 | G36: 2022 | H36: 2023 | I36: 2024 | J36: 2025 | K36: 2026 | L36: 2027 | M36: 2028 | N36: 2029 | O36: 2030
C37: A00 (60km/day) | D37: =D19-D35 -> -57009.086 | E37: =E19-E35 -> -62442.39 | F37: =F19-F35 -> -59147.007 | G37: =G19-G35 -> -61340.088 | H37: =H19-H35 -> -63221.309 | I37: =I19-I35 -> -64826.534 | J37: =J19-J35 -> -66187.928 | K37: =K19-K35 -> -67334.336 | ... O37: =O19-O35 -> -70248.581
D41: 2019 | E41: 2020 | F41: 2021 | G41: 2022 | H41: 2023 | I41: 2024 | J41: 2025 | K41: 2026 | L41: 2027 | M41: 2028 | N41: 2029 | O41: 2030
C42: A00 (10km/day) | D42: 3700.1453 | E42: -3522.3602 | F42: -1963.4357 | G42: -5841.7896 | H42: -9358.6057 | I42: -12551.212 | J42: -15453.197 | K42: -18094.784 | L42: -20503.169 | M42: -22702.823 | N42: -24715.767 | O42: -26561.818
C43: A00 (20km/day) | D43: -8441.701 | E43: -15306.366 | F43: -13400.15 | G43: -16941.449 | H43: -20131.146 | I43: -23006.276 | J43: -25600.143 | K43: -27942.694 | L43: -30060.858 | M43: -31978.846 | N43: -33718.426 | O43: -35299.17
C44: A00 (40km/day) | D44: -32725.393 | E44: -38874.378 | F44: -36273.578 | G44: -39140.769 | H44: -41676.228 | I44: -43916.405 | J44: -45894.036 | K44: -47638.515 | L44: -49176.237 | M44: -50530.892 | N44: -51723.744 | O44: -52773.876
C45: A00 (60km/day) | D45: -57009.086 | E45: -62442.39 | F45: -59147.007 | G45: -61340.088 | H45: -63221.309 | I45: -64826.534 | J45: -66187.928 | K45: -67334.336 | L45: -68291.615 | M45: -69082.937 | N45: -69729.062 | O45: -70248.581
D67: 2019 | E67: 2020 | F67: 2021 | G67: 2022 | H67: 2023 | I67: 2024 | J67: 2025 | K67: 2026 | L67: 2027 | M67: 2028 | N67: 2029 | O67: 2030 | P67: 2031 | Q67: 2032 | R67: 2033 | S67: 2034 | T67: 2035 | U67: 2036 | V67: 2037 | W67: 2038 | X67: 2039 | Y67: 2040 | Z67: 2041
C68: Annual range | D68: =60*365 -> 21900 | E68: =60*365 -> 21900 | F68: =60*365 -> 21900 | G68: =60*365 -> 21900 | H68: =60*365 -> 21900 | I68: =60*365 -> 21900 | J68: =60*365 -> 21900 | K68: =60*365 -> 21900 | ... Z68: =60*365 -> 21900
C69: Electricity amount | D69: =(D11/100)*D68 -> 2540.4 | E69: =D69 -> 2540.4 | F69: =E69 -> 2540.4 | G69: =F69 -> 2540.4 | H69: =G69 -> 2540.4 | I69: =H69 -> 2540.4 | J69: =I69 -> 2540.4 | K69: =J69 -> 2540.4 | L69: =K69 -> 2540.4 | ... Z69: =Y69 -> 2540.4
C70: Electricity Cost | D70: =D69*D12 -> 2032.32 | E70: =D70 -> 2032.32 | F70: =E70 -> 2032.32 | G70: =F70 -> 2032.32 | H70: =G70 -> 2032.32 | I70: =H70 -> 2032.32 | J70: =I70 -> 2032.32 | K70: =J70 -> 2032.32 | L70: =K70 -> 2032.32 | ... Z70: =Y70 -> 2032.32
C71: Discounted Electricity Cost | D71: =D70/(1+$D$13)^(D67-2019) -> 2032.32 | E71: =E70/(1+$D$13)^(E67-2019) -> 1973.1262 | F71: =F70/(1+$D$13)^(F67-2019) -> 1915.6565 | G71: =G70/(1+$D$13)^(G67-2019) -> 1859.8607 | H71: =H70/(1+$D$13)^(H67-2019) -> 1805.69 | I71: =I70/(1+$D$13)^(I67-2019) -> 1753.0971 | J71: =J70/(1+$D$13)^(J67-2019) -> 1702.036 | K71: =K70/(1+$D$13)^(K67-2019) -> 1652.4621 | ... Z71: =Z70/(1+$D$13)^(Z67-2019) -> 1060.6526
C72: Electricity Cost NPV | D72: =SUM(D71:K71) -> 14694.249 | E72: =SUM(E71:L71) -> 14266.261 | F72: =SUM(F71:M71) -> 13850.739 | G72: =SUM(G71:N71) -> 13447.319 | H72: =SUM(H71:O71) -> 13055.65 | I72: =SUM(I71:P71) -> 12675.388 | J72: =SUM(J71:Q71) -> 12306.202 | K72: =SUM(K71:R71) -> 11947.769 | ... S72: =SUM(S71:Z71) -> 9431.6791 | T72: =SUM(T41:AA41) -> 0 | U72: =SUM(U41:AB41) -> 0 | V72: =SUM(V41:AC41) -> 0 | W72: =SUM(W41:AD41) -> 0 | X72: =SUM(X41:AE41) -> 0 | Y72: =SUM(Y41:AF41) -> 0 | Z72: =SUM(Z41:AG41) -> 0
C74: Maintenance Cost | D74: =400 -> 400
C78: Insurance cost | D78: 3500 | E78: 3500 | F78: 3500 | G78: 3500 | H78: 3500 | I78: 3500 | J78: 3500 | K78: 3500 | L78: 3500 | M78: 3500 | N78: 3500 | O78: 3500 | P78: 3500 | Q78: 3500 | R78: 3500 | S78: 3500 | T78: 3500 | U78: 3500 | V78: 3500 | W78: 3500 | X78: 3500 | Y78: 3500 | Z78: 3500
C79: Discounted Insurance Cost | D79: =D78/(1+$D$13)^(D67-2019) -> 3500 | E79: =E78/(1+$D$13)^(E67-2019) -> 3398.0583 | F79: =F78/(1+$D$13)^(F67-2019) -> 3299.0857 | G79: =G78/(1+$D$13)^(G67-2019) -> 3202.9958 | H79: =H78/(1+$D$13)^(H67-2019) -> 3109.7047 | I79: =I78/(1+$D$13)^(I67-2019) -> 3019.1307 | J79: =J78/(1+$D$13)^(J67-2019) -> 2931.1949 | K79: =K78/(1+$D$13)^(K67-2019) -> 2845.8203 | ... Z79: =Z78/(1+$D$13)^(Z67-2019) -> 1826.6238
C80: Insurance cost NPV | D80: =SUM(D79:K79) -> 25305.99 | E80: =NPV(0.03,E79:L79) -> 21657.072 | F80: =NPV(0.03,F79:M79) -> 21026.284 | G80: =NPV(0.03,G79:N79) -> 20413.868 | H80: =NPV(0.03,H79:O79) -> 19819.289 | I80: =NPV(0.03,I79:P79) -> 19242.028 | J80: =NPV(0.03,J79:Q79) -> 18681.581 | K80: =NPV(0.03,K79:R79) -> 18137.457 | L80: =NPV(0.03,L79:S79) -> 17609.182 | ... O80: =NPV(0.03,O79:V79) -> 16114.896
C83: Annual range | D83: =60*365 -> 21900 | E83: =60*365 -> 21900 | F83: =60*365 -> 21900 | G83: =60*365 -> 21900 | H83: =60*365 -> 21900 | I83: =60*365 -> 21900 | J83: =60*365 -> 21900 | K83: =60*365 -> 21900 | ... Z83: =60*365 -> 21900
C84: Oil amount | D84: =(D27/100)*D83 -> 1160.7 | E84: =(E27/100)*E83 -> 1160.7 | F84: =(F27/100)*F83 -> 1160.7 | G84: =(G27/100)*G83 -> 1160.7 | H84: =(H27/100)*H83 -> 1160.7 | I84: =(I27/100)*I83 -> 1160.7 | J84: =(J27/100)*J83 -> 1160.7 | K84: =(K27/100)*K83 -> 1160.7 | ... O84: =(O27/100)*O83 -> 1160.7 | P84: =O84 -> 1160.7 | Q84: =P84 -> 1160.7 | R84: =Q84 -> 1160.7 | S84: =R84 -> 1160.7 | T84: =S84 -> 1160.7 | U84: =T84 -> 1160.7 | V84: =U84 -> 1160.7 | W84: =V84 -> 1160.7 | ... Z84: =Y84 -> 1160.7
C85: Oil cost | D85: =D84*$D$28 -> 8124.9 | E85: =E84*$D$28 -> 8124.9 | F85: =F84*$D$28 -> 8124.9 | G85: =G84*$D$28 -> 8124.9 | H85: =H84*$D$28 -> 8124.9 | I85: =I84*$D$28 -> 8124.9 | J85: =J84*$D$28 -> 8124.9 | K85: =K84*$D$28 -> 8124.9 | ... Z85: =Z84*$D$28 -> 8124.9
D86: =D85/(1+$D$29)^(D67-2019) -> 8124.9 | E86: =E85/(1+$D$29)^(E67-2019) -> 7888.2524 | F86: =F85/(1+$D$29)^(F67-2019) -> 7658.4975 | G86: =G85/(1+$D$29)^(G67-2019) -> 7435.4345 | H86: =H85/(1+$D$29)^(H67-2019) -> 7218.8684 | I86: =I85/(1+$D$29)^(I67-2019) -> 7008.6101 | J86: =J85/(1+$D$29)^(J67-2019) -> 6804.4758 | K86: =K85/(1+$D$29)^(K67-2019) -> 6606.2872 | ... Z86: =Z85/(1+$D$29)^(Z67-2019) -> 4240.3244
D87: =SUM(D86:K86) -> 58745.326 | E87: =SUM(E86:L86) -> 57034.297 | F87: =SUM(F86:M86) -> 55373.104 | G87: =SUM(G86:N86) -> 53760.295 | H87: =SUM(H86:O86) -> 52194.461 | I87: =SUM(I86:P86) -> 50674.234 | J87: =SUM(J86:Q86) -> 49198.286 | K87: =SUM(K86:R86) -> 47765.326 | ... O87: =SUM(O86:V86) -> 42438.873

Sheet A00 TCO (80)
C4: A00 Class BEV Sample Avg
D5: 2019 | E5: 2020 | F5: 2021 | G5: 2022 | H5: 2023 | I5: 2024 | J5: 2025 | K5: 2026 | L5: 2027 | M5: 2028 | N5: 2029 | O5: 2030
C6: Retail Price | D6: 63475 | E6: 58403 | F6: 53818.2 | G6: 49671.88 | H6: 45920.192 | I6: 42523.673 | J6: 39446.806 | K6: 36657.625 | L6: 34127.362 | M6: 31830.126 | N6: 29742.614 | O6: 27843.852
C7: Purchase Tax | D7: 0 | E7: 0 | F7: =F6*0.1 -> 5381.82 | G7: =G6*0.1 -> 4967.188 | H7: =H6*0.1 -> 4592.0192 | I7: =I6*0.1 -> 4252.3673 | J7: =J6*0.1 -> 3944.6806 | K7: =K6*0.1 -> 3665.7625 | L7: =L6*0.1 -> 3412.7362 | M7: =M6*0.1 -> 3183.0126 | ... O7: =O6*0.1 -> 2784.3852
C8: Consumer Final Price | D8: =D6+D7 -> 63475 | E8: =E6+E7 -> 58403 | F8: =F6+F7 -> 59200.02 | G8: =G6+G7 -> 54639.068 | H8: =H6+H7 -> 50512.211 | I8: =I6+I7 -> 46776.04 | J8: =J6+J7 -> 43391.486 | K8: =K6+K7 -> 40323.387 | ... O8: =O6+O7 -> 30628.237
C9: Range/Day (km) | D9: 80 | E9: 80 | F9: 80 | G9: 80 | H9: 80 | I9: 80 | J9: 80 | K9: 80 | L9: 80 | M9: 80 | N9: 80 | O9: 80
C10: Years of Usage | D10: 8 | E10: 8 | F10: 8 | G10: 8 | H10: 8 | I10: 8 | J10: 8 | K10: 8 | L10: 8 | M10: 8 | N10: 8 | O10: 8
C11: Electricity/hundred KM (Kwh) | D11: 11.6 | E11: 11.6 | F11: 11.6 | G11: 11.6 | H11: 11.6 | I11: 11.6 | J11: 11.6 | K11: 11.6 | L11: 11.6 | M11: 11.6 | N11: 11.6 | O11: 11.6
C12: Electricity Price (RMB/Kwh) | D12: 0.8 | E12: 0.8 | F12: 0.8 | G12: 0.8 | H12: 0.8 | I12: 0.8 | J12: 0.8 | K12: 0.8 | L12: 0.8 | M12: 0.8 | N12: 0.8 | O12: 0.8
C13: Discount Rate | D13: 0.03 | E13: 0.03 | F13: 0.03 | G13: 0.03 | H13: 0.03 | I13: 0.03 | J13: 0.03 | K13: 0.03 | L13: 0.03 | M13: 0.03 | N13: 0.03 | O13: 0.03
C14: NPV Energy Cost | D14: 19592.332 | E14: 19021.681 | F14: 18467.652 | G14: 17929.759 | H14: 17407.533 | I14: 16900.517 | J14: 16408.269 | K14: 15930.358 | L14: 15466.367 | M14: 15015.891 | N14: 14578.535 | O14: 14153.917 | P14: 13741.667 | Q14: 13341.424 | R14: 12952.839 | S14: 12575.572
C15: NPV Maintenance Cost | D15: =11*300+12*100 -> 4500 | E15: =D15*(1-$D$13) -> 4365 | F15: =E15*(1-$D$13) -> 4234.05 | G15: =F15*(1-$D$13) -> 4107.0285 | H15: =G15*(1-$D$13) -> 3983.8176 | I15: =H15*(1-$D$13) -> 3864.3031 | J15: =I15*(1-$D$13) -> 3748.374 | K15: =J15*(1-$D$13) -> 3635.9228 | L15: =K15*(1-$D$13) -> 3526.8451 | ... O15: =N15*(1-$D$13) -> 3218.8563
C16: NPV Insurance Cost | D16: 25305.99 | E16: 21657.072 | F16: 21026.284 | G16: 20413.868 | H16: 19819.289 | I16: 19242.028 | J16: 18681.581 | K16: 18137.457 | L16: 17609.182 | M16: 17096.293 | N16: 16598.343 | O16: 16114.896
C17: NPV Vehicle and Vessel Tax | D17: 0 | E17: 0 | F17: 0 | G17: 0 | H17: 0 | I17: 0 | J17: 0 | K17: 0 | L17: 0 | M17: 0 | N17: 0 | O17: 0
C18: Residual Value after Depreciation | D18: =0.15*D6 -> 9521.25 | E18: =0.15*E6 -> 8760.45 | F18: =0.15*F6 -> 8072.73 | G18: =0.15*G6 -> 7450.782 | H18: =0.15*H6 -> 6888.0288 | I18: =0.15*I6 -> 6378.5509 | J18: =0.15*J6 -> 5917.0208 | K18: =0.15*K6 -> 5498.6437 | ... O18: =0.15*O6 -> 4176.5778
C19: TCO | D19: =D8+D14+D15+D16+D17-D18 -> 103352.07 | E19: =E8+E14+E15+E16+E17-E18 -> 94686.304 | F19: =F8+F14+F15+F16+F17-F18 -> 94855.276 | G19: =G8+G14+G15+G16+G17-G18 -> 89638.941 | H19: =H8+H14+H15+H16+H17-H18 -> 84834.822 | I19: =I8+I14+I15+I16+I17-I18 -> 80404.338 | J19: =J8+J14+J15+J16+J17-J18 -> 76312.689 | K19: =K8+K14+K15+K16+K17-K18 -> 72528.482 | ... O19: =O8+O14+O15+O16+O17-O18 -> 59939.329
C22: A00 Class ICEV Sample Avg
D23: 2019 | E23: 2020 | F23: 2021 | G23: 2022 | H23: 2023 | I23: 2024 | J23: 2025 | K23: 2026 | L23: 2027 | M23: 2028 | N23: 2029 | O23: 2030
C24: Retail Price | D24: 51066 | E24: 51366 | F24: 51672 | G24: 51984.12 | H24: 52302.482 | I24: 52627.212 | J24: 52958.436 | K24: 53296.285 | L24: 53640.891 | M24: 53992.389 | N24: 54350.916 | O24: 54716.615
C25: Purchase Tax | D25: 5500 | E25: 5530 | F25: 5560.6 | G25: 5591.812 | H25: 5623.6482 | I25: 5656.1212 | J25: 5689.2436 | K25: 5723.0285 | L25: 5757.4891 | M25: 5792.6389 | N25: 5828.4916 | O25: 5865.0615
C26: Consumer Final Price | D26: 60500 | E26: 60830 | F26: 61166.6 | G26: 61509.932 | H26: 61860.131 | I26: 62217.333 | J26: 62581.68 | K26: 62953.314 | L26: 63332.38 | M26: 63719.027 | N26: 64113.408 | O26: 64515.676
C27: Range/Day (km) | D27: 80 | E27: =D27 -> 80 | F27: =E27 -> 80 | G27: =F27 -> 80 | H27: =G27 -> 80 | I27: =H27 -> 80 | J27: =I27 -> 80 | K27: =J27 -> 80 | L27: =K27 -> 80 | ... O27: =N27 -> 80
C28: Years of Usage | D28: 8 | E28: 8 | F28: 8 | G28: 8 | H28: 8 | I28: 8 | J28: 8 | K28: 8 | L28: 8 | M28: 8 | N28: 8 | O28: 8
C29: Oil/hundred KM (L/100km) | D29: 5.3 | E29: 5.3 | F29: 5.3 | G29: 5.3 | H29: 5.3 | I29: 5.3 | J29: 5.3 | K29: 5.3 | L29: 5.3 | M29: 5.3 | N29: 5.3 | O29: 5.3
C30: Oil Price (RMB/Litre) | D30: 7 | E30: 7 | F30: 7 | G30: 7 | H30: 7 | I30: 7 | J30: 7 | K30: 7 | L30: 7 | M30: 7 | N30: 7 | O30: 7
C31: Discount Rate | D31: 0.03 | E31: 0.03 | F31: 0.03 | G31: 0.03 | H31: 0.03 | I31: 0.03 | J31: 0.03 | K31: 0.03 | L31: 0.03 | M31: 0.03 | N31: 0.03 | O31: 0.03
C32: NPV Energy Cost | D32: 78327.101 | E32: 76045.729 | F32: 73830.805 | G32: 71680.393 | H32: 69592.615 | I32: 67565.646 | J32: 65597.714 | K32: 63687.101 | L32: 61832.137 | M32: 60031.201 | N32: 58282.719 | O32: 56585.165
C33: NPV Maintenance Cost | D33: =23*1200+23*600 -> 41400 | E33: =D33*(1-$D$31) -> 40158 | F33: =E33*(1-$D$31) -> 38953.26 | G33: =F33*(1-$D$31) -> 37784.662 | H33: =G33*(1-$D$31) -> 36651.122 | I33: =H33*(1-$D$31) -> 35551.589 | J33: =I33*(1-$D$31) -> 34485.041 | K33: =J33*(1-$D$31) -> 33450.49 | L33: =K33*(1-$D$31) -> 32446.975 | ... O33: =N33*(1-$D$31) -> 29613.478
C34: NPV Insurance Cost | D34: 21690.849 | E34: 21059.077 | F34: 20445.705 | G34: 19850.199 | H34: 19272.038 | I34: 18710.717 | J34: 18165.744 | K34: 17636.645 | L34: 17122.956 | M34: 16624.23 | N34: 16140.029 | O34: 15669.931
C35: NPV Vehicle and Vessel Tax | D35: 360 | E35: =D35*(1-$D$31) -> 349.2 | F35: =E35*(1-$D$31) -> 338.724 | G35: =F35*(1-$D$31) -> 328.56228 | H35: =G35*(1-$D$31) -> 318.70541 | I35: =H35*(1-$D$31) -> 309.14425 | J35: =I35*(1-$D$31) -> 299.86992 | K35: =J35*(1-$D$31) -> 290.87382 | L35: =K35*(1-$D$31) -> 282.14761 | ... O35: =N35*(1-$D$31) -> 257.50851
C36: Residual Value after Depreciation | D36: =0.35*D24 -> 17873.1 | E36: =0.35*E24 -> 17978.1 | F36: =0.35*F24 -> 18085.2 | G36: =0.35*G24 -> 18194.442 | H36: =0.35*H24 -> 18305.869 | I36: =0.35*I24 -> 18419.524 | J36: =0.35*J24 -> 18535.453 | K36: =0.35*K24 -> 18653.7 | ... O36: =0.35*O24 -> 19150.815
C37: TCO | D37: =D26+D32+D33+D34-D36 -> 184044.85 | E37: =E26+E32+E33+E34-E36 -> 180114.71 | F37: =F26+F32+F33+F34-F36 -> 176311.17 | G37: =G26+G32+G33+G34-G36 -> 172630.75 | H37: =H26+H32+H33+H34-H36 -> 169070.04 | I37: =I26+I32+I33+I34-I36 -> 165625.76 | J37: =J26+J32+J33+J34-J36 -> 162294.73 | K37: =K26+K32+K33+K34-K36 -> 159073.85 | ... O37: =O26+O32+O33+O34-O36 -> 147233.43
D38: 2019 | E38: 2020 | F38: 2021 | G38: 2022 | H38: 2023 | I38: 2024 | J38: 2025 | K38: 2026 | L38: 2027 | M38: 2028 | N38: 2029 | O38: 2030
C39: A00 (80km/day) | D39: =D19-D37 -> -80692.778 | E39: =E19-E37 -> -85428.402 | F39: =F19-F37 -> -81455.895 | G39: =G19-G37 -> -82991.804 | H39: =H19-H37 -> -84235.215 | I39: =I19-I37 -> -85221.422 | J39: =J19-J37 -> -85982.037 | K39: =K19-K37 -> -86545.368 | ... O39: =O19-O37 -> -87294.105
D43: 2019 | E43: 2020 | F43: 2021 | G43: 2022 | H43: 2023 | I43: 2024 | J43: 2025 | K43: 2026 | L43: 2027 | M43: 2028 | N43: 2029 | O43: 2030
C44: A00 (10km/day) | D44: 3700.1453 | E44: -3522.3602 | F44: -1963.4357 | G44: -5841.7896 | H44: -9358.6057 | I44: -12551.212 | J44: -15453.197 | K44: -18094.784 | L44: -20503.169 | M44: -22702.823 | N44: -24715.767 | O44: -26561.818
C45: A00 (20km/day) | D45: -8441.701 | E45: -15306.366 | F45: -13400.15 | G45: -16941.449 | H45: -20131.146 | I45: -23006.276 | J45: -25600.143 | K45: -27942.694 | L45: -30060.858 | M45: -31978.846 | N45: -33718.426 | O45: -35299.17
C46: A00 (40km/day) | D46: -32725.393 | E46: -38874.378 | F46: -36273.578 | G46: -39140.769 | H46: -41676.228 | I46: -43916.405 | J46: -45894.036 | K46: -47638.515 | L46: -49176.237 | M46: -50530.892 | N46: -51723.744 | O46: -52773.876
C47: A00 (60km/day) | D47: -57009.086 | E47: -62442.39 | F47: -59147.007 | G47: -61340.088 | H47: -63221.309 | I47: -64826.534 | J47: -66187.928 | K47: -67334.336 | L47: -68291.615 | M47: -69082.937 | N47: -69729.062 | O47: -70248.581
C48: A00 (80km/day) | D48: -80692.778 | E48: -85428.402 | F48: -81455.895 | G48: -82991.804 | H48: -84235.215 | I48: -85221.422 | J48: -85982.037 | K48: -86545.368 | L48: -86936.748 | M48: -87178.844 | N48: -87291.925 | O48: -87294.105
D69: 2019 | E69: 2020 | F69: 2021 | G69: 2022 | H69: 2023 | I69: 2024 | J69: 2025 | K69: 2026 | L69: 2027 | M69: 2028 | N69: 2029 | O69: 2030 | P69: 2031 | Q69: 2032 | R69: 2033 | S69: 2034 | T69: 2035 | U69: 2036 | V69: 2037 | W69: 2038 | X69: 2039 | Y69: 2040 | Z69: 2041
C70: Annual range | D70: =80*365 -> 29200 | E70: =80*365 -> 29200 | F70: =80*365 -> 29200 | G70: =80*365 -> 29200 | H70: =80*365 -> 29200 | I70: =80*365 -> 29200 | J70: =80*365 -> 29200 | K70: =80*365 -> 29200 | ... Z70: =80*365 -> 29200
C71: Electricity amount | D71: =(D11/100)*D70 -> 3387.2 | E71: =D71 -> 3387.2 | F71: =E71 -> 3387.2 | G71: =F71 -> 3387.2 | H71: =G71 -> 3387.2 | I71: =H71 -> 3387.2 | J71: =I71 -> 3387.2 | K71: =J71 -> 3387.2 | L71: =K71 -> 3387.2 | ... Z71: =Y71 -> 3387.2
C72: Electricity Cost | D72: =D71*D12 -> 2709.76 | E72: =D72 -> 2709.76 | F72: =E72 -> 2709.76 | G72: =F72 -> 2709.76 | H72: =G72 -> 2709.76 | I72: =H72 -> 2709.76 | J72: =I72 -> 2709.76 | K72: =J72 -> 2709.76 | L72: =K72 -> 2709.76 | ... Z72: =Y72 -> 2709.76
C73: Discounted Electricity Cost | D73: =D72/(1+$D$13)^(D69-2019) -> 2709.76 | E73: =E72/(1+$D$13)^(E69-2019) -> 2630.835 | F73: =F72/(1+$D$13)^(F69-2019) -> 2554.2087 | G73: =G72/(1+$D$13)^(G69-2019) -> 2479.8143 | H73: =H72/(1+$D$13)^(H69-2019) -> 2407.5867 | I73: =I72/(1+$D$13)^(I69-2019) -> 2337.4628 | J73: =J72/(1+$D$13)^(J69-2019) -> 2269.3813 | K73: =K72/(1+$D$13)^(K69-2019) -> 2203.2829 | ... Z73: =Z72/(1+$D$13)^(Z69-2019) -> 1414.2034
C74: Electricity Cost NPV | D74: =SUM(D73:K73) -> 19592.332 | E74: =SUM(E73:L73) -> 19021.681 | F74: =SUM(F73:M73) -> 18467.652 | G74: =SUM(G73:N73) -> 17929.759 | H74: =SUM(H73:O73) -> 17407.533 | I74: =SUM(I73:P73) -> 16900.517 | J74: =SUM(J73:Q73) -> 16408.269 | K74: =SUM(K73:R73) -> 15930.358 | ... S74: =SUM(S73:Z73) -> 12575.572 | T74: =SUM(T43:AA43) -> 0 | U74: =SUM(U43:AB43) -> 0 | V74: =SUM(V43:AC43) -> 0 | W74: =SUM(W43:AD43) -> 0 | X74: =SUM(X43:AE43) -> 0 | Y74: =SUM(Y43:AF43) -> 0 | Z74: =SUM(Z43:AG43) -> 0
C76: Maintenance Cost | D76: =400 -> 400
